Workbook
Name B_KQKT: TTDN!$AR$41:$AS$50
Name Bang_CDSPS: CDSPS!$C$15:$J$434
Name Bang_CDSPSNT: CDSPS_NT!$C$15:$J$432
Name BangKe_BR: TTDN!$AZ$1:$BJ$16
Name BangKe_MV: TTDN!$AZ$19:$BK$34
Name BangVat: TTDN!$CX$3:$DJ$11
Name BR_1: BR!$A$7
Name BR_KT_1: BR!$T$7
Name BR_THop: BR!$Z$8:$AA$19
Name CDSPS_1: CDSPS!$C$14
Name CDSPS_CKC: CDSPS!$J$15:$J$433
Name CDSPS_CKC59: CDSPS!$J$364:$J$433
Name CDSPS_CKN: CDSPS!$I$15:$I$433
Name CDSPS_CKN59: CDSPS!$I$364:$I$433
Name CDSPS_DKC: CDSPS!$F$15:$F$433
Name CDSPS_DKN: CDSPS!$E$15:$E$433
Name CDSPS_N111: CDSPS!$E$16
Name CDSPS_NT_1: CDSPS_NT!$C$14
Name CDSPS_NT_TC: CDSPS_NT!$D$433
Name CDSPS_PSC: CDSPS!$H$15:$H$433
Name CDSPS_PSN: CDSPS!$G$15:$G$433
Name CDSPS_TC: CDSPS!$D$435
Name CDSPS_TK: CDSPS!$C$15:$C$433
Name CDSPSNT_CKC: TTDN!$AN$37
Name CDSPSNT_CKN: TTDN!$AN$36
Name CDSPSNT_DKC: TTDN!$AN$33
Name CDSPSNT_DKN: TTDN!$AN$32
Name CDSPSNT_PSC: TTDN!$AN$35
Name CDSPSNT_PSN: TTDN!$AN$34
Name CDSPSNT_TK: TTDN!$AN$31
Name CN_CongPS: CN_CTiet!$C$21
Name CN_DongD: CN_CTiet!$C$16
Name CNPThu_1: SDDK_CN!$B$7
Name CNPThu_KT1: SDDK_CN!$G$7
Name CNPTra_1: SDDK_CN!$L$7
Name CNPTra_KT1: SDDK_CN!$Q$7
Name CNTH_1: CN_TH!$B$12
Name CNTH_TC: CN_TH!$C$15
Name DATA_CT: DATA_HDDT!$AI$1:$AS$150
Name DATA_HD: DATA_HDDT!$L$1:$AG$150
Name DATA_NM: DATA_HDDT!$A$1:$J$150
Name DC3738_1: DC_3738!$A$5
Name DC3738_TuDongHD: DC_3738!$L$2
Name DCQT_VatQ: GV!$AA$8:$AD$11
Name DCQT_VatT: GV!$U$8:$X$19
Name DCT_Ban: LuuY!$H$4
Name DCT_Mua: LuuY!$H$22
Name DK_C33311: CDSPS_NT!$J$287
Name DK_N133: CDSPS_NT!$I$129
Name DK_N33311: CDSPS_NT!$I$287
Name DK_N4212: CDSPS_NT!$I$361
Name GPAccTT99: Main!$D$1
Name GTGT_014B: GTGT!$V$24:$V$36
Name GTGT_32b: GTGT!$K$19
Name GTGT_34a: GTGT!$L$19
Name GTGT_DCVatQ: GTGT!$O$7:$P$10
Name GTGT_DCVatT: GTGT!$K$7:$L$18
Name GTGT_DK: GTGT!$H$23
Name GTGT_PBThue: GTGT!$O$24:$O$34
Name GTrinh_152: Giai_Trinh!$B$5

Sheet Main
A1: 29 | B1: 46294.564 | D1: PHẦN MỀM KẾ TOÁN GPAcc | Theo Thông tư 99/2025/TT-BTC | P1: ="Kỳ kế toán · Năm "&$A$3 -> Kỳ kế toán · Năm 2026
A2: 9
A3: 2026
A4: 19
A5: 8
A6: BÍNH NGỌ | D6: GPAcc
A7: Ất Mùi | M7: ="THÁNG "&TEXT($A$2,"00")&" · "&$A$3 -> THÁNG 09 · 2026
M9: =$A$1 -> 29
D12: Phần mềm kế toán doanh nghiệp trên Microsoft Excel
N23: =CHOOSE(WEEKDAY($B$1),"CHỦ NHẬT","THỨ HAI","THỨ BA","THỨ TƯ","THỨ NĂM","THỨ SÁU","THỨ BẢY") -> THỨ BA
D27: =IF(LEN(KB_CTy)=0,"",KB_CTy)
D28: ="Mã số thuế: "&IF(LEN(KB_MST)=0,"",KB_MST) -> Mã số thuế: | M28: ÂM LỊCH
D29: ="Địa chỉ: "&IF(LEN(KB_DC)=0,"",KB_DC) -> Địa chỉ: | M29: =$A$4&" tháng "&$A$5 -> 19 tháng 8 | Q29: ="Năm "&$A$6 -> Năm BÍNH NGỌ

Sheet VA_BOCUC
A1: Mã việc | B1: Loại | C1: Sheet | D1: Vùng | E1: Giá trị | F1: Tham số | G1: Điều kiện | H1: Ghi chú | I1: Tắt | K1: CÁCH DÙNG BẢNG NÀY
A2: VD_01 | B2: CONGTHUC | C2: PBKH | D2: I4 | E2: =SUBTOTAL(9,I9:I2000) | G2: KHAC | H2: ví dụ: đặt lại công thức cộng tổng | I2: x
A3: VD_02 | B3: DINHDANG | C3: PBKH | D3: I4 | F3: so=#,##0;font=Segoe UI;co=10;dam=1;chu=#174F8C;canh=phai | G3: KHAC | H3: ví dụ: định dạng ô vừa đặt | I3: x | K3: Mỗi DÒNG là một việc sửa bố cục. Sửa bảng này trong gói MauBieu.xlsx rồi phát hành
A4: VD_03 | B4: NUT | C4: RapMa | E4: RapMa_Auto | F4: ten=NutVD_Thu;chu=Thử Nút;l=700;t=2;w=110;h=22;nen=#FFFFFF;vien=#2F6EAD;chumau=#1F2937 | G4: KHAC | H4: ví dụ: thêm một nút lệnh | I4: x | K4: PhatHanh.ps1 -Ver <yymmdd> -TangSchema → khách bấm «Cập Nhật Mẫu Biểu» rồi
A5: VA260921_11 | B5: CONGTHUC | C5: KQKD | D5: J16 | E5: =IFERROR(+H16/H13,"") | G5: KHAC | H5: Boc IFERROR: file chua co so lieu thi ty le chia ra #DIV/0! | K5: «Nâng Cấp Bố Cục» là xong. KHÔNG cần phát hành vbaProject.bin, không cần viết code.
A6: VA260921_12 | B6: CONGTHUC | C6: KQKD | D6: K16 | E6: =IFERROR(+I16/I13,"") | G6: KHAC | H6: Boc IFERROR: file chua co so lieu thi ty le chia ra #DIV/0!
A7: VA260921_13 | B7: CONGTHUC | C7: KQKD | D7: J28 | E7: =IFERROR(H28/H15,"") | G7: KHAC | H7: Boc IFERROR: file chua co so lieu thi ty le chia ra #DIV/0! | K7: CỘT B — Loại việc:
A8: VA260921_14 | B8: CONGTHUC | C8: KQKD | D8: K28 | E8: =IFERROR(I28/I15,"") | G8: KHAC | H8: Boc IFERROR: file chua co so lieu thi ty le chia ra #DIV/0! | K8: CONGTHUC đặt công thức cho ô/vùng (cột E là công thức, ví dụ =SUBTOTAL(9,I9:I2000))
A9: VA26093001_01 | B9: CONGTHUC | C9: TMinh | D9: M214 | E9: =+VLOOKUP(M210,Bang_CDSPS,5,0) | G9: KHAC | H9: TM muc 9: TSCD huu hinh mua trong nam = PS No TK 211x | K9: GIATRI đặt giá trị / chữ cho ô/vùng
A10: VA26093001_02 | B10: CONGTHUC | C10: TMinh | D10: Q214 | E10: =+VLOOKUP(Q210,Bang_CDSPS,5,0) | G10: KHAC | H10: TM muc 9: TSCD huu hinh mua trong nam = PS No TK 211x | K10: DINHDANG định dạng ô/vùng (tham số ở cột F)
A11: VA26093001_03 | B11: CONGTHUC | C11: TMinh | D11: U214 | E11: =+VLOOKUP(U210,Bang_CDSPS,5,0) | G11: KHAC | H11: TM muc 9: TSCD huu hinh mua trong nam = PS No TK 211x | K11: NAME thêm / trỏ lại Name toàn cục (cột D = tên Name, cột E = =Sheet!$A$1)
A12: VA26093001_04 | B12: CONGTHUC | C12: TMinh | D12: Y214 | E12: =+VLOOKUP(Y210,Bang_CDSPS,5,0) | G12: KHAC | H12: TM muc 9: TSCD huu hinh mua trong nam = PS No TK 211x | K12: VALIDATION danh sách chọn (cột E: các mục cách nhau dấu | )
A13: VA26093001_05 | B13: CONGTHUC | C13: TMinh | D13: AC214 | E13: =+VLOOKUP(AC210,Bang_CDSPS,5,0) | G13: KHAC | H13: TM muc 9: TSCD huu hinh mua trong nam = PS No TK 211x | K13: NUT thêm nút lệnh (cột E = tên macro, cột F: ten= chu= l= t= w= h= nen= vien= chumau=)
A14: VA26093001_06 | B14: CONGTHUC | C14: TMinh | D14: M222 | E14: =+SUMIF(Bang_TSCD!$B$16:$B$5000,M210,Bang_TSCD!$R$16:$R$5000) | G14: KHAC | H14: TM muc 9: hao mon luy ke dau nam lay tu Bang_TSCD | K14: HIENSHEET cột E = hien | an | anhan
A15: VA26093001_07 | B15: CONGTHUC | C15: TMinh | D15: Q222 | E15: =+SUMIF(Bang_TSCD!$B$16:$B$5000,Q210,Bang_TSCD!$R$16:$R$5000) | G15: KHAC | H15: TM muc 9: hao mon luy ke dau nam lay tu Bang_TSCD | K15: VUNGIN cột D = vùng in
A16: VA26093001_08 | B16: CONGTHUC | C16: TMinh | D16: U222 | E16: =+SUMIF(Bang_TSCD!$B$16:$B$5000,U210,Bang_TSCD!$R$16:$R$5000) | G16: KHAC | H16: TM muc 9: hao mon luy ke dau nam lay tu Bang_TSCD
A17: VA26093001_09 | B17: CONGTHUC | C17: TMinh | D17: Y222 | E17: =+SUMIF(Bang_TSCD!$B$16:$B$5000,Y210,Bang_TSCD!$R$16:$R$5000) | G17: KHAC | H17: TM muc 9: hao mon luy ke dau nam lay tu Bang_TSCD | K17: CỘT F — tham số DINHDANG (chỉ ghi cái cần đổi, cách nhau dấu chấm phẩy):
A18: VA26093001_10 | B18: CONGTHUC | C18: TMinh | D18: AC222 | E18: =+SUMIF(Bang_TSCD!$B$16:$B$5000,AC210,Bang_TSCD!$R$16:$R$5000) | G18: KHAC | H18: TM muc 9: hao mon luy ke dau nam lay tu Bang_TSCD | K18: so=#,##0 font=Segoe UI co=10 dam=1 nghieng=0 chu=#174F8C nen=#DCEBF7
A19: VA26093001_11 | B19: CONGTHUC | C19: TMinh | D19: M223 | E19: =+SUMIF(Bang_TSCD!$B$16:$B$5000,M210,Bang_TSCD!$S$16:$S$5000) | G19: KHAC | H19: TM muc 9: khau hao trong nam lay tu Bang_TSCD | K19: canh=trai|giua|phai doc=tren|giua|duoi wrap=0 rong=12 cao=16
A20: VA26093001_12 | B20: CONGTHUC | C20: TMinh | D20: Q223 | E20: =+SUMIF(Bang_TSCD!$B$16:$B$5000,Q210,Bang_TSCD!$S$16:$S$5000) | G20: KHAC | H20: TM muc 9: khau hao trong nam lay tu Bang_TSCD | K20: vien=mong|dam|khong vienmau=#B9D3E8 (nen=khong là bỏ màu nền)
A21: VA26093001_13 | B21: CONGTHUC | C21: TMinh | D21: U223 | E21: =+SUMIF(Bang_TSCD!$B$16:$B$5000,U210,Bang_TSCD!$S$16:$S$5000) | G21: KHAC | H21: TM muc 9: khau hao trong nam lay tu Bang_TSCD
A22: VA26093001_14 | B22: CONGTHUC | C22: TMinh | D22: Y223 | E22: =+SUMIF(Bang_TSCD!$B$16:$B$5000,Y210,Bang_TSCD!$S$16:$S$5000) | G22: KHAC | H22: TM muc 9: khau hao trong nam lay tu Bang_TSCD | K22: CỘT G — Điều kiện:
A23: VA26093001_15 | B23: CONGTHUC | C23: TMinh | D23: AC223 | E23: =+SUMIF(Bang_TSCD!$B$16:$B$5000,AC210,Bang_TSCD!$S$16:$S$5000) | G23: KHAC | H23: TM muc 9: khau hao trong nam lay tu Bang_TSCD | K23: KHAC (mặc định) chỉ làm khi ô đang KHÁC giá trị đích → chạy lại bao nhiêu lần cũng không hại
A24: VA26093001_16 | B24: CONGTHUC | C24: TMinh | D24: K562 | E24: =+VLOOKUP(K559,Bang_CDSPSNT,4,0)/1000 | G24: KHAC | H24: TM muc 27: so du dau nam truoc lay tu CDSPS nam truoc | K24: TRONG chỉ làm khi ô đang trống (không đè cái khách đã nhập)
A25: VA26093001_17 | B25: CONGTHUC | C25: TMinh | D25: N562 | E25: =+VLOOKUP(N559,Bang_CDSPSNT,4,0)/1000-VLOOKUP(N559,Bang_CDSPSNT,3,0)/1000 | G25: KHAC | H25: TM muc 27: so du dau nam truoc lay tu CDSPS nam truoc | K25: LUON áp mỗi lần bấm Nâng Cấp Bố Cục, KHÔNG tính vào lời nhắc lúc mở file
A26: VA26093001_18 | B26: CONGTHUC | C26: TMinh | D26: Q562 | E26: =+VLOOKUP(Q559,Bang_CDSPSNT,4,0)/1000 | G26: KHAC | H26: TM muc 27: so du dau nam truoc lay tu CDSPS nam truoc
A27: VA26093001_19 | B27: CONGTHUC | C27: TMinh | D27: T562 | E27: =+VLOOKUP(T559,Bang_CDSPSNT,4,0)/1000 | G27: KHAC | H27: TM muc 27: so du dau nam truoc lay tu CDSPS nam truoc | K27: CỘT I — ghi x là bỏ qua dòng đó. Ba dòng VD_ ở trên là ví dụ, đang tắt.
A28: VA26093001_20 | B28: CONGTHUC | C28: TMinh | D28: W562 | E28: =+VLOOKUP(W559,Bang_CDSPSNT,4,0)/1000-VLOOKUP(W559,Bang_CDSPSNT,3,0)/1000 | G28: KHAC | H28: TM muc 27: so du dau nam truoc lay tu CDSPS nam truoc
A29: VA26093001_21 | B29: CONGTHUC | C29: TMinh | D29: Z562 | E29: =+VLOOKUP(Z559,Bang_CDSPSNT,4,0)/1000-VLOOKUP(Z559,Bang_CDSPSNT,3,0)/1000 | G29: KHAC | H29: TM muc 27: so du dau nam truoc lay tu CDSPS nam truoc | K29: Nút «Bảng Vá Bố Cục» trên Ribbon: xem còn việc nào chờ + mở bảng ra sửa.
A30: VA26093001_22 | B30: CONGTHUC | C30: TMinh | D30: AC562 | E30: =+VLOOKUP(AC559,Bang_CDSPSNT,4,0)/1000-VLOOKUP(AC559,Bang_CDSPSNT,3,0)/1000 | G30: KHAC | H30: TM muc 27: so du dau nam truoc lay tu CDSPS nam truoc | K30: Việc gì KHÔNG khai báo được (chèn/xoá cột, đổi giao diện cả sheet) thì vẫn phải viết
A31: VA26093001_23 | B31: CONGTHUC | C31: TMinh | D31: AF562 | E31: =+VLOOKUP(AF559,Bang_CDSPSNT,4,0)/1000 | G31: KHAC | H31: TM muc 27: so du dau nam truoc lay tu CDSPS nam truoc | K31: một hàm Buoc<n> trong ModBoCuc như trước.
A32: VA26093001_24 | B32: CONGTHUC | C32: TMinh | D32: K563 | E32: =+VLOOKUP(K559,Bang_CDSPSNT,6,0)/1000 | G32: KHAC | H32: TM muc 27: tang von trong nam truoc
A33: VA26093001_25 | B33: CONGTHUC | C33: TMinh | D33: AC564 | E33: =+MAX(VLOOKUP(AC559,Bang_CDSPSNT,6,0)-VLOOKUP(AC559,Bang_CDSPSNT,5,0),0)/1000 | G33: KHAC | H33: TM muc 27: lai trong nam truoc
A34: VA26093001_26 | B34: CONGTHUC | C34: TMinh | D34: AC567 | E34: =+MAX(VLOOKUP(AC559,Bang_CDSPSNT,5,0)-VLOOKUP(AC559,Bang_CDSPSNT,6,0),0)/1000 | G34: KHAC | H34: TM muc 27: lo trong nam truoc
A35: VA26093001_27 | B35: CONGTHUC | C35: TMinh | D35: AL784 | E35: =IF(SUM(Y784:AK784)>1,1,0) | G35: KHAC | H35: TM: an/hien dong ghi chu (*) theo so lieu
A36: VA260930_MB7_01 | B36: GIATRI | C36: KIEMTRA | D36: E10 | E36: 2 | G36: KHAC | H36: BR cot Thang: BatBuoc 2 = chi bat buoc khi dong co dinh khoan (khong dinh khoan -> bo qua, khong len NKC, khong bao loi)
A37: VA260930_MB7_02 | B37: GIATRI | C37: KIEMTRA | D37: E19 | E37: 2 | G37: KHAC | H37: MV cot Thang ke khai: BatBuoc 2 = chi bat buoc khi dong co dinh khoan
A38: VA260930_MB8_01 | B38: GIATRI | C38: 05KK_89 | D38: F1 | E38: Khai theo: | G38: KHAC | H38: TNCN quy TT89: nhan chon kieu khai
A39: VA260930_MB8_02 | B39: CONGTHUC | C39: 05KK_89 | D39: F2 | E39: =IF($G$1="","","Chọn "&$G$1&" kết chuyển:") | G39: KHAC | H39: TNCN quy TT89: nhan chon ky
A40: VA260930_MB8_03 | B40: GIATRI | C40: 05KK_89 | D40: G1 | E40: quý | G40: TRONG | H40: TNCN quy TT89: mac dinh khai theo quy (chi khi o trong)
A41: VA260930_MB8_04 | B41: DINHDANG | C41: 05KK_89 | D41: F1:F2 | F41: font=Segoe UI;co=10;dam=1;chu=#174F8C;canh=phai | G41: KHAC | H41: giong GTGT_89 C1
A42: VA260930_MB8_05 | B42: DINHDANG | C42: 05KK_89 | D42: G1:G2 | F42: font=Segoe UI;co=10;dam=1;chu=#174F8C;nen=#E3FAFC;canh=giua | G42: KHAC | H42: giong GTGT_89 D1
A43: VA260930_MB8_06 | B43: NUT | C43: 05KK_89 | E43: KC_TNCN_02 | F43: ten=NutKC_TNCN89;chu=Kết Chuyển;l=595;t=5;w=86;h=22;nen=#FFFFFF;vien=#2F6EAD;chumau=#174F8C | G43: KHAC | H43: nut Ket Chuyen nhu GTGT_89
A44: VA260930_MB8_07 | B44: CONGTHUC | C44: 05KK_89 | D44: E11 | E44: ="[01] Kỳ tính thuế: "&IF('05KK_02KK'!$G$95="tháng","Tháng ","Quý ")&'05KK_02KK'!$G$96&" năm "&YEAR(KB_Den) | G44: KHAC | H44: ky tinh thue: Thang/Quy theo kieu khai (truoc ghi cung Quy)
A45: VA26100301_01 | B45: NAME | C45: TTDN | D45: KB_CLTG | E45: =TTDN!$J$38 | G45: KHAC | H45: Cong tac noi file Ngan hang (GPAcc Ngan Hang Ty Gia): 1 = phan NH cua Keo DL lay tu file Ngan hang, 0 = nhu cu
A46: VA26100301_02 | B46: GIATRI | C46: TTDN | D46: J38 | E46: 0 | G46: TRONG | H46: Cong tac KB_CLTG mac dinh 0 - chi dat khi o con trong (khong de so 1 da go)
A47: VA26100301_03 | B47: DINHDANG | C47: TTDN | D47: J38 | F47: font=Segoe UI;co=9;dam=0;chu=#A0A0A0;canh=giua | G47: KHAC | H47: Cong tac KB_CLTG: o khong nhan, chu xam nho
A48: VA26100301_04 | B48: VALIDATION | C48: TTDN | D48: J38 | E48: 0|1 | G48: KHAC | H48: Cong tac KB_CLTG chi nhan 0 hoac 1
A49: VA26100501_01 | B49: NAME | C49: TTDN | D49: KB_GiaThanh | E49: =TTDN!$J$40 | G49: KHAC | H49: Cong tac noi file Gia Thanh San Xuat (khach mua them): 1 = hien nut Nap File Gia Thanh va cho file GT ghi ve, 0 = khong
A50: VA26100501_02 | B50: GIATRI | C50: TTDN | D50: J40 | E50: 0 | G50: TRONG | H50: Cong tac KB_GiaThanh mac dinh 0 - chi dat khi o con trong
A51: VA26100501_03 | B51: DINHDANG | C51: TTDN | D51: J40 | F51: font=Segoe UI;co=9;dam=0;chu=#A0A0A0;canh=giua | G51: KHAC | H51: Cong tac KB_GiaThanh: o khong nhan, chu xam nho
A52: VA26100501_04 | B52: VALIDATION | C52: TTDN | D52: J40 | E52: 0|1 | G52: KHAC | H52: Cong tac KB_GiaThanh chi nhan 0 hoac 1
A53: VA26100601_01 | B53: GIATRI | C53: KIEMTRA | D53: E25 | E53: 2 | G53: KHAC | H53: NH cot Thang: BatBuoc 2 = chi bat buoc khi dong co dinh khoan (dong khong dinh khoan, vd da hach toan ben MV -> khong bao loi)
A54: VA26100601_02 | B54: GIATRI | C54: KIEMTRA | D54: E30 | E54: 2 | G54: KHAC | H54: LT cot Thang: BatBuoc 2 = chi bat buoc khi dong co dinh khoan (dong khong dinh khoan -> khong bao loi)
A55: VA26101101_01 | B55: GIATRI | C55: KIEMTRA | D55: B62 | E55: TTNV_PC | G55: KHAC | H55: TTNV Phu cap: neo TTNV_PC, lap moi cot toi truoc TTNV_KTX (khach them/bot loai phu cap khong lech cot)
A56: VA26101101_02 | B56: GIATRI | C56: KIEMTRA | D56: C62 | E56: 1 | G56: KHAC | H56: TTNV Phu cap: neo TTNV_PC, lap moi cot toi truoc TTNV_KTX (khach them/bot loai phu cap khong lech cot)
A57: VA26101101_03 | B57: GIATRI | C57: KIEMTRA | D57: F62 | E57: Phụ cấp | G57: KHAC | H57: TTNV Phu cap: neo TTNV_PC, lap moi cot toi truoc TTNV_KTX (khach them/bot loai phu cap khong lech cot)
A58: VA26101101_04 | B58: GIATRI | C58: KIEMTRA | D58: H62 | E58: LAP:1:TTNV_KTX | G58: KHAC | H58: TTNV Phu cap: neo TTNV_PC, lap moi cot toi truoc TTNV_KTX (khach them/bot loai phu cap khong lech cot)
A59: VA26101101_05 | B59: GIATRI | C59: KIEMTRA | D59: B63 | E59: TTNV_KTX | G59: KHAC | H59: TTNV Phu cap khong thuong xuyen (tien): neo TTNV_KTX, lap moi 2 cot toi truoc TTNV_GC
A60: VA26101101_06 | B60: GIATRI | C60: KIEMTRA | D60: C63 | E60: 1 | G60: KHAC | H60: TTNV Phu cap khong thuong xuyen (tien): neo TTNV_KTX, lap moi 2 cot toi truoc TTNV_GC
A61: VA26101101_07 | B61: GIATRI | C61: KIEMTRA | D61: F63 | E61: Phụ cấp không thường xuyên | G61: KHAC | H61: TTNV Phu cap khong thuong xuyen (tien): neo TTNV_KTX, lap moi 2 cot toi truoc TTNV_GC
A62: VA26101101_08 | B62: GIATRI | C62: KIEMTRA | D62: H63 | E62: LAP:2:TTNV_GC | G62: KHAC | H62: TTNV Phu cap khong thuong xuyen (tien): neo TTNV_KTX, lap moi 2 cot toi truoc TTNV_GC
A63: VA26101101_09 | B63: GIATRI | C63: KIEMTRA | D63: B64 | E63: TTNV_KTX | G63: KHAC | H63: TTNV Thang tinh PC: neo TTNV_KTX cot 2, lap moi 2 cot toi truoc TTNV_GC (truoc day kiem nham cot tien)
... A67: VA26101101_13 | B67: GIATRI | C67: KIEMTRA | D67: H64 | E67: LAP:2:TTNV_GC | G67: KHAC | H67: TTNV Thang tinh PC: neo TTNV_KTX cot 2, lap moi 2 cot toi truoc TTNV_GC (truoc day kiem nham cot tien)
A68: VA26101101_14 | B68: GIATRI | C68: KIEMTRA | D68: A65:H68 | G68: KHAC | H68: Bo 4 dong TTNV cu (PC nha o/khac/khong thuong xuyen/thang) - da gop vao 3 dong LAP o tren
A69: VA26101301_01 | B69: NAME | C69: TTDN | D69: KB_BoChanNKC | E69: =TTDN!$J$42 | G69: KHAC | H69: Cong tac an (chi bao rieng khach can): 1 = ket chuyen NKC lech doi chieu PB-KH van giu so NKC/CDSPS, chi bao; 0 = chan nhu cu
A70: VA26101301_02 | B70: GIATRI | C70: TTDN | D70: J42 | E70: 0 | G70: TRONG | H70: Cong tac KB_BoChanNKC mac dinh 0 - chi dat khi o con trong
A71: VA26101301_03 | B71: DINHDANG | C71: TTDN | D71: J42 | F71: font=Segoe UI;co=9;dam=0;chu=#A0A0A0;canh=giua | G71: KHAC | H71: Cong tac KB_BoChanNKC: o khong nhan, chu xam nho
A72: VA26101301_04 | B72: VALIDATION | C72: TTDN | D72: J42 | E72: 0|1 | G72: KHAC | H72: Cong tac KB_BoChanNKC chi nhan 0 hoac 1

Sheet TTDN
A1: 5 | D1: THÔNG TIN DOANH NGHIỆP | AM1: Năm | AN1: Tháng | AO1: Quý | AR1: TÊN | AS1: TÊN TRÊN BÌA | AT1: GHI CHÚ | AU1: TK cấp 1 | AV1: TK cấp 2 | AW1: Sô hiệu | BM1: BẢNG THEO DÕI VAT | CD1: VÙNG TẠM LÀM SỔ KHO | CW1: BẢNG THEO DÕI VAT
AM2: =YEAR(KB_Den) -> 2026 | AN2: 1 | AO2: I | AR2: Sổ kế toán | BN2: DK | BO2: 1 | BP2: 2 | BQ2: 3 | BR2: 4 | BS2: 5 | BT2: 6 | BU2: 7 | BV2: 8 | BW2: 9 | BX2: 10 | BY2: 11 | BZ2: 12 | CD2: Tháng | CE2: Số HĐ | CF2: Ngày HĐ | CG2: Nội Dung | CH2: SL Nhập | CI2: DG Nhập | CJ2: TT nhập | CK2: SL Xuất | CL2: DG Xuất | CM2: TT Xuất | CN2: SL Tồn | CO2: DG Tồn | CP2: TT Tồn | CX2: DK | CY2: {=TRANSPOSE(Thang)} -> 1 | CZ2: 2 | DA2: 3 | DB2: 4 | DC2: 5 | DD2: 6 | DE2: 7 | DF2: 8 | DG2: 9 | DH2: 10 | DI2: 11 | DJ2: 12
A3: LẤY DỮ LIỆU | AN3: 2 | AO3: II | AR3: Sổ cái | BM3: Nợ 133 | CV3: 1 | CW3: Nợ 133
AL4: Main | AN4: 3 | AO4: III | AR4: Nhật ký chung | AS4: NHẬT KÝ CHUNG | AZ4: BẢNG KÊ HOÁ ĐƠN, CHỨNG TỪ HÀNG HOÁ, DỊCH VỤ BÁN RA | BM4: Nợ 3331 - nộp thuế | BO4: 0 | CV4: 2 | CW4: Nợ 133-dùng chung
E5: Tên doanh nghiệp: | AL5: CPU | AM5: BFEBFBFF000206A7 | AN5: 4 | AO5: IV | AR5: Sổ quỹ tiền mặt | AS5: QUỸ TIỀN MẶT | AT5: Loại quỹ: | BM5: Có 3331 | CV5: 3 | CW5: Có 133-DCQT
AL6: SecertKey | AM6: ABCDEFGHIJ | AN6: 5 | AR6: Sổ tiền gửi ngân hàng | AS6: TIỀN GỬI NGÂN HÀNG | AU6: - Tài khoản cấp I:……………………………. | AV6: - Tài khoản cấp II:……………………………. | AW6: Số hiệu tài khoản ngân hàng: | AZ6: (Kèm theo tờ khai thuế GTGT theo mẫu số 01/GTGT) | BM6: CK Khấu Trừ | BN6: 0 | BO6: 0 | BP6: 0 | BQ6: 0 | BR6: 0 | BS6: 0 | BT6: 0 | BU6: 0 | BV6: 0 | BW6: 0 | BX6: 0 | BY6: 0 | BZ6: 0 | CV6: 4 | CW6: Nợ 3331 - nộp thuế,DC
E7: Địa chỉ: | AN7: 6 | AR7: Sổ chi tiết vật liệu, sản phẩm, hàng hóa | AS7: VẬT LIỆU, SẢN PHẨM, HÀNG HÓA | AU7: TÀI KHOẢN:……………………………………. | AV7: TIỂU KHOẢN:………………………………….. | AW7: KHO: | AZ7: Kỳ tính thuế: Tháng....... năm ........../ Quý ….. Năm…… | BM7: CK Phải nộp | BN7: 0 | BO7: 0 | BP7: 0 | BQ7: 0 | BR7: 0 | BS7: 0 | BT7: 0 | BU7: 0 | BV7: 0 | BW7: 0 | BX7: 0 | BY7: 0 | BZ7: 0 | CV7: 5 | CW7: Có 3331
AN8: 7 | AR8: Sổ tài sản cố định | AS8: TÀI SẢN CỐ ĐỊNH | CV8: 6 | CW8: Có 3331-DCQT
E9: Mã số thuế: | J9: Email: | AN9: 8 | AR9: Sổ nhật ký chi tiền | AS9: NHẬT KÝ CHI TIỀN | AZ9: Người nộp thuế:........................................................................................ | CV9: 7 | CW9: CK 133
AN10: 9 | AR10: Sổ nhật ký thu tiền | AS10: NHẬT KÝ THU TIỀN | AZ10: Mã số thuế: ............................................................................................... | BM10: 0 | BN10: 1 | BO10: 2 | BP10: 3 | BQ10: 4 | BR10: 5 | BS10: 6 | BT10: 7 | BU10: 8 | BV10: 9 | BW10: 10 | BX10: 11 | BY10: 12 | CV10: 8 | CW10: CK 33311
E11: Điện thoại: | J11: Fax: | AN11: 10 | AR11: Sổ nhật ký mua hàng | AS11: NHẬT KÝ MUA HÀNG | BN11: VÙNG TẠM LÀM CÔNG NỢ | CV11: 9 | CW11: CK133 khấu trừ
A12: XÓA DỮ LIỆU | AN12: 11 | AR12: Sổ nhật ký bán hàng | AS12: NHẬT KÝ BÁN HÀNG | AZ12: Đơn vị tiền: đồng Việt Nam | BT12: Phát sinh | BV12: Phát Sinh Ngân Hàng | BX12: Cuối Kỳ
A13: 26101601 | F13: Từ ngày | K13: Đến ngày | AN13: 12 | AR13: Sổ chi phí sản xuất kinh doanh | AS13: CHI PHÍ SẢN XUẤT KINH DOANH | AU13: Tài khoản: | AZ13: STT | BA13: Hóa đơn, chứng từ bán ra | BE13: Tên người mua | BF13: Mã số thuế người mua | BG13: Mặt hàng | BH13: Doanh thu chưa có thuế GTGT | BI13: Thuế GTGT | BJ13: Ghi chú | BM13: Tháng | BN13: Ký hiệu HĐ | BO13: Số HĐ | BP13: Ngày | BQ13: Tên đơn vị mua hàng | BR13: Mã số thuế | BS13: Nội dung | BT13: Nợ | BU13: Có | BV13: Nợ | BW13: Có | BX13: Nợ | BY13: Có
E14: Kỳ kế toán: | F14: 46023 | K14: 46387 | AR14: Sổ chi tiết thanh toán | AS14: CHI TIẾT THANH TOÁN | AT14: Với người mua, người bán | AU14: Tài khoản:
AM15: KCT | AR15: Sổ chi tiết các tài khoản | AS15: CHI TIẾT CÁC TÀI KHOẢN | AU15: Tài khoản: | BA15: Ký hiệu mẫu HĐ | BB15: Ký hiệu HĐ | BC15: Số hoá đơn | BD15: Ngày, tháng, năm lập hóa đơn
E16: Thuế suất TNDN: | J16: Khai thuế GTGT theo: | K16: Theo tháng | AM16: 0 | AZ16: [1] | BA16: [2] | BB16: [3] | BC16: [4] | BD16: [5] | BE16: [6] | BF16: [7] | BG16: [8] | BH16: [9] | BI16: [10] | BJ16: [11]
AM17: 5
E18: Pass vào hóa đơn: | J18: Kết chuyển VAT: | K18: Tự động | AM18: 10 | AR18: TRUE | AS18: Check phân bổ khấu hao
AR19: TRUE | AS19: Check kết chuyển cuối kỳ
AM20: DR | AN20: Dùng riêng SXKD - được khấu trừ | AR20: TRUE | AS20: Check kéo hàng
E21: Người đại diện pháp luật | I21: Kế toán trưởng | M21: Thủ quỹ | AM21: DC | AN21: Dùng chung SXKD - được khấu trừ | AR21: FALSE | AS21: Check vat theo số người dùng
AM22: DT | AN22: Dùng cho hoạt động đầu tư | AZ22: BẢNG KÊ HOÁ ĐƠN, CHỨNG TỪ HÀNG HOÁ, DỊCH VỤ MUA VÀO
AM23: HDTT | AN23: Hóa đơn trực tiếp
AM24: 01 | AN24: Không chịu thuế GTGT | AO24: KCT | AZ24: (Kèm theo tờ khai thuế GTGT theo mẫu số 01/GTGT)
AM25: 02 | AN25: Chịu thuế GTGT 0% | AO25: 0 | AR25: tthai | AS25: Trạng thái hóa đơn MUA | AZ25: Kỳ tính thuế: Tháng....... năm ........../ Quý …. Năm….
AM26: 03 | AN26: Chịu thuế GTGT 5% | AO26: 0.05 | AR26: All | AS26: Tất cả
AM27: 04 | AN27: Chịu thuế GTGT 10% | AO27: 0.1 | AR27: 1 | AS27: Hóa đơn mới | AZ27: Người nộp thuế:........................................................................................
F28: TÙY CHỌN HỆ THỐNG | AR28: 2 | AS28: Hóa đơn thay thế | AZ28: Mã số thuế: ...............................................................................................
AR29: 3 | AS29: Hóa đơn điều chỉnh
AR30: 4 | AS30: Hóa đơn bị thay thế | AZ30: Đơn vị tiền: đồng Việt Nam
AM31: CDSPSNT_TK | AN31: =+"CDSPS_NT!"&ADDRESS(ROW(CDSPS_NT_1)+1,COLUMN(CDSPS_NT_1))&":"&ADDRESS(ROW(CDSPS_NT_TC)-1,COLUMN(CDSPS_NT_1)) -> CDSPS_NT!$C$15:$C$432 | AR31: 5 | AS31: Hóa đơn đã bị điều chỉnh | AZ31: STT | BA31: Hóa đơn, biên lai, chứng từ nộp thuế | BE31: Tên người bán | BF31: Mã số thuế người bán | BG31: Mặt hàng | BH31: Giá trị HHDV mua vào chưa có thuế | BI31: Thuế suất | BJ31: Thuế GTGT đủ điều kiện khấu trừ thuế | BK31: Ghi chú
I32: Kết chuyển tự động Lãi/Lỗ đầu năm: | J32: Yes | AM32: CDSPSNT_DKN | AN32: =+"CDSPS_NT!"&ADDRESS(ROW(CDSPS_NT_1)+1,COLUMN(CDSPS_NT_1)+2)&":"&ADDRESS(ROW(CDSPS_NT_TC)-1,COLUMN(CDSPS_NT_1)+2) -> CDSPS_NT!$E$15:$E$432 | AR32: 6 | AS32: Hóa đơn bị hủy
AM33: CDSPSNT_DKC | AN33: =+"CDSPS_NT!"&ADDRESS(ROW(CDSPS_NT_1)+1,COLUMN(CDSPS_NT_1)+3)&":"&ADDRESS(ROW(CDSPS_NT_TC)-1,COLUMN(CDSPS_NT_1)+3) -> CDSPS_NT!$F$15:$F$432 | BA33: Ký hiệu mẫu HĐ | BB33: Ký hiệu HĐ | BC33: Số hoá đơn | BD33: Ngày, tháng, năm lập hóa đơn
I34: Kết chuyển tự động Phân bổ - Khấu hao: | J34: Yes | AM34: CDSPSNT_PSN | AN34: =+"CDSPS_NT!"&ADDRESS(ROW(CDSPS_NT_1)+1,COLUMN(CDSPS_NT_1)+4)&":"&ADDRESS(ROW(CDSPS_NT_TC)-1,COLUMN(CDSPS_NT_1)+4) -> CDSPS_NT!$G$15:$G$432 | AR34: ttxly | AS34: Kết quả kiểm tra MUA | AZ34: [1] | BA34: [2] | BB34: [3] | BC34: [4] | BD34: [5] | BE34: [6] | BF34: [7] | BG34: [8] | BH34: [9] | BI34: [10] | BJ34: [11] | BK34: [12]
AM35: CDSPSNT_PSC | AN35: =+"CDSPS_NT!"&ADDRESS(ROW(CDSPS_NT_1)+1,COLUMN(CDSPS_NT_1)+5)&":"&ADDRESS(ROW(CDSPS_NT_TC)-1,COLUMN(CDSPS_NT_1)+5) -> CDSPS_NT!$H$15:$H$432 | AR35: All | AS35: Tất cả
I36: Kết chuyển tự động DT-CP qua 911: | J36: Yes | AM36: CDSPSNT_CKN | AN36: =+"CDSPS_NT!"&ADDRESS(ROW(CDSPS_NT_1)+1,COLUMN(CDSPS_NT_1)+6)&":"&ADDRESS(ROW(CDSPS_NT_TC)-1,COLUMN(CDSPS_NT_1)+6) -> CDSPS_NT!$I$15:$I$432 | AR36: 5 | AS36: Đã cấp mã hóa đơn
AM37: CDSPSNT_CKC | AN37: =+"CDSPS_NT!"&ADDRESS(ROW(CDSPS_NT_1)+1,COLUMN(CDSPS_NT_1)+7)&":"&ADDRESS(ROW(CDSPS_NT_TC)-1,COLUMN(CDSPS_NT_1)+7) -> CDSPS_NT!$J$15:$J$432 | AR37: 6 | AS37: Tổng cục thuế đã nhận không mã
J38: 0 | AR38: 8 | AS38: Tổng cục thuế đã nhận hóa đơn có mã khởi tạo từ máy tính tiền
AM39: https://www.dropbox.com/s/c6cttmr06r2410i/
J40: 0 | AM40: https://www.dropbox.com/s/zk86rb8thuycbl2/ | AR40: ttxly | AS40: Kết quả kiểm tra BAN
AM41: https://www.dropbox.com/s/ct02z1trmm7iacv/ | AR41: All | AS41: Tất cả
J42: 0 | AR42: 0 | AS42: Tổng cục thuế đã nhận
AR43: 1 | AS43: Đang tiến hành kiểm tra điều kiện cấp mã
AR44: 2 | AS44: CQT từ chối theo từng lần phát sinh
AR45: 3 | AS45: Hóa đơn đủ điều kiện cấp mã
AR46: 4 | AS46: Hóa đơn không đủ điều kiện cấp mã
AR47: 5 | AS47: Đã cấp mã hóa đơn
AR48: 6 | AS48: Tổng cục thuế đã nhận không mã
AR49: 7 | AS49: Đã kiểm tra HĐĐT định kỳ không có mã
AR50: 8 | AS50: Tổng cục thuế đã nhận hóa đơn có mã khởi tạo từ máy tính tiền

Sheet LuuY
B2: VÙNG KHAI BÁO CÁC BÚT TOÁN ĐỊNH KHOẢN NHANH
B3: Sheet | C3: STT | D3: Nội dung | E3: ĐK nợ | F3: ĐK có
B4: [1] | C4: [2] | D4: [3] | E4: [4] | F4: [5] | H4: BÁN RA - NHẬT KÝ BÁN | V4: Gõ mã tài khoản vào hai hàng mã bên dưới, theo từng CẶP cần so (cột NK thứ k <-> cột bảng kê thứ k). Để trống thì bỏ qua cặp đó.
B5: BR | C5: 1 | D5: TM_doanh thu Thương Mại | E5: 1111 | F5: 5111 | H5: Tháng | I5: NK bán | M5: Bảng kê Bán ra | Q5: Chênh lệch (NK - bảng kê)
B6: BR | C6: 2 | D6: TM_doanh thu Sản xuất | E6: 1111 | F6: 5112
B7: BR | C7: 3 | D7: TM_doanh thu xây dựng | E7: 1111 | F7: 5113 | H7: 1
B8: MV | C8: 1 | D8: TM_6428 | E8: 6428 | H8: 2
B9: MV | C9: 2 | D9: TM_6427 | E9: 6427 | H9: 3
H10: 4
H11: 5
H12: 6
H13: 7
H14: 8
H15: 9
H16: 10
H17: 11
H18: 12
H19: TC | I19: =SUM(I7:I18) -> 0 | J19: =SUM(J7:J18) -> 0 | K19: =SUM(K7:K18) -> 0 | L19: =SUM(L7:L18) -> 0 | M19: =SUM(M7:M18) -> 0 | N19: =SUM(N7:N18) -> 0 | O19: =SUM(O7:O18) -> 0 | P19: =SUM(P7:P18) -> 0 | ... T19: =SUM(T7:T18) -> 0
H22: MUA VÀO - NHẬT KÝ MUA | V22: Gõ mã tài khoản vào hai hàng mã bên dưới, theo từng CẶP cần so (cột NK thứ k <-> cột bảng kê thứ k). Để trống thì bỏ qua cặp đó.
H23: Tháng | I23: NK mua | M23: Bảng kê Mua vào | Q23: Chênh lệch (NK - bảng kê)
H25: 1
H26: 2
H27: 3
H28: 4
H29: 5
H30: 6
H31: 7
H32: 8
H33: 9
H34: 10
H35: 11
H36: 12
H37: TC | I37: =SUM(I25:I36) -> 0 | J37: =SUM(J25:J36) -> 0 | K37: =SUM(K25:K36) -> 0 | L37: =SUM(L25:L36) -> 0 | M37: =SUM(M25:M36) -> 0 | N37: =SUM(N25:N36) -> 0 | O37: =SUM(O25:O36) -> 0 | P37: =SUM(P25:P36) -> 0 | ... T37: =SUM(T25:T36) -> 0

Sheet BAO_LOI
A1: BÁO CÁO KIỂM TRA DỮ LIỆU NHẬP
A5: STT | B5: Sheet | C5: Ô (bấm để tới) | D5: Giá trị đang có | E5: Lỗi | F5: Cách sửa

Sheet LayHDXML
B1: x | K1: Hyperlink lấy File PDF: | L1: Yes
K2: Lấy lại DATA làm hóa đơn: | L2: No
K4: =+SUBTOTAL(9,K8:K1478) -> 0 | M4: =+SUBTOTAL(9,M8:M1478) -> 0 | N4: =+SUBTOTAL(9,N8:N1478) -> 0 | AA4: Danh sách các hóa đơn chưa có
B5: Thông tin hóa đơn | G5: Thông tin bên bán | J5: Nội dung hóa đơn | O5: Thông tin bên mua | R5: Thông tin tra cứu | AA5: Thông tin hóa đơn | AE5: Thông tin khách hàng | AG5: Tiền hóa đơn
B6: Mẫu số | C6: Ký hiệu | D6: Số hóa đơn | E6: Ngày lập hóa đơn | F6: Ngày ký hóa đơn | G6: Tên người bán | H6: Mã số thuế | I6: Địa chỉ | J6: Nội dung | K6: Thành tiền chưa có VAT | L6: Thuế suất | M6: Thuế GTGT | N6: Tổng hóa đơn | O6: Tên người mua | P6: Mã số thuế | Q6: Địa chỉ | R6: Link tra cứu | S6: Mã tra cứu | T6: Mã cơ quan thuế | U6: Ngày TCT ký | V6: Hyperlink | W6: Ghi chú | X6: Kiểm tra với Chi tiết | Y6: Kiểm tra với Web HĐ | AA6: Mẫu số | AB6: Ký hiệu | AC6: Số hóa đơn | AD6: Ngày lập hóa đơn | AE6: Tên khách hàng | AF6: Mã số thuế | AG6: Tổng tiền chưa thuế | AH6: Thuế GTGT | AI6: Tổng hóa đơn
B7: [1] | C7: [2] | D7: [3] | E7: [4] | F7: [5] | G7: [6] | H7: [7] | I7: [8] | J7: [9] | K7: [10] | L7: [11] | M7: [12] | N7: [13] | O7: [14] | P7: [15] | Q7: [16] | R7: [17] | S7: [18] | T7: [19] | U7: [20] | V7: [21] | W7: [22] | X7: [23] | Y7: [24] | AA7: [1] | AB7: [2] | AC7: [3] | AD7: [4] | AE7: [5] | AF7: [6] | AG7: [7] | AH7: [8] | AI7: [9]

Sheet NK_HDXML
M4: =+SUBTOTAL(9,M8:M1478) -> 0 | O4: =+SUBTOTAL(9,O8:O1478) -> 0
B5: Thông tin HĐ | F5: Người bán/Người mua | H5: Chi tiết mua vào | Q5: Kiểm tra với Mua vào
B6: Mẫu số | C6: Ký hiệu | D6: Số hóa đơn | E6: Ngày hóa đơn | F6: Tên người bán/Mua | G6: Mã số thuế | H6: Mã hàng | I6: Tên hàng | J6: Đơn vị tính | K6: Số lượng | L6: Đơn giá | M6: Thành tiền | N6: Thuế suất (%) | O6: Tiền thuế | P6: Ghi chú
B7: [1] | C7: [2] | D7: [3] | E7: [4] | F7: [5] | G7: [6] | H7: [7] | I7: [8] | J7: [9] | K7: [10] | L7: [11] | M7: [12] | N7: [13] | O7: [14] | P7: [15] | Q7: [16]

Sheet HOADON
I5: =+SUBTOTAL(9,I8:I994) -> 0 | K5: =+SUBTOTAL(9,K8:K994) -> 0 | L5: =+SUBTOTAL(9,L8:L994) -> 0 | M5: =+SUBTOTAL(9,M8:M994) -> 0 | N5: =+SUBTOTAL(9,N8:N994) -> 0 | U5: Đối chiếu VAT | Y5: Đối chiếu Thành tiền | AC5: Hóa đơn liên quan
A6: STT | B6: Ký hiệu mẫu số | C6: Ký hiệu hóa đơn | D6: Số hóa đơn | E6: Ngày lập | F6: Tên người mua/Tên người nhận hàng | G6: MST người mua/MST người nhận hàng | H6: Nội dung | I6: Tổng tiền chưa thuế | J6: Thuế suất | K6: Tổng tiền thuế | L6: Tổng tiền CKTM | M6: Tổng tiền phí | N6: Tổng tiền thanh toán | O6: Đơn vị tiền tệ | P6: Trạng thái hóa đơn | Q6: Kết quả kiểm tra hóa đơn | R6: Tháng | S6: Loại chứng từ | U6: Tổng tiền VAT | V6: VAT bên MV/BR | W6: Đối chiếu | Y6: Tổng tiền hàng | Z6: Tiền hàng bên MV/BR | AA6: Đối chiếu | AC6: Chuỗi thay thế / điều chỉnh | AD6: Thông báo sai sót (04/SS)
A7: [1] | B7: [2] | C7: [3] | D7: [4] | E7: [5] | F7: [6] | G7: [7] | H7: [8] | I7: [9] | J7: [10] | K7: [11] | L7: [12] | M7: [13] | N7: [14] | O7: [15] | P7: [16] | Q7: [17] | R7: [18] | S7: [19] | U7: [1] | V7: [2] | W7: [3] | Y7: [1] | Z7: [2] | AA7: [3] | AC7: [1] | AD7: [2]

Sheet BR
A1: 3
A4: Chú ý: Bạn muốn thêm khách hàng nào để theo dõi công nợ thì để 'Chuột' vào dòng đó rồi thực hiện lệnh 'Thêm Công Nợ' | I4: =+SUBTOTAL(9,I8:I1478) -> 0 | K4: =+SUBTOTAL(9,K8:K1478) -> 0 | R4: =+SUBTOTAL(9,R8:R1478) -> 0 | S4: Mã Đ/C ? | T4: Vùng kiểm tra | Y4: TỔNG HỢP BÁN RA
A5: Loại | B5: Ký hiệu mẫu HĐ | C5: Ký Hiệu HĐ | D5: Số HĐ | E5: Ngày HĐ | F5: Tên khách hàng mua | G5: MST | H5: Nội Dung | I5: Thành tiền | J5: Thuế suất | K5: VAT | L5: Ghi chú | M5: Định Khoản | Q5: Tháng | R5: Tổng HĐ | S5: Mã Đ/C | T5: TT & VAT | U5: Bra & Nky | V5: T.toán NH | W5: Kê khai TCT
M6: Đ/K thành tiền | O6: Đ/K VAT | S6: HĐ điều chỉnh
A7: [1] | B7: [2] | C7: [3] | D7: [4] | E7: [5] | F7: [6] | G7: [7] | H7: [8] | I7: [9] | J7: [10] | K7: [11] | L7: [12] | M7: Nợ | N7: Có | O7: Nợ | P7: Có | Q7: [13] | R7: [14] | S7: [15] | T7: [1] | U7: [2] | V7: [3] | W7: [4] | Y7: Tháng | Z7: Doanh số bán ra | AA7: VAT
R8: =$I8+$K8 -> 0 | Y8: {=Thang} -> 1
R9: =$I9+$K9 -> 0 | Y9: 2
R10: =$I10+$K10 -> 0 | Y10: 3
R11: =$I11+$K11 -> 0 | Y11: 4
R12: =$I12+$K12 -> 0 | Y12: 5
R13: =$I13+$K13 -> 0 | Y13: 6
R14: =$I14+$K14 -> 0 | Y14: 7
R15: =$I15+$K15 -> 0 | Y15: 8
R16: =$I16+$K16 -> 0 | Y16: 9
R17: =$I17+$K17 -> 0 | Y17: 10
R18: =$I18+$K18 -> 0 | Y18: 11
R19: =$I19+$K19 -> 0 | Y19: 12
R20: =$I20+$K20 -> 0
R21: =$I21+$K21 -> 0 | Y21: Tổng cộng | Z21: =+SUM(Z8:Z20) -> 0 | AA21: =+SUM(AA8:AA20) -> 0
R22: =$I22+$K22 -> 0
R23: =$I23+$K23 -> 0
R24: =$I24+$K24 -> 0 | Y24: Quý | Z24: Doanh số bán ra | AA24: VAT
R25: =$I25+$K25 -> 0 | Y25: {=Quy} -> I | Z25: =+Z8+Z9+Z10 -> 0 | AA25: =+AA8+AA9+AA10 -> 0
R26: =$I26+$K26 -> 0 | Y26: II | Z26: =+Z11+Z12+Z13 -> 0 | AA26: =+AA11+AA12+AA13 -> 0
R27: =$I27+$K27 -> 0 | Y27: III | Z27: =+Z14+Z15+Z16 -> 0 | AA27: =+AA14+AA15+AA16 -> 0
R28: =$I28+$K28 -> 0 | Y28: IV | Z28: =+Z17+Z18+Z19 -> 0 | AA28: =+AA17+AA18+AA19 -> 0
R29: =$I29+$K29 -> 0
R30: =$I30+$K30 -> 0 | Y30: Tổng cộng | Z30: =SUM(Z25:Z29) -> 0 | AA30: =SUM(AA25:AA29) -> 0
R31: =$I31+$K31 -> 0
R32: =$I32+$K32 -> 0
R33: =$I33+$K33 -> 0
R34: =$I34+$K34 -> 0
R35: =$I35+$K35 -> 0
R36: =$I36+$K36 -> 0
R37: =$I37+$K37 -> 0
R38: =$I38+$K38 -> 0
R39: =$I39+$K39 -> 0
R40: =$I40+$K40 -> 0
R41: =$I41+$K41 -> 0
R42: =$I42+$K42 -> 0
... R1805: =$I1805+$K1805 -> 0

Sheet NK_Ban
I1: Kiểm tra để công thức: | J1: N
G5: =+SUBTOTAL(9,$G$8:G526) -> 0 | I5: =+SUBTOTAL(9,$I$8:I526) -> 0 | O5: Vùng kiểm tra
A6: Tháng | B6: Số HĐ | C6: Ngày HĐ | D6: Mã HH, DV,TP | E6: Tên HH, DV, TP | F6: ĐVT | G6: Số lượng | H6: Đơn giá | I6: Thành tiền | J6: Định khoản | K6: Số phiếu xuất | L6: Tên khách hàng mua | M6: Kho xuất | N6: Ghi chú | O6: K.Tra N.Ký & B.Ra | P6: Đơn giá vốn | Q6: Tỷ lệ
A7: [1] | B7: [2] | C7: [3] | D7: [4] | E7: [5] | F7: [6] | G7: [7] | H7: [8] | I7: [9] | J7: [10] | K7: [11] | L7: [12] | M7: [13] | N7: [14] | O7: [15] | P7: [16] | Q7: [17]
I8: =$G8*$H8 -> 0
I9: =$G9*$H9 -> 0
I10: =$G10*$H10 -> 0
I11: =$G11*$H11 -> 0
I12: =$G12*$H12 -> 0
I13: =$G13*$H13 -> 0
I14: =$G14*$H14 -> 0
I15: =$G15*$H15 -> 0
I16: =$G16*$H16 -> 0
I17: =$G17*$H17 -> 0
I18: =$G18*$H18 -> 0
I19: =$G19*$H19 -> 0
... I1405: =$G1405*$H1405 -> 0

Sheet MV
A1: 1
A4: Chú ý: Bạn muốn thêm khách hàng nào để theo dõi công nợ thì để 'Chuột' vào dòng đó rồi thực hiện lệnh 'Thêm Công Nợ' | I4: =+SUBTOTAL(9,I8:I1478) -> 0 | K4: =+SUBTOTAL(9,K8:K1478) -> 0 | R4: =+SUBTOTAL(9,R8:R1478) -> 0 | T4: Mã Đ/C ? | U4: Vùng kiểm tra
A5: Loại | B5: Ký hiệu mẫu HĐ | C5: Ký hiệu HĐ | D5: Số HĐ | E5: Ngày HĐ | F5: Tên người bán | G5: Mã số thuế người bán | H5: Mặt hàng | I5: Thành tiền chưa có VAT | J5: Thuế suất | K5: VAT | L5: Ghi chú | M5: Định Khoản | Q5: Tg kê khai BCT | R5: Tổng HĐ | S5: Tg ghi sổ | T5: Mã Đ/C | U5: TT & VAT | V5: M.Vào & N.Ký | W5: T.toán NH | X5: Trùng HĐ | Y5: Kê khai TCT | AA5: TỔNG HỢP MUA VÀO
M6: Đ/K thành tiền | O6: Đ/K VAT | T6: HĐ điều chỉnh
A7: [1] | B7: [2] | C7: [3] | D7: [4] | E7: [5] | F7: [6] | G7: [7] | H7: [8] | I7: [9] | J7: [10] | K7: [11] | L7: [12] | M7: Nợ | N7: Có | O7: Nợ | P7: Có | Q7: [13] | R7: [14] | S7: [15] | T7: [16] | U7: [1] | V7: [2] | W7: [3] | X7: [4] | Y7: [5] | AA7: Tháng | AB7: Doanh số mua vào | AC7: VAT
R8: =$I8+$K8 -> 0 | AA8: {=Thang} -> 1
R9: =$I9+$K9 -> 0 | AA9: 2
R10: =$I10+$K10 -> 0 | AA10: 3
R11: =$I11+$K11 -> 0 | AA11: 4
R12: =$I12+$K12 -> 0 | AA12: 5
R13: =$I13+$K13 -> 0 | AA13: 6
R14: =$I14+$K14 -> 0 | AA14: 7
R15: =$I15+$K15 -> 0 | AA15: 8
R16: =$I16+$K16 -> 0 | AA16: 9
R17: =$I17+$K17 -> 0 | AA17: 10
R18: =$I18+$K18 -> 0 | AA18: 11
R19: =$I19+$K19 -> 0 | AA19: 12
R20: =$I20+$K20 -> 0
R21: =$I21+$K21 -> 0 | AA21: Tổng cộng | AB21: =+SUM(AB8:AB20) -> 0 | AC21: =+SUM(AC8:AC20) -> 0
R22: =$I22+$K22 -> 0
R23: =$I23+$K23 -> 0
R24: =$I24+$K24 -> 0 | AA24: Quý | AB24: Doanh số mua vào | AC24: VAT
R25: =$I25+$K25 -> 0 | AA25: {=Quy} -> I | AB25: =+AB8+AB9+AB10 -> 0 | AC25: =+AC8+AC9+AC10 -> 0
R26: =$I26+$K26 -> 0 | AA26: II | AB26: =+AB11+AB12+AB13 -> 0 | AC26: =+AC11+AC12+AC13 -> 0
R27: =$I27+$K27 -> 0 | AA27: III | AB27: =+AB14+AB15+AB16 -> 0 | AC27: =+AC14+AC15+AC16 -> 0
R28: =$I28+$K28 -> 0 | AA28: IV | AB28: =+AB17+AB18+AB19 -> 0 | AC28: =+AC17+AC18+AC19 -> 0
R29: =$I29+$K29 -> 0
R30: =$I30+$K30 -> 0 | AA30: Tổng cộng | AB30: =SUM(AB25:AB29) -> 0 | AC30: =SUM(AC25:AC29) -> 0
R31: =$I31+$K31 -> 0
R32: =$I32+$K32 -> 0
R33: =$I33+$K33 -> 0
R34: =$I34+$K34 -> 0
R35: =$I35+$K35 -> 0
R36: =$I36+$K36 -> 0
R37: =$I37+$K37 -> 0
R38: =$I38+$K38 -> 0
R39: =$I39+$K39 -> 0
R40: =$I40+$K40 -> 0
R41: =$I41+$K41 -> 0
R42: =$I42+$K42 -> 0
... R447: =$I447+$K447 -> 0

Sheet NK_Mua
I1: Kiểm tra để công thức: | J1: N
G5: =+SUBTOTAL(9,$G$8:G1479) -> 0 | I5: =+SUBTOTAL(9,$I$8:I1479) -> 0 | O5: Vùng kiểm tra
A6: Tháng | B6: Số HĐ | C6: Ngày HĐ | D6: Mã HH, DV,TP | E6: Tên HH, DV, TP | F6: ĐVT | G6: Số lượng | H6: Đơn giá | I6: Thành tiền | J6: Định khoản | K6: Số phiếu nhập | L6: Tên khách hàng bán | M6: Kho nhập | N6: Ghi chú | O6: K.Tra N.Ký & M.Vào
A7: [1] | B7: [2] | C7: [3] | D7: [4] | E7: [5] | F7: [6] | G7: [7] | H7: [8] | I7: [9] | J7: [10] | K7: [11] | L7: [12] | M7: [13] | N7: [14] | O7: [15]
I8: =$G8*$H8 -> 0
I9: =$G9*$H9 -> 0
I10: =$G10*$H10 -> 0
I11: =$G11*$H11 -> 0
I12: =$G12*$H12 -> 0
I13: =$G13*$H13 -> 0
I14: =$G14*$H14 -> 0
I15: =$G15*$H15 -> 0
I16: =$G16*$H16 -> 0
I17: =$G17*$H17 -> 0
I18: =$G18*$H18 -> 0
I19: =$G19*$H19 -> 0
... I1480: =$G1480*$H1480 -> 0

Sheet NH
H4: =+SUBTOTAL(9,H8:H1478) -> 0
C5: Ký hiệu NH | D5: Ngày | E5: Tên người rút-nộp tiền | F5: Mã | G5: Nội dung | H5: Số tiền | I5: Ghi chú | J5: Định khoản | L5: Tháng
J6: Nợ | K6: Có
C7: [1] | D7: [2] | E7: [3] | F7: [4] | G7: [5] | H7: [6] | I7: [7] | J7: [8] | K7: [9] | L7: [10]

Sheet LT
H4: =+SUBTOTAL(9,H8:H1478) -> 0
C5: Ký hiệu | D5: Ngày | E5: Tên người rút-nộp tiền | F5: Mã | G5: Nội dung | H5: Số tiền | I5: Ghi chú | J5: Định khoản | L5: Tháng
J6: Nợ | K6: Có
C7: [1] | D7: [2] | E7: [3] | F7: [4] | G7: [5] | H7: [6] | I7: [7] | J7: [8] | K7: [9] | L7: [10]
B13: 45064
B14: 45064

Sheet SDDK_CN
B4: BẢNG THEO DÕI CÔNG NỢ PHẢI THU (131;141;1388) | L4: BẢNG THEO DÕI CÔNG NỢ PHẢI TRẢ (331;3388;335;341) | U4: BẢNG THEO DÕI ĐỊNH KHOẢN TỰ ĐỘNG
E5: =+SUBTOTAL(9,E$8:$E226) -> 0 | F5: =+SUBTOTAL(9,F$8:F226) -> 0 | O5: =+SUBTOTAL(9,$O$8:O226) -> 0 | P5: =+SUBTOTAL(9,$P$8:P226) -> 0
B6: Tên đối tượng công nợ | C6: Mã số thuế | D6: Ký hiệu | E6: Đầu kỳ nợ | F6: Đầu kỳ có | G6: Trùng MST | H6: Trùng TK | I6: Định khoản có | L6: Tên đối tượng công nợ | M6: Mã số thuế | N6: Ký hiệu | O6: Đầu kỳ nợ | P6: Đầu kỳ có | Q6: Trùng MST | R6: Trùng TK | S6: Định khoản nợ | U6: Mã NV | V6: Tên khách hàng | W6: Mã số thuế | X6: Định khoản Nợ | Y6: Định khoản Có
B7: [1] | C7: [2] | D7: [3] | E7: [4] | F7: [5] | G7: [6] | H7: [7] | I7: [8] | L7: [1] | M7: [2] | N7: [3] | O7: [4] | P7: [5] | Q7: [6] | R7: [7] | S7: [8] | U7: [1] | V7: [2] | W7: [3] | X7: [4] | Y7: [5]

Sheet CN_TH
A1: 1 | C1: Chọn nhóm công nợ: | D1: Phải thu
A2: 12 | C2: Muốn xem chi tiết công nợ nào thì để chuột tại dòng công nợ đó và thực hiện lệnh "Xem chi Tiết"
B4: =+CDSPS!$C$5 -> Đơn vị :
B5: =+CDSPS!$C$6 -> Địa chỉ :
B6: =+CDSPS!$C$7 -> Mã số thuế :
B7: =" BẢNG TỔNG HỢP CÔNG NỢ "&UPPER($D$1) -> BẢNG TỔNG HỢP CÔNG NỢ PHẢI THU
B8: Từ tháng 1 đến tháng 12 năm 2026
K9: Đơn vị tính: đồng Việt Nam
B10: STT | C10: Tên khách hàng | D10: Mã số thuế | E10: Ký hiệu | F10: Số dư đầu kỳ | H10: Số phát sinh | J10: Số dư cuối kỳ
F11: Nợ | G11: Có | H11: Nợ | I11: Có | J11: Nợ | K11: Có
B12: [1] | C12: [2] | D12: [3] | E12: [4] | F12: [5] | G12: [6] | H12: [7] | I12: [8] | J12: [9] | K12: [10]
C15: Tổng cộng
I17: Ngày 31 tháng 12 năm 2026
C18: Người lập biểu Kế toán trưởng | I18: Người đại diện theo pháp luật
C19: (Ký, họ tên) (Ký, họ tên) | I19: (Ký, họ tên, đóng dấu)
I25: =KB_GD -> 0

Sheet CN_CTiet
G1: Chọn nhóm công nợ: | H1: Phải thu | J1: Bạn muốn xử lý nghiệp vụ nào thì để chuột tại nghiệp vụ đó và thực hiện lệnh
C5: =+CDSPS!$C$5 -> Đơn vị :
C6: =+CDSPS!$C$6 -> Địa chỉ :
C7: =+CDSPS!$C$7 -> Mã số thuế :
C8: ="BẢNG CHI TIẾT CÔNG NỢ "&UPPER($H$1) -> BẢNG CHI TIẾT CÔNG NỢ PHẢI THU
F10: Ký hiệu:
F11: Tên khách hàng:
M12: Đơn vị tính: đồng Việt Nam
C13: STT | D13: Ký hiệu HĐ | E13: Số HĐ | F13: Ngày | G13: Tên đơn vị mua hàng | H13: Mã số thuế | I13: Nội dung | J13: Số phát sinh | L13: Số dư | N13: Dòng
J14: Nợ | K14: Có | L14: Nợ | M14: Có
C15: [1] | D15: [2] | E15: [3] | F15: [4] | G15: [5] | H15: [6] | I15: [7] | J15: [8] | K15: [9] | L15: [10] | M15: [11] | N15: [12]
G16: Số dư đầu kỳ
G21: Cộng phát sinh
G22: Số dư cuối kỳ

Sheet PBKH
B4: BẢNG THEO DÕI CHI PHÍ CHỜ PHÂN BỔ VÀ TÀI SẢN TRÍCH KHẤU HAO
F5: Lưu ý: Đọc kỹ các Ghi chú tại từng cột | I5: =+SUBTOTAL(9,I9:I1479) -> 0 | K5: =+SUBTOTAL(9,K9:K1479) -> 0 | S5: =+SUBTOTAL(9,S9:S1479) -> 0 | U5: =+SUBTOTAL(9,U9:U1479) -> 0 | V5: =+SUBTOTAL(9,V9:V1479) -> 0 | Y5: =+SUBTOTAL(9,Y9:Y1479) -> 0 | Z5: =+SUBTOTAL(9,Z9:Z1479) -> 0 | AA5: =+SUBTOTAL(9,AA9:AA1479) -> 0 | AB5: =+SUBTOTAL(9,AB9:AB1479) -> 0 | AC5: =+SUBTOTAL(9,AC9:AC1479) -> 0 | AD5: =+SUBTOTAL(9,AD9:AD1479) -> 0 | AE5: =+SUBTOTAL(9,AE9:AE1479) -> 0 | AF5: =+SUBTOTAL(9,AF9:AF1479) -> 0 | ... AJ5: =+SUBTOTAL(9,AJ9:AJ1479) -> 0
B6: Nhóm | C6: Định khoản CCDC-TS | D6: Số HĐ | E6: Ngày HĐ | F6: Tên TS | G6: Ngày đưa vào SD | H6: Ngày bắt đầu P.Bổ K.Hao | I6: Giá trị TS | J6: Thời gian P/Bổ KH | K6: Giá trị đã P.Bổ K.Hao năm trước | L6: TK trích P/Bổ KH | M6: Tg ghi sổ | N6: Tg tạm ngưng P.B K.H | O6: Tg P.Bổ K.Hao lại sau khi tạm ngưng | P6: Ghi giảm TS P.Bổ K.Hao | S6: Giá trị P.Bổ K.Hao 1 tháng | T6: Ghi chú | U6: Vùng lấy số dư cho đầu năm sau | Y6: 1 | Z6: 2 | AA6: 3 | AB6: 4 | AC6: 5 | AD6: 6 | AE6: 7 | AF6: 8 | AG6: 9 | AH6: 10 | AI6: 11 | AJ6: 12
P7: Số hiệu | Q7: Ngày, tháng, năm | R7: Lý do | U7: Giá trị PH-KH năm nay | V7: Giá trị còn lại | W7: Rút trích
B8: [1] | C8: [2] | D8: [3] | E8: [4] | F8: [5] | G8: [6] | H8: [7] | I8: [8] | J8: [9] | K8: [10] | L8: [11] | M8: [12] | N8: [13] | O8: [14] | P8: [15] | Q8: [16] | R8: [17] | S8: [18] | T8: [19] | U8: [20] | V8: [21] | W8: [22] | Y8: [1] | Z8: [2] | AA8: [3] | AB8: [4] | AC8: [5] | AD8: [6] | AE8: [7] | AF8: [8] | AG8: [9] | AH8: [10] | AI8: [11] | AJ8: [12]
S9: =IF($J9="",0,IF($B9="PB",$I9/$J9,$I9/($J9*12))) -> 0
S10: =IF($J10="",0,IF($B10="PB",$I10/$J10,$I10/($J10*12))) -> 0
S11: =IF($J11="",0,IF($B11="PB",$I11/$J11,$I11/($J11*12))) -> 0
S12: =IF($J12="",0,IF($B12="PB",$I12/$J12,$I12/($J12*12))) -> 0
S13: =IF($J13="",0,IF($B13="PB",$I13/$J13,$I13/($J13*12))) -> 0
S14: =IF($J14="",0,IF($B14="PB",$I14/$J14,$I14/($J14*12))) -> 0
S15: =IF($J15="",0,IF($B15="PB",$I15/$J15,$I15/($J15*12))) -> 0
S16: =IF($J16="",0,IF($B16="PB",$I16/$J16,$I16/($J16*12))) -> 0
S17: =IF($J17="",0,IF($B17="PB",$I17/$J17,$I17/($J17*12))) -> 0
S18: =IF($J18="",0,IF($B18="PB",$I18/$J18,$I18/($J18*12))) -> 0
S19: =IF($J19="",0,IF($B19="PB",$I19/$J19,$I19/($J19*12))) -> 0
S20: =IF($J20="",0,IF($B20="PB",$I20/$J20,$I20/($J20*12))) -> 0
... S290: =IF($J290="",0,IF($B290="PB",$I290/$J290,$I290/($J290*12))) -> 0

Sheet Bang_PBo
F1: Chọn tháng kết chuyển: | G1: 6
D5: ="Đơn vị : "&KB_CTy -> Đơn vị :
D6: ="Địa chỉ : "&KB_DC -> Địa chỉ :
D7: ="Mã số thuế : "&KB_MST -> Mã số thuế :
D8: BẢNG PHÂN BỔ CHI PHÍ CHỜ PHÂN BỔ
G9: Tháng | H9: 6
G10: Năm | H10: =YEAR(KB_Den) -> 2026
P11: Đơn vị tính: đồng Việt Nam
C12: Ký hiệu | D12: Chứng từ | F12: Tên chi phí | G12: Ngày đưa vào SD | H12: Ngày bắt đầu P/Bổ | I12: Giá trị ban đầu | J12: Thời gian P/Bổ | K12: Số tháng đã P/Bổ | L12: Giá trị đã P/Bổ | M12: Giá trị còn lại | N12: Giá trị P/Bổ 1 tháng | O12: Giá trị P/Bổ kỳ này | P12: Ghi chú | R12: Chi tiết phân bổ từng tháng
D13: Số hóa đơn | E13: Ngày hóa đơn | R13: 1 | S13: 2 | T13: 3 | U13: 4 | V13: 5 | W13: 6 | X13: 7 | Y13: 8 | Z13: 9 | AA13: 10 | AB13: 11 | AC13: 12
C15: [0] | D15: [1] | E15: [2] | F15: [3] | G15: [4] | H15: [5] | I15: [6] | J15: [7] | K15: [8] | L15: [9] | M15: [10] | N15: [11] | O15: [12] | P15: [13] | R15: [1] | S15: [2] | T15: [3] | U15: [4] | V15: [5] | W15: [6] | X15: [7] | Y15: [8] | Z15: [9] | AA15: [10] | AB15: [11] | AC15: [12]
F18: Tổng cộng
M20: , Ngày 30 tháng 6 năm 2025
E21: Người lập biểu | H21: Kế toán trưởng | M21: Người đại diện theo pháp luật
E22: (Ký, họ tên) | H22: (Ký, họ tên) | M22: (Ký, họ tên, đóng dấu)
E28: =IF(ISBLANK(KB_TQuy),"",KB_TQuy) | H28: =IF(ISBLANK(KB_KTT),"",KB_KTT) | M28: =KB_GD -> 0

Sheet Bang_TSCD
F1: Chọn lại tài sản: | G1: All
F2: Chọn tháng kết chuyển: | G2: 12
C5: ="Đơn vị : "&KB_CTy -> Đơn vị :
C6: ="Địa chỉ : "&KB_DC&", "&KB_TTP -> Địa chỉ : ,
C7: ="Mã số thuế : "&KB_MST -> Mã số thuế :
C8: ="SỔ THEO DÕI VÀ TRÍCH KHẤU HAO TSCĐ "&IF($G$1="All","",RIGHT($G$1,LEN($G$1)-5)&" ")&"NĂM "&YEAR(KB_Den) -> SỔ THEO DÕI VÀ TRÍCH KHẤU HAO TSCĐ NĂM 2026
Q9: Đơn vị tính: đồng Việt Nam
A10: Ký hiệu | B10: Tài khoản | C10: Số TT | D10: Ghi tăng TSCĐ | K10: Khấu hao TSCĐ | O10: Ghi giảm TSCĐ | R10: Không in, không xóa | V10: Chi tiết khấu hao từng tháng
D11: Chứng từ | F11: Tên, đặc điểm, kí hiệu TSCĐ | G11: Nước sản xuất | H11: Tháng năm đưa vào sử dụng | I11: Số hiệu TSCĐ | J11: Nguyên giá TSCĐ | K11: Khấu hao | N11: Khấu hao đã tính đến khi ghi giảm TSCĐ | O11: Chứng từ | Q11: Lý do giảm TSCĐ | R11: Khấu hao cộng dồn đến cuối năm trước | S11: Khấu hao cộng dồn năm nay | T11: Khấu hao tháng | V11: 1 | W11: 2 | X11: 3 | Y11: 4 | Z11: 5 | AA11: 6 | AB11: 7 | AC11: 8 | AD11: 9 | AE11: 10 | AF11: 11 | AG11: 12
D12: Số hiệu | E12: Ngày tháng | K12: Tỷ lệ (%) khấu hao | L12: Thời gian | M12: Mức khấu hao năm | O12: Số hiệu | P12: Ngày, tháng, năm
A15: [0] | B15: [1] | C15: [2] | D15: [3] | E15: [4] | F15: [5] | G15: [6] | H15: [7] | I15: [8] | J15: [9] | K15: [10] | L15: [11] | M15: [12] | N15: [13] | O15: [14] | P15: [15] | Q15: [16] | R15: [17] | S15: [18] | T15: [19] | V15: [1] | W15: [2] | X15: [3] | Y15: [4] | Z15: [5] | AA15: [6] | AB15: [7] | AC15: [8] | AD15: [9] | AE15: [10] | AF15: [11] | AG15: [12]
F18: Tổng cộng TSCĐ
N20: , Ngày 31 tháng 12 năm 2023
E21: Người ghi sổ | I21: Kế toán trưởng | N21: Người đại diện theo pháp luật
E22: (Ký, họ tên) | I22: (Ký, họ tên) | N22: (Ký, họ tên, đóng dấu)
E28: =IF(ISBLANK(KB_TQuy),"",KB_TQuy) | I28: =IF(ISBLANK(KB_KTT),"",KB_KTT) | N28: =KB_GD -> 0

Sheet DK_HHDV
B4: BẢNG THEO DÕI SỐ DƯ ĐẦU KỲ VÀ PHÁT SINH HÀNG HÓA, DỊCH VỤ | K4: BẢNG KÝ HIỆU ĐỊNH KHOẢN
B5: Mã hàng hóa, dịch vụ | C5: Tên hàng hóa, dịch vụ | D5: ĐVT | E5: ="TỒN ĐẦU NĂM "&KB_Nam -> TỒN ĐẦU NĂM 2026 | H5: Định khoản | I5: K.Tra trùng | K5: Tài khoản | L5: Diễn giải
E6: Số lượng | F6: Đơn giá | G6: Thành tiền
B7: [1] | C7: [2] | D7: [3] | E7: [4] | F7: [5] | G7: [6] | H7: [7] | I7: [8] | K7: [1] | L7: [2] | M7: Lưu ý:
K8: All | L8: Hàng hóa, dịch vụ | M8: _ Nhập liên tục không ngắt quãng
K9: 1521 | L9: Nguyên Vật Liệu | M9: _ Phải khai báo ký hiệu định khoản và nội dung diễn giải
K10: 154 | L10: Dở Dang | M10: _ Không cần khai báo tài khoản xuất khác hoặc nhập khác. Nếu muốn nhập khác hoặc xuất thể hiện trên bảng NXT thì khi định khoản bên NK Bán hoặc NK Mua ghép thêm chữ "K"
K11: 155 | L11: Thành Phẩm | M11: _ Luôn bắt đầu bằng tài khoản: 152;153;154;155;156
K12: 1561 | L12: Hàng Hóa | M12: _Tài khoản All luôn có và nằm đầu tiên
K13: 157 | L13: Hàng hóa đang đi đường

Sheet RapMa
M2: Sheet cần ráp mã: | N2: NK_Ban
A4: RÁP MÃ HÀNG HÓA - DỊCH VỤ
A5: Tháng | B5: Chứng từ | D5: Chi tiết chứng từ | J5: Định khoản | K5: Dòng NK | L5: Dò tìm mã hàng trong Danh Mục
B6: Số | C6: Ngày | D6: Mã HH-DV | E6: Tên HH-DV | F6: Đơn vị tính | G6: Số lượng | H6: Đơn giá | I6: Thành tiền | L6: Mã HH-DV | M6: Tên HH-DV | N6: Đơn vị tính | O6: Tin cậy | P6: Gợi ý 2 | Q6: Gợi ý 3
A7: [1] | B7: [2] | C7: [3] | D7: [4] | E7: [5] | F7: [6] | G7: [7] | H7: [8] | I7: [9] | J7: [10] | K7: [11] | L7: [12] | M7: [13] | N7: [14] | O7: [15] | P7: [16] | Q7: [17]

Sheet DM_RapMa
B2: THIẾT LẬP RÁP MÃ
B3: Sửa trực tiếp vào cột «Giá trị». Để trống thì chương trình dùng số mặc định.
B5: Ráp mã tự động | C5: Giá trị | D5: Giải thích
B6: Ngưỡng tự điền mã (%) | C6: 70 | D6: Độ tin cậy tối thiểu để chương trình tự điền mã vào cột «Mã HH-DV»
B7: Cách biệt tối thiểu với ứng viên 2 | C7: 15 | D7: Ứng viên nhất phải hơn ứng viên nhì bấy nhiêu % thì mới tự điền
B8: Kiểu sinh mã mới | C8: 1 | D8: 0 = chỉ lấy tên · 1 = nhóm_tên (NVL_Ong_Nhua_90) · 2 = nhóm + số thứ tự (NVL0001)
B9: Số từ tối đa lấy vào mã | C9: 4 | D9: Cụm chữ số (0.4 · C100 · 30x60) luôn được giữ, không tính vào số từ này
B10: Thêm đơn vị tính vào đuôi mã | C10: 0 | D10: 1 = có (Ton_Lanh_04_Kg) · 0 = không
B11: Bắt buộc trùng cụm số | C11: 1 | D11: 1 = hai tên phải cùng cụm số mới ráp (Nối ray 3P ≠ Ray điện 3P 100A) · 0 = bỏ luật này
B16: TỪ ĐỒNG NGHĨA
B17: Nhà cung cấp viết một kiểu, danh mục của mình viết một kiểu. Ghi vào đây để máy quy về một mối trước khi dò.
B18: Chữ trong nhật ký | C18: Quy về chữ | D18: Ghi chú
B19: TOLE | C19: TON | D19: ví dụ sẵn — xoá được
B20: TOL | C20: TON
B21: BU LONG | C21: BULONG
B220: TỪ KỴ NHAU
B221: Hai chữ này không bao giờ là một mặt hàng — dù máy chấm điểm cao thì cũng không được ráp.
B222: Chữ bên này | C222: Kỵ với chữ | D222: Ghi chú
B223: Chổi điện | C223: Tay lấy điện | D223: chổi than ≠ bộ lấy điện, cùng 3P 60A nên máy hay nhầm

Sheet NXT
D1: Chọn TK kết chuyển: | F1: 1521
B5: ="Đơn vị : "&KB_CTy -> Đơn vị : | F5: ="BẢNG TỔNG HỢP NHẬP XUẤT TỒN "&UPPER(VLOOKUP($F$1,DK_HHDV!$K$8:$L$18,2,0)) -> BẢNG TỔNG HỢP NHẬP XUẤT TỒN NGUYÊN VẬT LIỆU | Y5: BẢNG THEO DÕI GIÁ TRỊ NHẬP - XUẤT
B6: ="Địa chỉ : "&KB_DC -> Địa chỉ : | F6: TỪ THÁNG 1 ĐẾN THÁNG 12 | Y6: TKDK | Z6: Diễn giải | AA6: 1 | AB6: 2 | AC6: 3 | AD6: 4 | AE6: 5 | AF6: 6 | AG6: 7 | AH6: 8 | AI6: 9 | AJ6: 10 | AK6: 11 | AL6: 12
B7: ="Mã số thuế : "&KB_MST -> Mã số thuế : | F7: ="NĂM "& KB_Nam -> NĂM 2026
U9: Đơn vị tính: đồng Việt Nam
B10: Stt | C10: Mã hàng | D10: Tên HH, DV | E10: ĐVT | F10: Tồn đầu kỳ | H10: Nhập trong kỳ | J10: Nhập khác trong kỳ | L10: Nhập trong kỳ | N10: Xuất trong kỳ | P10: Xuất trong kỳ | R10: Xuất trong kỳ | T10: Tồn cuối kỳ | V10: Giá | W10: Định khoản
F11: Số lượng | G11: Thành tiền | H11: Số lượng | I11: Thành tiền | J11: Số lượng | K11: Thành tiền | L11: Số lượng | M11: Thành tiền | N11: Số lượng | O11: Thành tiền | P11: Số lượng | Q11: Thành tiền | R11: Số lượng | S11: Thành tiền | T11: Số lượng | U11: Thành tiền
B12: [1] | C12: [2] | D12: [2] | E12: [3] | F12: [4] | G12: [5] | H12: [7'] | I12: [8'] | J12: [7''] | K12: [8''] | L12: [6] | M12: [7] | N12: [9'] | O12: [10'] | P12: [9''] | Q12: [10''] | R12: [8] | S12: [9] | T12: [10] | U12: [11] | V12: Cuối Kỳ | W12: [0]
D16: Tổng cộng
T18: , Ngày 31 tháng 12 năm 2023
D19: Người ghi sổ | L19: Kế toán trưởng | T19: Người đại diện theo pháp luật
D20: (Ký, họ tên) | L20: (Ký, họ tên) | T20: (Ký, họ tên, đóng dấu)
D26: =IF(ISBLANK(KB_TQuy),"",KB_TQuy) | L26: =IF(ISBLANK(KB_KTT),"",KB_KTT) | T26: =KB_GD -> 0

Sheet GV
T4: VÙNG THEO DÕI VAT - NGƯỜI DÙNG CUNG CẤP SỐ LIỆU ĐỂ KẾT CHUYỂN NHẬT KÝ CHUNG
B5: BẢNG KHAI BÁO SỐ DƯ VÀ TÍNH GIÁ VỐN CUỐI KỲ | U5: BẢNG THEO DÕI THUẾ GTGT ( THEO THÁNG - NGƯỜI DÙNG TỰ K.C ) | AA5: BẢNG THEO DÕI THUẾ GTGT ( THEO QUÝ - NGƯỜI DÙNG TỰ K.C )
T6: Tháng | U6: Đầu Kỳ | V6: Mua Vào | W6: Bán Ra | X6: Cuối Kỳ | Z6: Quý | AA6: Đầu Kỳ | AB6: Mua Vào | AC6: Bán Ra | AD6: Cuối Kỳ
B7: LOẠI HÌNH KINH DOANH THƯƠNG MẠI | U7: [1] | V7: [2] | W7: [3] | X7: [4] | AA7: [1] | AB7: [2] | AC7: [3] | AD7: [4]
B8: Nội dung | C8: Đ.Khoản Nợ | D8: Đ.Khoản Có | E8: 1 | F8: 2 | G8: 3 | H8: 4 | I8: 5 | J8: 6 | K8: 7 | L8: 8 | M8: 9 | N8: 10 | O8: 11 | P8: 12 | T8: {=Thang} -> 1 | Z8: {=Quy} -> I
B9: Giá vốn thương mại | C9: 6321 | D9: 1561 | T9: 2 | Z9: II
B10: Giá vốn thương mại | C10: 6321 | D10: 1562 | T10: 3 | Z10: III
T11: 4 | Z11: IV
T12: 5
B13: LOẠI HÌNH KINH DOANH SẢN XUẤT; XÂY DỰNG - LẮP ĐẶT; DỊCH VỤ … | T13: 6
B14: Nội dung | C14: Đ.Khoản Nợ | D14: Đ.Khoản Có | E14: 1 | F14: 2 | G14: 3 | H14: 4 | I14: 5 | J14: 6 | K14: 7 | L14: 8 | M14: 9 | N14: 10 | O14: 11 | P14: 12 | T14: 7
B15: NVL xuất sản xuất | C15: 621 | D15: 1521 | T15: 8
B16: K/C nguyên vật liệu | C16: 1542 | D16: 621 | T16: 9
B17: K/C nhân công sản xuất | C17: 1542 | D17: 622 | T17: 10
B18: K/C chi phí phân bổ | C18: 1542 | D18: 6273 | T18: 11
B19: K/C chi phí khấu hao | C19: 1542 | D19: 6274 | T19: 12
B20: K/C chi phí mua ngoài | C20: 1542 | D20: 6277
B21: K/C chi phí mua khác | C21: 1542 | D21: 6278
B22: Thành phẩm NK | C22: 1551 | D22: 1542
B23: Thành phẩm XK | C23: 6321 | D23: 1551
B26: CÁC BÚT TOÁN LƯƠNG + BẢO HIỂM + THUẾ TNCN
B27: Nội dung | C27: Đ.Khoản Nợ | D27: Đ.Khoản Có | E27: 1 | F27: 2 | G27: 3 | H27: 4 | I27: 5 | J27: 6 | K27: 7 | L27: 8 | M27: 9 | N27: 10 | O27: 11 | P27: 12
B28: BHXH phải nộp NV sản xuất | C28: 622 | D28: 3383
B29: BHYT phải nộp NV sản xuất | C29: 622 | D29: 3384
B30: BHTN phải nộp NV sản xuất | C30: 622 | D30: 3386
B31: BHXH phải nộp NV bán hàng | C31: 6411 | D31: 3383
B32: BHYT phải nộp NV bán hàng | C32: 6411 | D32: 3384
B33: BHTN phải nộp NV bán hàng | C33: 6411 | D33: 3386
B34: BHXH phải nộp NV văn phòng | C34: 6421 | D34: 3383
B35: BHYT phải nộp NV văn phòng | C35: 6421 | D35: 3384
B36: BHTN phải nộp NV văn phòng | C36: 6421 | D36: 3386
B37: BHXH khấu trừ NLĐ | C37: 3341 | D37: 3383
B38: BHYT khấu trừ NLĐ | C38: 3341 | D38: 3384
B39: BHTN khấu trừ NLĐ | C39: 3341 | D39: 3386
... B48: Chi lương | C48: 3341 | D48: 1111
B50: CÁC BÚT TOÁN GIẢM TRỪ DOANH THU (HBTL-CKTM…)
B51: Nội dung | C51: Đ.Khoản Nợ | D51: Đ.Khoản Có | E51: 1 | F51: 2 | G51: 3 | H51: 4 | I51: 5 | J51: 6 | K51: 7 | L51: 8 | M51: 9 | N51: 10 | O51: 11 | P51: 12
B52: Kết chuyển hàng bán trả lại
C61: BẢNG THEO DÕI CHI PHÍ KHẤU HAO VÀ PHÂN BỔ
B62: Nội dung | C62: Ký hiệu | D62: Đ/Khoản | E62: 1 | F62: 2 | G62: 3 | H62: 4 | I62: 5 | J62: 6 | K62: 7 | L62: 8 | M62: 9 | N62: 10 | O62: 11 | P62: 12
C63: [1] | D63: [2] | E63: [3] | F63: [4] | G63: [5] | H63: [6] | I63: [7] | J63: [8] | K63: [9] | L63: [10] | M63: [11] | N63: [12] | O63: [13] | P63: [14]

Sheet TTNV
D1: Lưu ý: cột nào có dấu (*) thì vui lòng điền đầy đủ
I4: THÔNG TIN LÀM HỢP ĐỒNG LAO ĐỘNG | X4: THÔNG TIN LÀM LƯƠNG | AS4: THÔNG TIN THÁNG LÀM VIỆC | BF4: THÔNG TIN THÁNG ĐÓNG BẢO HIỂM | BS4: BẢNG TỶ LỆ ĐÓNG BH QUA CÁC THÁNG | CB4: Bảng Ký Hiệu Định Khoản
B6: STT | C6: Mã NV (*) | D6: Tên nhân viên (*) | E6: MST TNCN | F6: Số CMND (*) | G6: Ngày cấp (*) | H6: Nơi cấp (*) | I6: Thông tin liên lạc | N6: Thông tin công việc | R6: Thông tin HĐLĐ | X6: Các khoản phụ cấp | AC6: Các khoản phụ cấp không thường xuyên | AG6: Giảm trừ gia cảnh | AK6: Thu nhập miễn thuế TNCN | AN6: Ghi chú | AS6: Tháng làm việc (*) | BF6: Tháng làm việc (*)
I7: Địa chỉ (*) | J7: Đ.Thoại | K7: Fax | L7: Email | M7: Số TK ngân hàng | N7: Công việc (*) | O7: Mô tả công việc (*) | P7: Mức lương (*) | Q7: Mức lương đóng BHXH (*) | R7: Số HĐLĐ (*) | S7: Loại HĐLĐ (*) | T7: Thời gian | V7: Ghi chú lao động NN hay VN (*) | X7: Cơm trưa | Y7: Điện thoại | Z7: Xăng | AA7: Nhà ở | AB7: Khác | AC7: Lễ 30/4 | AD7: Tháng tính PC | AE7: Lễ 2/9 | AF7: Tháng tính PC | AG7: Bản thân | AH7: Người phụ thuộc | AK7: Cơm trưa | AL7: Điện thoại | AM7: Khác | AN7: Định khoản (*) | AO7: Loại (*) | AP7: H.Thức trả lương (*) | AQ7: Ủy quyền QToan (*) | AS7: 1 | AT7: 2 | AU7: 3 | AV7: 4 | AW7: 5 | AX7: 6 | AY7: 7 | AZ7: 8 | BA7: 9 | BB7: 10 | BC7: 11 | BD7: 12 | BF7: 1 | BG7: 2 | BH7: 3 | BI7: 4 | BJ7: 5 | BK7: 6 | BL7: 7 | BM7: 8 | BN7: 9 | BO7: 10 | BP7: 11 | BQ7: 12 | BT7: Việt Nam | BV7: Nước ngoài | BX7: Mức đóng Max | BZ7: Tỷ giá tính lương NN
T8: Bắt đầu | U8: Kết thúc | AH8: Số lượng | AI8: Số tiền | AJ8: Tháng bắt đầu | BS8: Tháng | BT8: Công ty | BU8: Người LĐ | BV8: Công ty | BW8: Người LĐ | BX8: BHXH, BHYT | BY8: BHTN | CB8: K.Hiệu | CC8: Diễn giải
B9: [1] | C9: [2] | D9: [3] | E9: [4] | F9: [5] | G9: [6] | H9: [7] | I9: [8] | J9: [9] | K9: [10] | L9: [11] | M9: [12] | N9: [13] | O9: [14] | P9: [15] | Q9: [16] | R9: [17] | S9: [18] | T9: [19] | U9: [20] | V9: [21] | X9: [PC] | Y9: [PC] | Z9: [PC] | AA9: [PC] | AB9: [PC] | AC9: [KTX] | AD9: [KTX] | AE9: [KTX] | AF9: [KTX] | AG9: [GC] | AH9: [GC] | AI9: [GC] | AJ9: [GC] | AK9: [MT] | AL9: [MT] | AM9: [MT] | AN9: [1] | AO9: [2] | AP9: [3] | AQ9: [4] | AS9: [1] | AT9: [2] | AU9: [3] | AV9: [4] | AW9: [5] | AX9: [6] | AY9: [7] | AZ9: [8] | BA9: [9] | BB9: [10] | BC9: [11] | BD9: [12] | BF9: [1] | BG9: [2] | BH9: [3] | BI9: [4] | BJ9: [5] | BK9: [6] | BL9: [7] | BM9: [8] | BN9: [9] | BO9: [10] | BP9: [11] | BQ9: [12] | BS9: [1] | BT9: [2] | BU9: [3] | BV9: [4] | BW9: [5] | BX9: [6] | BY9: [7] | BZ9: [8] | CB9: [1] | CC9: [2]
BF10: All | BG10: All | BH10: All | BI10: All | BJ10: All | BK10: All | BL10: All | BM10: All | BN10: All | BO10: All | BP10: All | BQ10: All | BS10: {=Thang} -> 1 | BT10: 17.5;3;1 | BU10: 8;1.5;1 | BV10: 3.5;3;0 | BW10: 0;1.5;0 | BX10: =1490000*20 -> 29800000 | BY10: =4420000*20 -> 88400000 | BZ10: 22100 | CB10: 622 | CC10: Nhân công trực tiếp
BS11: 2 | BT11: 17.5;3;1 | BU11: 8;1.5;1 | BV11: 3.5;3;0 | BW11: 0;1.5;0 | BX11: =1490000*20 -> 29800000 | BY11: =4420000*20 -> 88400000 | BZ11: 22100 | CB11: 6271 | CC11: Nhân công sản xuất chung
BS12: 3 | BT12: 17.5;3;1 | BU12: 8;1.5;1 | BV12: 3.5;3;0 | BW12: 0;1.5;0 | BX12: =1490000*20 -> 29800000 | BY12: =4420000*20 -> 88400000 | BZ12: 22100 | CB12: 6411 | CC12: Nhân viên bán hàng
BS13: 4 | BT13: 17.5;3;1 | BU13: 8;1.5;1 | BV13: 3.5;3;0 | BW13: 0;1.5;0 | BX13: =1490000*20 -> 29800000 | BY13: =4420000*20 -> 88400000 | BZ13: 22100 | CB13: 6421 | CC13: Nhân viên văn phòng
BS14: 5 | BT14: 17.5;3;1 | BU14: 8;1.5;1 | BV14: 3.5;3;0 | BW14: 0;1.5;0 | BX14: =1490000*20 -> 29800000 | BY14: =4420000*20 -> 88400000 | BZ14: 22100
BS15: 6 | BT15: 17.5;3;1 | BU15: 8;1.5;1 | BV15: 3.5;3;0 | BW15: 0;1.5;0 | BX15: =1490000*20 -> 29800000 | BY15: =4420000*20 -> 88400000 | BZ15: 22100
BS16: 7 | BT16: 17;3;1 | BU16: 8;1.5;1 | BV16: 3;3;0 | BW16: 0;1.5;0 | BX16: =1490000*20 -> 29800000 | BY16: =4420000*20 -> 88400000 | BZ16: 22100
BS17: 8 | BT17: 17;3;1 | BU17: 8;1.5;1 | BV17: 3;3;0 | BW17: 0;1.5;0 | BX17: =1490000*20 -> 29800000 | BY17: =4420000*20 -> 88400000 | BZ17: 22100
BS18: 9 | BT18: 17;3;1 | BU18: 8;1.5;1 | BV18: 3;3;0 | BW18: 0;1.5;0 | BX18: =1490000*20 -> 29800000 | BY18: =4420000*20 -> 88400000 | BZ18: 22100
BS19: 10 | BT19: 17;3;0 | BU19: 8;1.5;1 | BV19: 3;3;0 | BW19: 0;1.5;0 | BX19: =1490000*20 -> 29800000 | BY19: =4420000*20 -> 88400000 | BZ19: 22100
BS20: 11 | BT20: 17;3;0 | BU20: 8;1.5;1 | BV20: 3;3;0 | BW20: 0;1.5;0 | BX20: =1490000*20 -> 29800000 | BY20: =4420000*20 -> 88400000 | BZ20: 22100
BS21: 12 | BT21: 17;3;0 | BU21: 8;1.5;1 | BV21: 3;3;0 | BW21: 0;1.5;0 | BX21: =1490000*20 -> 29800000 | BY21: =4420000*20 -> 88400000 | BZ21: 22100

Sheet HDLD
Q1: Mã nhân viên: | R1: NVA
F5: =UPPER(KB_CTy) | N5: CỘNG HÒA XÃ HỘI CHỦ NGHĨA VIỆT NAM
N6: Độc lập - Tự do - Hạnh phúc
F8: Số HĐLĐ: | P8: , ngày 30 tháng 12 năm 1899
G10: HỢP ĐỒNG LAO ĐỘNG
G12: Căn cứ Bộ luật Lao động số 10/2012/QH13 ngày 18 tháng 6 năm 2012;
G13: Căn cứ Nghị định số 05/2015/NĐ-CP ngày 12 tháng 01 năm 2015 quy định chi tiết và hướng dẫn thi hành một số nội dung của Bộ Luật lao động;
G15: ="Căn cứ nhu cầu hoạt động của "&KB_CTy&" và xét khả năng của người lao động;" -> Căn cứ nhu cầu hoạt động của và xét khả năng của người lao động;
F17: Hợp đồng lao động (“HĐLĐ”) này được ký ngày 30 tháng 12 năm 1899 tại Văn phòng DD, địa chỉ , bởi và giữa các bên có đầy đủ tư cách giao kết hợp đồng lao động theo quy định, gồm:
F20: Thông tin | H20: BÊN SỬ DỤNG LAO ĐỘNG (Sau đây gọi là Doanh nghiệp) | M20: NGƯỜI LAO ĐỘNG (Sau đây gọi là NLĐ)
F21: Tên chính thức | H21: =KB_CTy -> 0 | M21: Nhân Viên A
F22: Mã số thuế/CMND | H22: ="Mã số thuế: "&KB_MST -> Mã số thuế: | M22: Số CMND:
E23: Điền chi tiết ngày cấp (nếu muốn) | H23: Ngày cấp: | M23: Ngày cấp:
E24: Điền chi tiết nơi cấp (nếu muốn) | H24: Nơi cấp: | M24: Nơi cấp:
F25: Thông tin liên lạc | H25: ="Điện thoại: "&KB_DT -> Điện thoại: | M25: Điện thoại:
H26: ="Fax: "&KB_Fax -> Fax: | M26: Fax:
H27: ="Email: "&KB_Email -> Email: | M27: Email:
F28: Địa chỉ | H28: =KB_DC -> 0
F29: Người đại diện | H29: =KB_GD -> 0
E30: Điền chi tiết số TKNH (nếu muốn) | F30: TK ngân hàng
F32: Tùy ngữ cảnh cụ thể, mỗi bên được gọi riêng là “Bên” và hai bên được gọi chung là “Các bên”.
F33: Xét rằng:
G34: - Doanh nghiệp có nhu cầu tuyển dụng và sử dụng lao động phục vụ hoạt động sản xuất kinh doanh; và
G35: - NLĐ là cá nhân độc lập, tự thấy rằng có đầy đủ năng lực giao kết hợp đồng lao động và có thể đáp ứng yêu cầu công việc của Doanh nghiệp.
F37: Sau khi bàn bạc thống nhất, các bên đồng ý ký kết Hợp đồng này với các điều khoản và điều kiện cụ thể như sau:
F38: ĐIỀU 1: CÔNG VIỆC VÀ ĐỊA ĐIỂM LÀM VIỆC
F39: 1.1 Công việc:
G40: Mô tả công viêc:
G41: Doanh nghiệp được quyền tạm thời chuyển NLĐ làm công việc khác so với HĐLĐ trong các trường hợp sau:
H42: a. Thiên tai, hỏa hoạn, dịch bệnh;
H43: b. Áp dụng biện pháp ngăn ngừa, khắc phục tai nạn lao động, bệnh nghề nghiệp;
H44: c. Sự cố điện, nước;
H45: d. Do nhu cầu sản xuất, kinh doanh.
G46: Trường hợp NLĐ không chấp nhận thực hiện việc mới sau điều chuyển thì hai bên tiến hành thanh lý hợp đồng trên cơ sở đồng thuận, nhưng Doanh nghiệp đảm bảo phải trả ít nhất 01 tháng lương do thay đổi công việc dẫn đến chấm dứt hợp đồng trước hạn.
F49: 1.2 Địa điểm làm việc của người lao động:
G50: ="Tại trụ sở chính của Doanh nghiệp, địa chỉ: "&KB_DC&", "&KB_TTP&"." -> Tại trụ sở chính của Doanh nghiệp, địa chỉ: , .
G51: Trường hợp Doanh nghiệp có thay đổi địa chỉ trụ sở chính thì NLĐ tiếp tục làm việc theo địa chỉ mới. Trường hợp đặc biệt theo quyết định của Giám đốc Doanh nghiệp, Doanh nghiệp có thể chỉ định NLĐ làm việc tại địa điểm khác địa chỉ nêu trên nhưng phải báo trước ít nhất 03 ngày để NLĐ kịp thời chuẩn bị.
F55: ĐIỀU 2: THỜI HẠN CỦA HỢP ĐỒNG LAO ĐỘNG
F56: Thời hạn của HĐLĐ này được quy định như sau (đánh dấu X vào  tương ứng với loại HĐLĐ mà Doanh nghiệp giao kết với NLĐ tại phần đầu hợp đồng này):
G58: Loại Hợp đồng giao kết | J58: Thời gian thực hiện hợp đồng | L58: Thời điểm bắt đầu | O58: Thời điểm kết thúc
G59: Xác định thời hạn
G60: Không xác định thời hạn
G61: Theo mùa vụ
G62: Theo một công việc nhất định
G64: Đối với hợp đồng xác định thời hạn thử việc: Trong thời hạn 03 ngày trước khi kết thúc thời gian thử việc, Doanh nghiệp phải thông báo cho NLĐ kết quả công việc NLĐ đã làm thử; trường hợp công việc làm thử đạt yêu cầu thì khi kết thúc thời gian thử việc, Doanh nghiệp phải giao kết ngay HĐLĐ với NLĐ.
G66: Thời hạn HĐLĐ quy định tại Điều này chỉ được sửa đổi một lần bằng phụ lục HĐLĐ và không được làm thay đổi loại hợp đồng đã giao kết, trừ trường hợp kéo dài thời hạn HĐLĐ với NLĐ cao tuổi và NLĐ là cán bộ công đoàn không chuyên trách quy định tại Khoản 6 Điều 192 của Bộ luật Lao động.
F69: ĐIỀU 3: MỨC LƯƠNG, HÌNH THỨC TRẢ LƯƠNG, THỜI HẠN TRẢ LƯƠNG, PHỤ CẤP LƯƠNG VÀ CÁC KHOẢN BỔ SUNG KHÁC
F71: 3.1 Mức lương, phụ cấp lương, các khoản bổ sung khác:
G72: a. Mức lương: | I72: 5000000 | J72: đồng/tháng/24 ngày công.
G73: b. Phụ cấp lương:
G74: c. Các khoản bổ sung khác: Theo quy định của Doanh nghiệp.
G75: d. Tiền lương làm thêm giờ: được tính theo đơn giá tiền lương hoặc tiền lương thực trả theo công việc đang làm như sau: - Vào ngày thường, ít nhất bằng 150%; - Vào ngày nghỉ hằng tuần, ít nhất bằng 200%; - Vào ngày nghỉ lễ, tết, ngày nghỉ có hưởng lương, ít nhất bằng 300%.
F79: 3.2 Hình thức trả lương: Bằng tiền mặt Việt Nam đồng.
F80: 3.3 Kỳ hạn trả lương:
G81: a. Kỳ hạn trả lương: Tiền lương được trả tháng một lần. Tiền lương được Doanh nghiệp trả trực tiếp, đẩy đủ và đúng thời hạn cho NLĐ căn cứ vào thời gian làm việc thực tế của NLĐ trong tháng đó. Trường hợp đặc biệt do thiên tai, hỏa hoạn hoặc lý do bất khả kháng khác mà Doanh nghiệp đã tìm mọi biện pháp khắc phục nhưng không thể trả lương đúng thời hạn thì không được trả chậm quá 01 tháng.
G84: b. Thời điểm trả lương: Ngày 10 hàng tháng. Trường hợp thời điểm trả lương trùng ngày lễ, ngày nghỉ theo quy định thì được trả vào ngày làm việc tiếp theo.
F87: ĐIỀU 4: CHẾ ĐỘ NÂNG LƯƠNG:
F88: 4.1 Điều kiện: Theo quy định của Doanh nghiệp.
F89: 4.2 Thời gian: Theo quy định của Doanh nghiệp.
F90: 4.3 Thời điểm: Theo quy định của Doanh nghiệp.
F91: 4.4 Mức lương sau khi nâng: Theo quy định của Doanh nghiệp.
F93: ĐIỀU 5: THỜI GIỜ LÀM VIỆC, THỜI GIỜ NGHỈ NGƠI
F94: Trừ trường hợp đặc biệt theo Quyết định của Giám đốc Doanh nghiệp, thời giờ làm việc thời gian nghỉ ngơi được quy định như sau:
F95: 5.1 Thời giờ làm việc trong ngày:
G96: a. Thời điểm bắt đầu: 08 giờ 00
G97: b. Thời điểm kết thúc: 17 giờ 00
F98: 5.2 Thời giờ làm việc trong tuần: Từ thứ hai đến thứ sáu, sáng thứ bảy hằng tuần.
F99: 5.3 Thời giờ làm thêm giờ: Theo quy định của Doanh nghiệp.
F100: 5.4 Thời gian nghỉ trong giờ làm việc: Làm việc liên tục hai giờ đồng hồ được nghỉ giải lao 10 phút. Nghỉ trưa từ 12 giờ 00 đến 01 giờ 30 phút hàng ngày làm việc.
F102: 5.5 Thời gian nghỉ hằng tuần: Trừ các ngày làm việc theo điều 5.2
F103: 5.6 Thời gian nghỉ hằng năm, nghỉ lễ, tết: Theo quy định hiện hành của Bộ Luật lao động. Trường hợp ngày nghỉ, lễ kéo dài và trùng thứ bảy chủ nhật thì Giám đốc Doanh nghiệp quyết định nghỉ bù, làm bù nhưng vẫn đảm bảo công việc được sắp xếp ổn thỏa, hợp lý.
F105: 5.7 Thời gian nghỉ việc riêng: Theo quy định của Bộ Luật Lao động, Luật Bảo hiểm xã hội hiện hành. Trừ trường hợp nghỉ ốm, lý do sức khỏe đặc biệt thì NLĐ phải có kế hoạch sắp xếp công việc đảm bảo không ảnh hưởng đến bộ phận, phòng ban khác và phải báo trước cho Trưởng phòng nhân sự/Giám đốc ít nhất 03 ngày.
F107: 5.8 Thời gian nghỉ không hưởng lương: Nghỉ việc không báo trước hoặc không có lý do rõ ràng, nghỉ quá số ngày phép năm.
F109: ĐIỀU 6: TRANG BỊ BẢO HỘ LAO ĐỘNG CHO NGƯỜI LAO ĐỘNG
F110: Trong suốt quá trình làm việc tại Doanh nghiệp, NLĐ được trang bị các loại trang phục, trang bị bảo hộ lao động sau đây:
F111: TT | G111: Chủng loại | J111: Số lượng | L111: Chất lượng | N111: Thời hạn sử dụng | P111: Ghi chú
G112: Không phát sinh
F116: ĐIỀU 7: BẢO HIỂM XÃ HỘI, BẢO HIỂM THẤT NGHIỆP VÀ BẢO HIỂM Y TẾ
F117: 7.1 Tỷ lệ đóng: Tính theo mức % tính trên mức đóng bảo hiểm xã hội, bảo hiểm thất nghiệp, bảo hiểm y tế thuộc trách nhiệm của người sử dụng lao động và của người lao động theo quy định của pháp luật về bảo hiểm xã hội, bảo hiểm thất nghiệp, bảo hiểm y tế tại thời điểm phát sinh.
F119: 7.2 Phương thức đóng, thời gian đóng: Doanh nghiệp chịu trách nhiệm đóng phần bảo hiểm của Doanh nghiệp. Phần bảo hiểm thuộc trách nhiệm của NLĐ được NLĐ ủy quyền Doanh nghiệp trừ vào lương hàng tháng và đóng hộ.
F122: ĐIỀU 8: ĐÀO TẠO, BỒI DƯỠNG, NÂNG CAO TRÌNH ĐỘ KỸ NĂNG NGHỀ
F123: Tại từng thời điểm khác nhau và theo Quyết định của Giám đốc Doanh nghiệp, Doanh nghiệp đảm bảo thời gian, kinh phí đào tạo, bồi dưỡng, nâng cao trình độ kỹ năng nghề cho NLĐ trong quá trình làm việc và cống hiến tại Doanh nghiệp.
F126: ĐIỀU 9: BẢO MẬT THÔNG TIN
F127: NLĐ cam kết rằng mọi thông tin nội bộ của Doanh nghiệp gồm báo cáo hàng tuần, hàng tháng, danh sách khách hàng, nhà cung cấp, quản lý điều hành và các thông tin nội bộ khác là thông tin mật. NLĐ cam kết không được tiết lộ, mua bán, trao đổi, chia sẻ cho bên thứ ba dưới bất cứ hình thức nào. Trường hợp Doanh nghiệp có chứng cứ cho rằng NLĐ tiết lộ thông tin ảnh hưởng đến kinh doanh, uy tín, thương hiệu của Doanh nghiệp thì NLĐ phải bồi thường thiệt hại 100%.
F131: ĐIỀU 10: CHẤM DỨT HỢP ĐỒNG LAO ĐỘNG
F132: Hợp đồng lao động này chấm dứt hiệu lực khi và chỉ khi thuộc một trong các trường hợp sau đây:
F133: 10.1 Hết thời hạn ghi tại Điều 2 mà các bên không gia hạn;
F134: 10.2 NLĐ đơn phương chấm dứt hợp đồng trong các trường hợp sau:
G135: a. Bị đánh đập hoặc có lời nói, hành vi nhục mạ, hành vi làm ảnh hưởng đến sức khỏe, nhân phẩm, danh dự hoặc cưỡng bức lao động; bị quấy rối tình dục tại nơi làm việc;
G137: b. Phải nghỉ việc để chăm sóc vợ hoặc chồng, bố đẻ, mẹ đẻ, bố vợ, mẹ vợ hoặc bố chồng, mẹ chồng, con đẻ, con nuôi bị ốm đau, tai nạn;
G139: c. Gia đình gặp khó khăn do thiên tai, hỏa hoạn, địch họa, dịch bệnh hoặc chuyển chỗ ở mà người lao động đã tìm mọi biện pháp nhưng không thể tiếp tục thực hiện hợp đồng lao động.
F141: 10.3 Doanh nghiệp đơn phương chấm dứt hợp đồng trong các trường hợp sau:
G142: a. NLĐ thường xuyên không hoàn thành công việc theo hợp đồng lao động;
G143: b. Lý do bất khả kháng khác thuộc một trong các trường hợp sau đây: (i) Do địch họa, dịch bệnh; (ii) Di dời hoặc thu hẹp địa điểm sản xuất, kinh doanh theo yêu cầu của cơ quan nhà nước có thẩm quyền.
F146: ĐIỀU 11: CÁC ĐIỀU KHOẢN KHÁC
F147: Các điều khoản khác không ghi trong hợp đồng này như trách nhiệm vật chất, bồi thường thiệt hại, kỷ luật lao động, giải quyết tranh chấp lao động và các vấn đề khác có liên quan thì thực hiện theo quy định tại Bộ luật Lao động 2012, tại Nghị định 05/2015/NĐ-CP và các văn bản hướng dẫn thi hành.
F149: Trường hợp các bên tiến hành ký phụ lục hợp đồng thì phụ lục có giá trị thực hiện như hợp đồng. Trường hợp, phụ lục hợp đồng có điều khoản xung đột với hợp đồng này thì áp dụng điều khoản có lợi hơn cho NLĐ.
F151: Hợp đồng này được lập bằng Tiếng Việt, tổng cộng 04 trang được đánh số thứ tự từ 01 đến 04 và lập thành 02 bản có giá trị pháp lý như nhau.
F153: ĐỂ GHI NHẬN CÁC THỎA THUẬN TRONG HỢP ĐỒNG, đại diện có thẩm quyền của các bên đã ký kết Hợp đồng này vào ngày ghi tại phần đầu Hợp đồng.
F155: ĐẠI DIỆN VÀ THAY MẶT DOANH NGHIỆP | L155: ĐẠI DIỆN VÀ THAY MẶT NLĐ
...

Sheet BangLuong
G1: Phụ cấp nào không có thì bạn ẩn đi, nếu nhiều hơn 5 khoản thì các phụ cấp đó sẽ dồn vào cột phụ cấp khác
G2: Phụ cấp không thường xuyên nào không có thì bạn ẩn đi, nếu quá 2 khoản thì khoản thứ 3 trở đi sẽ cộng dồn vào cột Phụ cấp không thường xuyên khác
B5: ="Đơn vị : "&KB_CTy -> Đơn vị :
B6: ="Địa chỉ : "&KB_DC&", "&KB_TTP -> Địa chỉ : ,
B7: ="Mã số thuế : "&KB_MST -> Mã số thuế :
B8: BẢNG LƯƠNG
B9: TỪ THÁNG 1 ĐẾN THÁNG 12
B10: ="Năm "&KB_Nam -> Năm 2026
U11: Đơn vị tính: đồng Việt Nam
B12: Stt | C12: Họ & Tên | D12: Chức vụ | E12: Lương cơ bản | F12: Phụ cấp ăn trưa | G12: Phụ cấp điện thoại | H12: Phụ cấp xăng | I12: Phụ cấp -1 | J12: Phụ cấp -2 | K12: Phụ cấp khác | L12: Phụ cấp không thường xuyên 1 | M12: Phụ cấp không thường xuyên 2 | N12: Phụ cấp không thường xuyên khác | O12: Tổng Thu Nhập | P12: Các khoản trừ | S12: Thực lãnh | T12: Ký nhận | U12: Ghi chú | V12: Không in, không xóa
P13: Bảo hiểm | Q13: TNCN | R13: Khác | V13: Mã số thuế | W13: Số CMND
B16: [1] | C16: [2] | D16: [3] | E16: [4] | F16: [5] | G16: [6] | H16: [7] | I16: [8] | J16: [9] | K16: [10] | L16: [11] | M16: [12] | N16: [13] | O16: [14] | P16: [15] | Q16: [16] | R16: [17] | S16: [18] | T16: [19] | U16: [20] | V16: [21] | W16: [22]
C19: Tổng cộng
S21: , ngày 31 tháng 12 năm 2023
C22: Người lập biểu | S22: Người đại diện theo pháp luật
C23: (Ký, họ tên) | S23: (Ký, họ tên, đóng dấu)
C29: =IF(ISBLANK(KB_TQuy),"",KB_TQuy) | S29: =KB_GD -> 0

Sheet TinhLuong
I1: Phụ cấp nào không có thì bạn ẩn đi, nếu nhiều hơn 5 khoản thì các phụ cấp đó sẽ dồn vào cột phụ cấp khác
I2: Phụ cấp không thường xuyên nào không có thì bạn ẩn đi, nếu quá 2 khoản thì khoản thứ 3 trở đi sẽ cộng dồn vào cột Phụ cấp không thường xuyên khác
A4: BẢNG TÍNH LƯƠNG | AB4: VÙNG TÍNH BẢO HIỂM VÀ THUẾ THU NHẬP CÁ NHÂN
A6: Mã nhân viên | B6: Họ & Tên | C6: Mã số thuế TNCN | D6: Số chứng minh nhân dân | E6: Chức vụ | F6: Lương tính BHXH | G6: Lương cơ bản | H6: Phụ cấp ăn trưa | I6: Phụ cấp điện thoại | J6: Phụ cấp xăng | K6: Phụ cấp nhà ở | L6: Phụ cấp -2 | M6: Phụ cấp khác | N6: Phụ cấp không thường xuyên 1 | O6: Phụ cấp không thường xuyên 2 | P6: Phụ cấp không thường xuyên khác | Q6: Tổng Thu Nhập | R6: Các khoản trừ | U6: Thực lãnh | V6: Định khoản | W6: Loại HĐLĐ | X6: Hình thức trả lương | Y6: Tháng | AB6: Vùng tính bảo hiểm | AH6: Vùng tính thuế TNCN | AP6: Tổng TNCT trả cho cá nhân thuộc diện khấu trừ thuế | AQ6: Ủy quyền quyết toán thuế TNCN | AR6: Vùng công đoàn
R7: Bảo hiểm | S7: TNCN | T7: Khác | AB7: Bảo hiểm xã hội | AD7: Bảo hiểm y tế | AF7: Bảo hiểm thất nghiệp | AH7: TN chịu thuế | AI7: Các khoản giảm trừ | AN7: TN tính thuế | AO7: Thuế TNCN | AR7: Kinh phí công đoàn | AS7: Đoàn phí
AI8: Bảo hiểm bắt buộc | AJ8: Giảm trừ gia cảnh | AM8: Khác | AR8: 0.02 | AS8: 0.01
AB9: Công ty | AC9: NLĐ | AD9: Công ty | AE9: NLĐ | AF9: Công ty | AG9: NLĐ | AJ9: Bản thân | AK9: Người phụ thuộc | AR9: Công ty | AS9: NLĐ
A10: [1] | B10: [2] | C10: [3] | D10: [4] | E10: [5] | F10: [6] | G10: [7] | H10: [8] | I10: [9] | J10: [10] | K10: [11] | L10: [12] | M10: [13] | N10: [14] | O10: [15] | P10: [16] | Q10: [17] | R10: [18] | S10: [19] | T10: [20] | U10: [21] | V10: [22] | W10: [23] | X10: [24] | Y10: [25] | AK10: Số lg | AL10: Số tiền

Sheet CDSPS
A1: 1
A2: 9
C5: ="Đơn vị : "&KB_CTy -> Đơn vị : | H5: Mẫu số S06 – DN
C6: ="Địa chỉ : "&KB_DC -> Địa chỉ : | H6: (Kèm theo Thông tư số 99/2025/TT-BTC
C7: ="Mã số thuế : "&KB_MST -> Mã số thuế : | H7: Ngày 27/10/2025 của Bộ trưởng Bộ Tài chính)
C8: BẢNG CÂN ĐỐI SỐ PHÁT SINH
E9: TỪ THÁNG 1 | F9: ĐẾN THÁNG 9
E10: NĂM | F10: 2026
J11: Đơn vị tính: đồng Việt Nam
C12: Số hiệu tài khoản | D12: Tên tài khoản kế toán | E12: Số dư đầu kỳ | G12: Số phát sinh trong kỳ | I12: Số dư cuối kỳ
E13: Nợ | F13: Có | G13: Nợ | H13: Có | I13: Nợ | J13: Có | K13: K.In
C14: [1] | D14: [2] | E14: [3] | F14: [4] | G14: [5] | H14: [6] | I14: [7] | J14: [8] | K14: K.Xóa
C15: 111 | D15: TIỀN MẶT | E15: 0 | F15: 0 | G15: 0 | H15: 0 | I15: 0 | J15: 0 | K15: 0
C16: 1111 | D16: Tiền Việt Nam | E16: 0 | F16: 0 | G16: 0 | H16: 0 | I16: 0 | J16: 0 | K16: 0
C17: 1112 | D17: Ngoại tệ | E17: 0 | F17: 0 | G17: 0 | H17: 0 | I17: 0 | J17: 0 | K17: 0
C18: 1113 | D18: Vàng tiền tệ | E18: 0 | F18: 0 | G18: 0 | H18: 0 | I18: 0 | J18: 0 | K18: 0
C19: 112 | D19: TIỀN GỬI KHÔNG KỲ HẠN | E19: 0 | F19: 0 | G19: 0 | H19: 0 | I19: 0 | J19: 0 | K19: 0
C20: 1121 | D20: Tiền gửi không kỳ hạn Việt Nam | E20: 0 | F20: 0 | G20: 0 | H20: 0 | I20: 0 | J20: 0 | K20: 0
C21: 1121-01 | D21: Tiền gữi không kỳ hạn Việt Nam Đồng | E21: 0 | F21: 0 | G21: 0 | H21: 0 | I21: 0 | J21: 0 | K21: 0
C22: 1121-02 | D22: Tiền gữi không kỳ hạn Việt Nam Đồng | E22: 0 | F22: 0 | G22: 0 | H22: 0 | I22: 0 | J22: 0 | K22: 0
C23: 1121-03 | D23: Tiền gữi không kỳ hạn Việt Nam Đồng | E23: 0 | F23: 0 | G23: 0 | H23: 0 | I23: 0 | J23: 0 | K23: 0
C24: 1121-04 | D24: Tiền gữi không kỳ hạn Việt Nam Đồng | E24: 0 | F24: 0 | G24: 0 | H24: 0 | I24: 0 | J24: 0 | K24: 0
C25: 1121-05 | D25: Tiền gữi không kỳ hạn Việt Nam Đồng | E25: 0 | F25: 0 | G25: 0 | H25: 0 | I25: 0 | J25: 0 | K25: 0
C26: 1121-06 | D26: Tiền gữi không kỳ hạn Việt Nam Đồng | E26: 0 | F26: 0 | G26: 0 | H26: 0 | I26: 0 | J26: 0 | K26: 0
C27: 1121-07 | D27: Tiền gữi không kỳ hạn Việt Nam Đồng | E27: 0 | F27: 0 | G27: 0 | H27: 0 | I27: 0 | J27: 0 | K27: 0
C28: 1121-08 | D28: Tiền gữi không kỳ hạn Việt Nam Đồng | E28: 0 | F28: 0 | G28: 0 | H28: 0 | I28: 0 | J28: 0 | K28: 0
C29: 1121-09 | D29: Tiền gữi không kỳ hạn Việt Nam Đồng | E29: 0 | F29: 0 | G29: 0 | H29: 0 | I29: 0 | J29: 0 | K29: 0
C30: 1121-10 | D30: Tiền gữi không kỳ hạn Việt Nam Đồng | E30: 0 | F30: 0 | G30: 0 | H30: 0 | I30: 0 | J30: 0 | K30: 0
C31: 1122 | D31: Tiền gửi không kỳ hạn ngoại tệ | E31: 0 | F31: 0 | G31: 0 | H31: 0 | I31: 0 | J31: 0 | K31: 0
C32: 1122-01 | D32: Tiền gữi không kỳ hạn ngoại tệ | E32: 0 | F32: 0 | G32: 0 | H32: 0 | I32: 0 | J32: 0 | K32: 0
C33: 1122-02 | D33: Tiền gữi không kỳ hạn ngoại tệ | E33: 0 | F33: 0 | G33: 0 | H33: 0 | I33: 0 | J33: 0 | K33: 0
C34: 1122-03 | D34: Tiền gữi không kỳ hạn ngoại tệ | E34: 0 | F34: 0 | G34: 0 | H34: 0 | I34: 0 | J34: 0 | K34: 0
C35: 1122-04 | D35: Tiền gữi không kỳ hạn ngoại tệ | E35: 0 | F35: 0 | G35: 0 | H35: 0 | I35: 0 | J35: 0 | K35: 0
C36: 1122-05 | D36: Tiền gữi không kỳ hạn ngoại tệ | E36: 0 | F36: 0 | G36: 0 | H36: 0 | I36: 0 | J36: 0 | K36: 0
C37: 1122-06 | D37: Tiền gữi không kỳ hạn ngoại tệ | E37: 0 | F37: 0 | G37: 0 | H37: 0 | I37: 0 | J37: 0 | K37: 0
C38: 1122-07 | D38: Tiền gữi không kỳ hạn ngoại tệ | E38: 0 | F38: 0 | G38: 0 | H38: 0 | I38: 0 | J38: 0 | K38: 0
C39: 1122-08 | D39: Tiền gữi không kỳ hạn ngoại tệ | E39: 0 | F39: 0 | G39: 0 | H39: 0 | I39: 0 | J39: 0 | K39: 0
C40: 1122-09 | D40: Tiền gữi không kỳ hạn ngoại tệ | E40: 0 | F40: 0 | G40: 0 | H40: 0 | I40: 0 | J40: 0 | K40: 0
C41: 1122-10 | D41: Tiền gữi không kỳ hạn ngoại tệ | E41: 0 | F41: 0 | G41: 0 | H41: 0 | I41: 0 | J41: 0 | K41: 0
C42: 1123 | D42: Vàng tiền tệ | E42: 0 | F42: 0 | G42: 0 | H42: 0 | I42: 0 | J42: 0 | K42: 0
C43: 113 | D43: TIỀN ĐANG CHUYỂN | E43: 0 | F43: 0 | G43: 0 | H43: 0 | I43: 0 | J43: 0 | K43: 0
C44: 1131 | D44: Tiền Việt Nam | E44: 0 | F44: 0 | G44: 0 | H44: 0 | I44: 0 | J44: 0 | K44: 0
C45: 1132 | D45: Ngoại tệ | E45: 0 | F45: 0 | G45: 0 | H45: 0 | I45: 0 | J45: 0 | K45: 0
C46: 121 | D46: CHỨNG KHOÁN KINH DOANH | E46: 0 | F46: 0 | G46: 0 | H46: 0 | I46: 0 | J46: 0 | K46: 0
C47: 1211 | D47: Cổ phiếu | E47: 0 | F47: 0 | G47: 0 | H47: 0 | I47: 0 | J47: 0 | K47: 0
C48: 1212 | D48: Trái phiếu | E48: 0 | F48: 0 | G48: 0 | H48: 0 | I48: 0 | J48: 0 | K48: 0
C49: 1218 | D49: Chứng khoán và công cụ tài chính khác | E49: 0 | F49: 0 | G49: 0 | H49: 0 | I49: 0 | J49: 0 | K49: 0
C50: 128 | D50: ĐẦU TƯ NẮM GIỮ ĐẾN NGÀY ĐÁO HẠN | E50: 0 | F50: 0 | G50: 0 | H50: 0 | I50: 0 | J50: 0 | K50: 0
C51: 1281 | D51: Tiền gửi có kỳ hạn | E51: 0 | F51: 0 | G51: 0 | H51: 0 | I51: 0 | J51: 0 | K51: 0
C52: 12811 | D52: Tiền gửi có kỳ hạn - ngắn hạn <= 3 tháng | E52: 0 | F52: 0 | G52: 0 | H52: 0 | I52: 0 | J52: 0 | K52: 0
C53: 12812 | D53: Tiền gửi có kỳ hạn - ngắn hạn <= 12 tháng | E53: 0 | F53: 0 | G53: 0 | H53: 0 | I53: 0 | J53: 0 | K53: 0
... C61: 131 | D61: PHẢI THU CỦA KHÁCH HÀNG | E61: 0 | F61: 0 | G61: 0 | H61: 0 | I61: 0 | J61: 0 | K61: 0
C62: 131-01 | D62: Phải thu của khách hàng | E62: 0 | F62: 0 | G62: 0 | H62: 0 | I62: 0 | J62: 0 | K62: 0
C63: 131-02 | D63: Phải thu của khách hàng | E63: 0 | F63: 0 | G63: 0 | H63: 0 | I63: 0 | J63: 0 | K63: 0
C64: 131-03 | D64: Phải thu của khách hàng | E64: 0 | F64: 0 | G64: 0 | H64: 0 | I64: 0 | J64: 0 | K64: 0
C65: 131-04 | D65: Phải thu của khách hàng | E65: 0 | F65: 0 | G65: 0 | H65: 0 | I65: 0 | J65: 0 | K65: 0
C66: 131-05 | D66: Phải thu của khách hàng | E66: 0 | F66: 0 | G66: 0 | H66: 0 | I66: 0 | J66: 0 | K66: 0
C67: 131-06 | D67: Phải thu của khách hàng | E67: 0 | F67: 0 | G67: 0 | H67: 0 | I67: 0 | J67: 0 | K67: 0
C68: 131-07 | D68: Phải thu của khách hàng | E68: 0 | F68: 0 | G68: 0 | H68: 0 | I68: 0 | J68: 0 | K68: 0
C69: 131-08 | D69: Phải thu của khách hàng | E69: 0 | F69: 0 | G69: 0 | H69: 0 | I69: 0 | J69: 0 | K69: 0
C70: 131-09 | D70: Phải thu của khách hàng | E70: 0 | F70: 0 | G70: 0 | H70: 0 | I70: 0 | J70: 0 | K70: 0
C71: 131-10 | D71: Phải thu của khách hàng | E71: 0 | F71: 0 | G71: 0 | H71: 0 | I71: 0 | J71: 0 | K71: 0
C72: 131-11 | D72: Phải thu của khách hàng | E72: 0 | F72: 0 | G72: 0 | H72: 0 | I72: 0 | J72: 0 | K72: 0
C73: 131-12 | D73: Phải thu của khách hàng | E73: 0 | F73: 0 | G73: 0 | H73: 0 | I73: 0 | J73: 0 | K73: 0
... C127: 131-66 | D127: Phải thu của khách hàng | E127: 0 | F127: 0 | G127: 0 | H127: 0 | I127: 0 | J127: 0 | K127: 0
C128: 133 | D128: THUẾ GTGT ĐÃ KHẤU TRỪ | E128: 0 | F128: 0 | G128: 0 | H128: 0 | I128: 0 | J128: 0 | K128: 0
C129: 1331 | D129: Thuế GTGT được khấu trừ của hàng hóa, dịch vụ | E129: 0 | F129: 0 | G129: 0 | H129: 0 | I129: 0 | J129: 0 | K129: 0
C130: 1332 | D130: Thuế GTGT được khấu trừ của TSCĐ | E130: 0 | F130: 0 | G130: 0 | H130: 0 | I130: 0 | J130: 0 | K130: 0
C131: 133CN | D131: Thuế GTGT được khấu trừ của chi nhánh | E131: 0 | F131: 0 | G131: 0 | H131: 0 | I131: 0 | J131: 0 | K131: 0
C132: 136 | D132: PHẢI THU NỘI BỘ | E132: 0 | F132: 0 | G132: 0 | H132: 0 | I132: 0 | J132: 0 | K132: 0
C133: 1361 | D133: Vốn kinh doanh ở các đơn vị trực thuộc | E133: 0 | F133: 0 | G133: 0 | H133: 0 | I133: 0 | J133: 0 | K133: 0
C134: 1362 | D134: Phải thu nội bộ về chênh lệch tỷ giá | E134: 0 | F134: 0 | G134: 0 | H134: 0 | I134: 0 | J134: 0 | K134: 0
C135: 1363 | D135: Phải thu nội bộ về chi phí đi vay đủ điều kiện được vốn hoá | E135: 0 | F135: 0 | G135: 0 | H135: 0 | I135: 0 | J135: 0 | K135: 0
C136: 1368 | D136: Phải thu nội bộ khác | E136: 0 | F136: 0 | G136: 0 | H136: 0 | I136: 0 | J136: 0 | K136: 0
C137: 138 | D137: PHẢI THU KHÁC | E137: 0 | F137: 0 | G137: 0 | H137: 0 | I137: 0 | J137: 0 | K137: 0 | L137: 0
C138: 1381 | D138: Tài sản thiếu chờ xử lý | E138: 0 | F138: 0 | G138: 0 | H138: 0 | I138: 0 | J138: 0 | K138: 0
C139: 1383 | D139: Thuế TTĐB của hàng nhập khẩu | E139: 0 | F139: 0 | G139: 0 | H139: 0 | I139: 0 | J139: 0 | K139: 0
C140: 1388 | D140: Phải thu khác | E140: 0 | F140: 0 | G140: 0 | H140: 0 | I140: 0 | J140: 0 | K140: 0
C141: 13881 | D141: Phải thu khác - mua vào | E141: 0 | F141: 0 | G141: 0 | H141: 0 | I141: 0 | J141: 0 | K141: 0
C142: 13888 | D142: Phải thu khác | E142: 0 | F142: 0 | G142: 0 | H142: 0 | I142: 0 | J142: 0 | K142: 0
C143: 141 | D143: TẠM ỨNG | E143: 0 | F143: 0 | G143: 0 | H143: 0 | I143: 0 | J143: 0 | K143: 0
C144: 151 | D144: HÀNG MUA ĐANG ĐI ĐƯỜNG | E144: 0 | F144: 0 | G144: 0 | H144: 0 | I144: 0 | J144: 0 | K144: 0
C145: 152 | D145: NGUYÊN LIỆU, VẬT LIỆU | E145: 0 | F145: 0 | G145: 0 | H145: 0 | I145: 0 | J145: 0 | K145: 0 | L145: 0
C146: 1521 | D146: Nguyên liệu, vật liệu chính | E146: 0 | F146: 0 | G146: 0 | H146: 0 | I146: 0 | J146: 0 | K146: 0
C147: 1522 | D147: Vật liệu phụ | E147: 0 | F147: 0 | G147: 0 | H147: 0 | I147: 0 | J147: 0 | K147: 0
C148: 1523 | D148: Nhiên liệu | E148: 0 | F148: 0 | G148: 0 | H148: 0 | I148: 0 | J148: 0 | K148: 0
C149: 1524 | D149: Vật tư thay thế | E149: 0 | F149: 0 | G149: 0 | H149: 0 | I149: 0 | J149: 0 | K149: 0
C150: 1525 | D150: Vật liệu và thiết bị xây dựng cơ bản | E150: 0 | F150: 0 | G150: 0 | H150: 0 | I150: 0 | J150: 0 | K150: 0
C151: 153 | D151: CÔNG CỤ, DỤNG CỤ | E151: 0 | F151: 0 | G151: 0 | H151: 0 | I151: 0 | J151: 0 | K151: 0 | L151: 0
C152: 1531 | D152: Công cụ, dụng cụ | E152: 0 | F152: 0 | G152: 0 | H152: 0 | I152: 0 | J152: 0 | K152: 0
C153: 1532 | D153: Bao bì luân chuyển | E153: 0 | F153: 0 | G153: 0 | H153: 0 | I153: 0 | J153: 0 | K153: 0
C154: 1533 | D154: Đồ dùng cho thuê | E154: 0 | F154: 0 | G154: 0 | H154: 0 | I154: 0 | J154: 0 | K154: 0
C155: 1534 | D155: Thiết bị, phụ tùng thay thế | E155: 0 | F155: 0 | G155: 0 | H155: 0 | I155: 0 | J155: 0 | K155: 0
C156: 154 | D156: CHI PHÍ SẢN XUẤT, KINH DOANH DỞ DANG | E156: 0 | F156: 0 | G156: 0 | H156: 0 | I156: 0 | J156: 0 | K156: 0 | L156: 0
C157: 1541 | D157: Xây lắp | E157: 0 | F157: 0 | G157: 0 | H157: 0 | I157: 0 | J157: 0 | K157: 0
C158: 1542 | D158: Sản phẩm khác | E158: 0 | F158: 0 | G158: 0 | H158: 0 | I158: 0 | J158: 0 | K158: 0
C159: 1543 | D159: Dịch vụ | E159: 0 | F159: 0 | G159: 0 | H159: 0 | I159: 0 | J159: 0 | K159: 0
C160: 155 | D160: SẢN PHẨM | E160: 0 | F160: 0 | G160: 0 | H160: 0 | I160: 0 | J160: 0 | K160: 0 | L160: 0
C161: 1551 | D161: Thành phẩm | E161: 0 | F161: 0 | G161: 0 | H161: 0 | I161: 0 | J161: 0 | K161: 0
C162: 1552 | D162: Bán thành phẩm | E162: 0 | F162: 0 | G162: 0 | H162: 0 | I162: 0 | J162: 0 | K162: 0
...

Sheet CDSPS_NT
C5: ="Đơn vị : "&KB_CTy -> Đơn vị : | I5: Mẫu số S06 – DN
C6: ="Địa chỉ : "&KB_DC -> Địa chỉ : | I6: (Kèm theo Thông tư số 99/2025/TT-BTC
C7: ="Mã số thuế : "&KB_MST -> Mã số thuế : | I7: Ngày 27/10/2025 của Bộ trưởng Bộ Tài chính)
C8: BẢNG CÂN ĐỐI SỐ PHÁT SINH NĂM TRƯỚC
E9: TỪ THÁNG 1 | F9: ĐẾN THÁNG 12
E10: NĂM | F10: =+CDSPS!F10-1 -> 2025
J11: Đơn vị tính: đồng Việt Nam
C12: Số hiệu tài khoản | D12: Tên tài khoản kế toán | E12: Số dư đầu kỳ | G12: Số phát sinh trong kỳ | I12: Số dư cuối kỳ
E13: Nợ | F13: Có | G13: Nợ | H13: Có | I13: Nợ | J13: Có | K13: K.In
C14: [1] | D14: [2] | E14: [3] | F14: [4] | G14: [5] | H14: [6] | I14: [7] | J14: [8] | K14: K.Xóa
C15: 111 | D15: TIỀN MẶT | E15: 0 | F15: 0 | G15: 0 | H15: 0 | I15: 0 | J15: 0 | K15: 0
C16: 1111 | D16: Tiền Việt Nam | E16: 0 | F16: 0 | G16: 0 | H16: 0 | I16: 0 | J16: 0 | K16: 0
C17: 1112 | D17: Ngoại tệ | E17: 0 | F17: 0 | G17: 0 | H17: 0 | I17: 0 | J17: 0 | K17: 0
C18: 1113 | D18: Vàng tiền tệ | E18: 0 | F18: 0 | G18: 0 | H18: 0 | I18: 0 | J18: 0 | K18: 0
C19: 112 | D19: TIỀN GỬI KHÔNG KỲ HẠN | E19: 0 | F19: 0 | G19: 0 | H19: 0 | I19: 0 | J19: 0 | K19: 0
C20: 1121 | D20: Tiền gửi không kỳ hạn Việt Nam | E20: 0 | F20: 0 | G20: 0 | H20: 0 | I20: 0 | J20: 0 | K20: 0
C21: 1121-01 | D21: Tiền gữi không kỳ hạn Việt Nam Đồng | E21: 0 | F21: 0 | G21: 0 | H21: 0 | I21: 0 | J21: 0 | K21: 0
C22: 1121-02 | D22: Tiền gữi không kỳ hạn Việt Nam Đồng | E22: 0 | F22: 0 | G22: 0 | H22: 0 | I22: 0 | J22: 0 | K22: 0
C23: 1121-03 | D23: Tiền gữi không kỳ hạn Việt Nam Đồng | E23: 0 | F23: 0 | G23: 0 | H23: 0 | I23: 0 | J23: 0 | K23: 0
C24: 1121-04 | D24: Tiền gữi không kỳ hạn Việt Nam Đồng | E24: 0 | F24: 0 | G24: 0 | H24: 0 | I24: 0 | J24: 0 | K24: 0
C25: 1121-05 | D25: Tiền gữi không kỳ hạn Việt Nam Đồng | E25: 0 | F25: 0 | G25: 0 | H25: 0 | I25: 0 | J25: 0 | K25: 0
C26: 1121-06 | D26: Tiền gữi không kỳ hạn Việt Nam Đồng | E26: 0 | F26: 0 | G26: 0 | H26: 0 | I26: 0 | J26: 0 | K26: 0
C27: 1121-07 | D27: Tiền gữi không kỳ hạn Việt Nam Đồng | E27: 0 | F27: 0 | G27: 0 | H27: 0 | I27: 0 | J27: 0 | K27: 0
C28: 1121-08 | D28: Tiền gữi không kỳ hạn Việt Nam Đồng | E28: 0 | F28: 0 | G28: 0 | H28: 0 | I28: 0 | J28: 0 | K28: 0
C29: 1121-09 | D29: Tiền gữi không kỳ hạn Việt Nam Đồng | E29: 0 | F29: 0 | G29: 0 | H29: 0 | I29: 0 | J29: 0 | K29: 0
C30: 1121-10 | D30: Tiền gữi không kỳ hạn Việt Nam Đồng | E30: 0 | F30: 0 | G30: 0 | H30: 0 | I30: 0 | J30: 0 | K30: 0
C31: 1122 | D31: Tiền gửi không kỳ hạn ngoại tệ | E31: 0 | F31: 0 | G31: 0 | H31: 0 | I31: 0 | J31: 0 | K31: 0
C32: 1122-01 | D32: Tiền gữi không kỳ hạn ngoại tệ | E32: 0 | F32: 0 | G32: 0 | H32: 0 | I32: 0 | J32: 0 | K32: 0
C33: 1122-02 | D33: Tiền gữi không kỳ hạn ngoại tệ | E33: 0 | F33: 0 | G33: 0 | H33: 0 | I33: 0 | J33: 0 | K33: 0
C34: 1122-03 | D34: Tiền gữi không kỳ hạn ngoại tệ | E34: 0 | F34: 0 | G34: 0 | H34: 0 | I34: 0 | J34: 0 | K34: 0
C35: 1122-04 | D35: Tiền gữi không kỳ hạn ngoại tệ | E35: 0 | F35: 0 | G35: 0 | H35: 0 | I35: 0 | J35: 0 | K35: 0
C36: 1122-05 | D36: Tiền gữi không kỳ hạn ngoại tệ | E36: 0 | F36: 0 | G36: 0 | H36: 0 | I36: 0 | J36: 0 | K36: 0
C37: 1122-06 | D37: Tiền gữi không kỳ hạn ngoại tệ | E37: 0 | F37: 0 | G37: 0 | H37: 0 | I37: 0 | J37: 0 | K37: 0
C38: 1122-07 | D38: Tiền gữi không kỳ hạn ngoại tệ | E38: 0 | F38: 0 | G38: 0 | H38: 0 | I38: 0 | J38: 0 | K38: 0
C39: 1122-08 | D39: Tiền gữi không kỳ hạn ngoại tệ | E39: 0 | F39: 0 | G39: 0 | H39: 0 | I39: 0 | J39: 0 | K39: 0
C40: 1122-09 | D40: Tiền gữi không kỳ hạn ngoại tệ | E40: 0 | F40: 0 | G40: 0 | H40: 0 | I40: 0 | J40: 0 | K40: 0
C41: 1122-10 | D41: Tiền gữi không kỳ hạn ngoại tệ | E41: 0 | F41: 0 | G41: 0 | H41: 0 | I41: 0 | J41: 0 | K41: 0
C42: 1123 | D42: Vàng tiền tệ | E42: 0 | F42: 0 | G42: 0 | H42: 0 | I42: 0 | J42: 0 | K42: 0
C43: 113 | D43: TIỀN ĐANG CHUYỂN | E43: 0 | F43: 0 | G43: 0 | H43: 0 | I43: 0 | J43: 0 | K43: 0
C44: 1131 | D44: Tiền Việt Nam | E44: 0 | F44: 0 | G44: 0 | H44: 0 | I44: 0 | J44: 0 | K44: 0
C45: 1132 | D45: Ngoại tệ | E45: 0 | F45: 0 | G45: 0 | H45: 0 | I45: 0 | J45: 0 | K45: 0
C46: 121 | D46: CHỨNG KHOÁN KINH DOANH | E46: 0 | F46: 0 | G46: 0 | H46: 0 | I46: 0 | J46: 0 | K46: 0
C47: 1211 | D47: Cổ phiếu | E47: 0 | F47: 0 | G47: 0 | H47: 0 | I47: 0 | J47: 0 | K47: 0
C48: 1212 | D48: Trái phiếu | E48: 0 | F48: 0 | G48: 0 | H48: 0 | I48: 0 | J48: 0 | K48: 0
C49: 1218 | D49: Chứng khoán và công cụ tài chính khác | E49: 0 | F49: 0 | G49: 0 | H49: 0 | I49: 0 | J49: 0 | K49: 0
C50: 128 | D50: ĐẦU TƯ NẮM GIỮ ĐẾN NGÀY ĐÁO HẠN | E50: 0 | F50: 0 | G50: 0 | H50: 0 | I50: 0 | J50: 0 | K50: 0
C51: 1281 | D51: Tiền gửi có kỳ hạn | E51: 0 | F51: 0 | G51: 0 | H51: 0 | I51: 0 | J51: 0 | K51: 0
C52: 12811 | D52: Tiền gửi có kỳ hạn - ngắn hạn <= 3 tháng | E52: 0 | F52: 0 | G52: 0 | H52: 0 | I52: 0 | J52: 0 | K52: 0
C53: 12812 | D53: Tiền gửi có kỳ hạn - ngắn hạn <= 12 tháng | E53: 0 | F53: 0 | G53: 0 | H53: 0 | I53: 0 | J53: 0 | K53: 0
... C61: 131 | D61: PHẢI THU CỦA KHÁCH HÀNG | E61: 0 | F61: 0 | G61: 0 | H61: 0 | I61: 0 | J61: 0 | K61: 0
C62: 131-01 | D62: Phải thu của khách hàng | E62: 0 | F62: 0 | G62: 0 | H62: 0 | I62: 0 | J62: 0 | K62: 0
C63: 131-02 | D63: Phải thu của khách hàng | E63: 0 | F63: 0 | G63: 0 | H63: 0 | I63: 0 | J63: 0 | K63: 0
C64: 131-03 | D64: Phải thu của khách hàng | E64: 0 | F64: 0 | G64: 0 | H64: 0 | I64: 0 | J64: 0 | K64: 0
C65: 131-04 | D65: Phải thu của khách hàng | E65: 0 | F65: 0 | G65: 0 | H65: 0 | I65: 0 | J65: 0 | K65: 0
C66: 131-05 | D66: Phải thu của khách hàng | E66: 0 | F66: 0 | G66: 0 | H66: 0 | I66: 0 | J66: 0 | K66: 0
C67: 131-06 | D67: Phải thu của khách hàng | E67: 0 | F67: 0 | G67: 0 | H67: 0 | I67: 0 | J67: 0 | K67: 0
C68: 131-07 | D68: Phải thu của khách hàng | E68: 0 | F68: 0 | G68: 0 | H68: 0 | I68: 0 | J68: 0 | K68: 0
C69: 131-08 | D69: Phải thu của khách hàng | E69: 0 | F69: 0 | G69: 0 | H69: 0 | I69: 0 | J69: 0 | K69: 0
C70: 131-09 | D70: Phải thu của khách hàng | E70: 0 | F70: 0 | G70: 0 | H70: 0 | I70: 0 | J70: 0 | K70: 0
C71: 131-10 | D71: Phải thu của khách hàng | E71: 0 | F71: 0 | G71: 0 | H71: 0 | I71: 0 | J71: 0 | K71: 0
C72: 131-11 | D72: Phải thu của khách hàng | E72: 0 | F72: 0 | G72: 0 | H72: 0 | I72: 0 | J72: 0 | K72: 0
C73: 131-12 | D73: Phải thu của khách hàng | E73: 0 | F73: 0 | G73: 0 | H73: 0 | I73: 0 | J73: 0 | K73: 0
... C127: 131-66 | D127: Phải thu của khách hàng | E127: 0 | F127: 0 | G127: 0 | H127: 0 | I127: 0 | J127: 0 | K127: 0
C128: 133 | D128: THUẾ GTGT ĐƯỢC KHẤU TRỪ | E128: 0 | F128: 0 | G128: 0 | H128: 0 | I128: 0 | J128: 0 | K128: 0
C129: 1331 | D129: Thuế GTGT được khấu trừ của hàng hóa - dịch vụ | E129: 0 | F129: 0 | G129: 0 | H129: 0 | I129: 0 | J129: 0 | K129: 0
C130: 1332 | D130: Thuế GTGT được khấu trừ của TSCĐ | E130: 0 | F130: 0 | G130: 0 | H130: 0 | I130: 0 | J130: 0 | K130: 0
C131: 133CN | D131: Thuế GTGT được khấu trừ của chi nhánh | E131: 0 | F131: 0 | G131: 0 | H131: 0 | I131: 0 | J131: 0 | K131: 0
C132: 136 | D132: PHẢI THU NỘI BỘ | E132: 0 | F132: 0 | G132: 0 | H132: 0 | I132: 0 | J132: 0 | K132: 0
C133: 1361 | D133: Vốn kinh doanh ở các đơn vị trực thuộc | E133: 0 | F133: 0 | G133: 0 | H133: 0 | I133: 0 | J133: 0 | K133: 0
C134: 1362 | D134: Phải thu nội bộ về chênh lệch tỷ giá | E134: 0 | F134: 0 | G134: 0 | H134: 0 | I134: 0 | J134: 0 | K134: 0
C135: 1363 | D135: Phải thu nội bộ về chi phí đi vay đủ điều kiện được vốn hoá | E135: 0 | F135: 0 | G135: 0 | H135: 0 | I135: 0 | J135: 0 | K135: 0
C136: 1368 | D136: Phải thu nội bộ khác | E136: 0 | F136: 0 | G136: 0 | H136: 0 | I136: 0 | J136: 0 | K136: 0
C137: 138 | D137: PHẢI THU KHÁC | E137: 0 | F137: 0 | G137: 0 | H137: 0 | I137: 0 | J137: 0 | K137: 0
C138: 1381 | D138: Tài sản thiếu chờ xử lý | E138: 0 | F138: 0 | G138: 0 | H138: 0 | I138: 0 | J138: 0 | K138: 0
C139: 1383 | D139: Thuế TTĐB của hàng nhập khẩu | E139: 0 | F139: 0 | G139: 0 | H139: 0 | I139: 0 | J139: 0 | K139: 0
C140: 1388 | D140: Phải thu khác | E140: 0 | F140: 0 | G140: 0 | H140: 0 | I140: 0 | J140: 0 | K140: 0
C141: 13881 | D141: Phải thu khác - mua vào | E141: 0 | F141: 0 | G141: 0 | H141: 0 | I141: 0 | J141: 0 | K141: 0
C142: 13888 | D142: Phải thu khác | E142: 0 | F142: 0 | G142: 0 | H142: 0 | I142: 0 | J142: 0 | K142: 0
C143: 141 | D143: TẠM ỨNG | E143: 0 | F143: 0 | G143: 0 | H143: 0 | I143: 0 | J143: 0 | K143: 0
... C233: 331 | D233: PHẢI TRẢ CHO NGƯỜI BÁN | E233: 0 | F233: 0 | G233: 0 | H233: 0 | I233: 0 | J233: 0 | K233: 0
C234: 331-01 | D234: Phải trả cho người bán | E234: 0 | F234: 0 | G234: 0 | H234: 0 | I234: 0 | J234: 0 | K234: 0
C235: 331-02 | D235: Phải trả cho người bán | E235: 0 | F235: 0 | G235: 0 | H235: 0 | I235: 0 | J235: 0 | K235: 0
C236: 331-03 | D236: Phải trả cho người bán | E236: 0 | F236: 0 | G236: 0 | H236: 0 | I236: 0 | J236: 0 | K236: 0
C237: 331-04 | D237: Phải trả cho người bán | E237: 0 | F237: 0 | G237: 0 | H237: 0 | I237: 0 | J237: 0 | K237: 0
C238: 331-05 | D238: Phải trả cho người bán | E238: 0 | F238: 0 | G238: 0 | H238: 0 | I238: 0 | J238: 0 | K238: 0
C239: 331-06 | D239: Phải trả cho người bán | E239: 0 | F239: 0 | G239: 0 | H239: 0 | I239: 0 | J239: 0 | K239: 0
C240: 331-07 | D240: Phải trả cho người bán | E240: 0 | F240: 0 | G240: 0 | H240: 0 | I240: 0 | J240: 0 | K240: 0
C241: 331-08 | D241: Phải trả cho người bán | E241: 0 | F241: 0 | G241: 0 | H241: 0 | I241: 0 | J241: 0 | K241: 0
C242: 331-09 | D242: Phải trả cho người bán | E242: 0 | F242: 0 | G242: 0 | H242: 0 | I242: 0 | J242: 0 | K242: 0
C243: 331-10 | D243: Phải trả cho người bán | E243: 0 | F243: 0 | G243: 0 | H243: 0 | I243: 0 | J243: 0 | K243: 0
C244: 331-11 | D244: Phải trả cho người bán | E244: 0 | F244: 0 | G244: 0 | H244: 0 | I244: 0 | J244: 0 | K244: 0
C245: 331-12 | D245: Phải trả cho người bán | E245: 0 | F245: 0 | G245: 0 | H245: 0 | I245: 0 | J245: 0 | K245: 0
... C283: 331-50 | D283: Phải trả cho người bán | E283: 0 | F283: 0 | G283: 0 | H283: 0 | I283: 0 | J283: 0 | K283: 0
C284: 332 | D284: PHẢI TRẢ CỔ TỨC, LỢI NHUẬN | E284: 0 | F284: 0 | G284: 0 | H284: 0 | I284: 0 | J284: 0 | K284: 0
C285: 333 | D285: THUẾ VÀ CÁC KHOẢN PHẢI NỘP NHÀ NƯỚC | E285: 0 | F285: 0 | G285: 0 | H285: 0 | I285: 0 | J285: 0 | K285: 0
C286: 3331 | D286: Thuế giá trị gia tăng phải nộp | E286: 0 | F286: 0 | G286: 0 | H286: 0 | I286: 0 | J286: 0 | K286: 0
C287: 33311 | D287: Thuế GTGT đầu ra | E287: 0 | F287: 0 | G287: 0 | H287: 0 | I287: 0 | J287: 0 | K287: 0
C288: 33312 | D288: Thuế GTGT hàng nhập khẩu | E288: 0 | F288: 0 | G288: 0 | H288: 0 | I288: 0 | J288: 0 | K288: 0
C289: 3331CN | D289: Thuế GTGT đầu ra chi nhánh | E289: 0 | F289: 0 | G289: 0 | H289: 0 | I289: 0 | J289: 0 | K289: 0
C290: 3332 | D290: Thuế tiêu thụ đặc biệt | E290: 0 | F290: 0 | G290: 0 | H290: 0 | I290: 0 | J290: 0 | K290: 0
...

Sheet DOI_TK
B2: BẢNG ĐỔI SỐ HIỆU TÀI KHOẢN NĂM TRƯỚC (TT200 / TT133) SANG TT99
B3: Dùng khi bấm 'Lấy SDĐK năm trước' (sheet TTDN) hoặc 'Lấy Số Dư Đầu Bảng CĐSPS_NT'. Cột C để trống = TT99 bỏ tài khoản này, KHÔNG chuyển số dư (tự xử lý). Chế độ: trống = áp dụng chung; TT133 = chỉ khi file năm trước KHÔNG có TK 641; TT200 = ngược lại. Dòng ở đây ghi đè bảng mặc định trong code (ModDoiTK). TK chi tiết (131-05, 3411-VCB...) tự đổi theo TK gốc.
B4: TK cũ | C4: TK mới (TT99) | D4: Chế độ | E4: Ghi chú
B5: 1385 | C5: 1388 | E5: Phai thu ve co phan hoa - TT99 bo, gop vao 1388
B6: 1522 | C6: 1521 | E6: Chi phi mua NVL gop vao NVL (nhu 1562 -> 1561) - KIEM TRA
B7: 1544 | C7: 1541 | E7: Chi phi bao hanh xay lap -> 1541 Xay lap - KIEM TRA
B8: 1562 | C8: 1561 | E8: TT99 gop chi phi thu mua vao hang hoa
B9: 161 | E9: TT99 bo - tu xu ly
B10: 1611 | E10: TT99 bo - tu xu ly
B11: 1612 | E11: TT99 bo - tu xu ly
B12: 2115 | C12: 2118 | E12: Cay lau nam, suc vat -> TSCD khac (TT99 co TK 215 tai san sinh hoc) - KIEM TRA
B13: 3385 | C13: 3388 | E13: Phai tra ve co phan hoa - TT99 bo, gop vao 3388
B14: 3389 | C14: 3386 | E14: Bao hiem that nghiep doi so hieu
B15: 3524 | C15: 3525 | E15: Du phong phai tra khac doi so hieu
B16: 417 | C16: 4118 | E16: Quy ho tro sap xep DN - TT99 bo - KIEM TRA
B17: 441 | C17: 4118 | E17: Theo TT99: 441 -> 4118 Von khac
B18: 461 | E18: TT99 bo - tu xu ly
B19: 4611 | E19: TT99 bo - tu xu ly
B20: 4612 | E20: TT99 bo - tu xu ly
B21: 466 | C21: 4118 | E21: Theo TT99: 466 -> 4118 Von khac
B22: 5112 | C22: 5111 | E22: TT99: doanh thu san pham gop vao 5111
B23: 5113 | C23: 5112 | E23: TT99: doanh thu dich vu la 5112
B24: 5152 | C24: 5155 | E24: TT99: chenh lech ty gia la 5155
B25: 5153 | C25: 5155 | E25: TT99: chenh lech ty gia la 5155
B26: 611 | E26: TT99 bo (kiem ke dinh ky)
B27: 6111 | E27: TT99 bo
B28: 6112 | E28: TT99 bo
B29: 631 | E29: TT99 bo
B30: 6322 | C30: 6321 | E30: TT99: gia von san pham gop vao 6321
B31: 6323 | C31: 6322 | E31: TT99: gia von dich vu la 6322
B32: 6419 | C32: 6418 | E32: TK tu mo cua khach
B33: 64110 | C33: 6418 | E33: TK tu mo cua khach
B34: 6429 | C34: 6428 | E34: TK tu mo cua khach
B35: 64210 | C35: 6428 | E35: TK tu mo cua khach
B36: 64221 | C36: 6421 | E36: TK tu mo cua khach
B37: 64222 | C37: 6422 | E37: TK tu mo cua khach
B38: 64223 | C38: 6423 | E38: TK tu mo cua khach
B39: 64224 | C39: 6424 | E39: TK tu mo cua khach
B40: 64225 | C40: 6425 | E40: TK tu mo cua khach
B41: 64227 | C41: 6427 | E41: TK tu mo cua khach
B42: 64228 | C42: 6428 | E42: TK tu mo cua khach
B43: 1386 | C43: 2441 | D43: TT133 | E43: TT133: cam co, ky quy -> 2441
B44: 6421 | C44: 641 | D44: TT133 | E44: TT133: chi phi ban hang -> 641
B45: 6422 | C45: 642 | D45: TT133 | E45: TT133: chi phi quan ly DN -> 642

Sheet NKC
P1: 46023
P2: 46295
D5: =+CDSPS!$C$5 -> Đơn vị : | K5: Mẫu số S03a – DN
D6: =+CDSPS!$C$6 -> Địa chỉ : | K6: (Kèm theo Thông tư số 99/2025/TT-BTC
D7: =+CDSPS!$C$7 -> Mã số thuế : | K7: Ngày 27/10/2025 của Bộ trưởng Bộ Tài chính)
D8: SỔ NHẬT KÝ CHUNG
G9: TỪ THÁNG 1 | H9: ĐẾN THÁNG 9
G10: NĂM | H10: 2026
G11: Tổng phát sinh
N12: Đơn vị tính: đồng Việt Nam
D13: Ngày tháng ghi sổ | E13: Chứng từ | G13: Diễn giải | H13: Đã ghi sổ cái | I13: STT dòng | J13: Trang số | K13: Số hiệu TK | L13: Số hiệu TK đối ứng | M13: Số phát sinh
E14: Số hiệu | F14: Ngày tháng | M14: Nợ | N14: Có
D16: [1] | E16: [2] | F16: [3] | G16: [4] | H16: [5] | I16: [6] | J16: [7] | K16: [8] | L16: [8'] | M16: [9] | N16: [10]
O707: 1
E879: - Sổ này có 16 trang, đánh số từ trang 01 đến trang 16
E880: - Ngày mở sổ : 01/01/26
M881: Ngày 30 tháng 09 năm 2026
D882: Người ghi sổ | G882: Kế toán trưởng | M882: Người đại diện theo pháp luật
D883: (Ký, họ tên) | G883: (Ký, họ tên) | M883: (Ký, họ tên, đóng dấu)

Sheet HTTK
I1: Lưu ý
I2: _ Muốn thêm tài khoản nào thì Insert thêm
I3: _ Sau khi thêm nhớ điền Cấp tài khoản ở cột 'Cấp Tài Khoản'
E4: HỆ THỐNG TÀI KHOẢN KẾ TOÁN - TT99 | I4: _ Chỉ được mở thêm tài khoản đến CẤP 4
I5: _ Các tài khoản chi tiết đều phải có dấu gạch ngang khi thêm ( ví dụ 131-DN)
E6: Số tài khoản | F6: Tên tài khoản | G6: Cấp tài khoản
E7: [1] | F7: [2] | G7: [3]
E8: 111 | F8: TIỀN MẶT | G8: 1
E9: 1111 | F9: Tiền Việt Nam | G9: 2
E10: 1112 | F10: Ngoại tệ | G10: 2
E11: 1113 | F11: Vàng tiền tệ | G11: 2
E12: 112 | F12: TIỀN GỬI KHÔNG KỲ HẠN | G12: 1
E13: 1121 | F13: Tiền gửi không kỳ hạn Việt Nam | G13: 2
E14: 1121-01 | F14: Tiền gữi không kỳ hạn Việt Nam Đồng | G14: 3
E15: 1121-02 | F15: Tiền gữi không kỳ hạn Việt Nam Đồng | G15: 3
E16: 1121-03 | F16: Tiền gữi không kỳ hạn Việt Nam Đồng | G16: 3
E17: 1121-04 | F17: Tiền gữi không kỳ hạn Việt Nam Đồng | G17: 3
E18: 1121-05 | F18: Tiền gữi không kỳ hạn Việt Nam Đồng | G18: 3
E19: 1121-06 | F19: Tiền gữi không kỳ hạn Việt Nam Đồng | G19: 3
E20: 1121-07 | F20: Tiền gữi không kỳ hạn Việt Nam Đồng | G20: 3
E21: 1121-08 | F21: Tiền gữi không kỳ hạn Việt Nam Đồng | G21: 3
E22: 1121-09 | F22: Tiền gữi không kỳ hạn Việt Nam Đồng | G22: 3
E23: 1121-10 | F23: Tiền gữi không kỳ hạn Việt Nam Đồng | G23: 3
E24: 1122 | F24: Tiền gửi không kỳ hạn ngoại tệ | G24: 2
E25: 1122-01 | F25: Tiền gữi không kỳ hạn ngoại tệ | G25: 3
E26: 1122-02 | F26: Tiền gữi không kỳ hạn ngoại tệ | G26: 3
E27: 1122-03 | F27: Tiền gữi không kỳ hạn ngoại tệ | G27: 3
E28: 1122-04 | F28: Tiền gữi không kỳ hạn ngoại tệ | G28: 3
E29: 1122-05 | F29: Tiền gữi không kỳ hạn ngoại tệ | G29: 3
E30: 1122-06 | F30: Tiền gữi không kỳ hạn ngoại tệ | G30: 3
E31: 1122-07 | F31: Tiền gữi không kỳ hạn ngoại tệ | G31: 3
E32: 1122-08 | F32: Tiền gữi không kỳ hạn ngoại tệ | G32: 3
E33: 1122-09 | F33: Tiền gữi không kỳ hạn ngoại tệ | G33: 3
E34: 1122-10 | F34: Tiền gữi không kỳ hạn ngoại tệ | G34: 3
E35: 1123 | F35: Vàng tiền tệ | G35: 2
E36: 113 | F36: TIỀN ĐANG CHUYỂN | G36: 1
E37: 1131 | F37: Tiền Việt Nam | G37: 2
E38: 1132 | F38: Ngoại tệ | G38: 2
E39: 121 | F39: CHỨNG KHOÁN KINH DOANH | G39: 1
E40: 1211 | F40: Cổ phiếu | G40: 2
E41: 1212 | F41: Trái phiếu | G41: 2
E42: 1218 | F42: Chứng khoán và công cụ tài chính khác | G42: 2
E43: 128 | F43: ĐẦU TƯ NẮM GIỮ ĐẾN NGÀY ĐÁO HẠN | G43: 1
E44: 1281 | F44: Tiền gửi có kỳ hạn | G44: 2
E45: 12811 | F45: Tiền gửi có kỳ hạn - ngắn hạn <= 3 tháng | G45: 3
E46: 12812 | F46: Tiền gửi có kỳ hạn - ngắn hạn <= 12 tháng | G46: 3
... E54: 131 | F54: PHẢI THU CỦA KHÁCH HÀNG | G54: 1
E55: 131-01 | F55: Phải thu của khách hàng | G55: 2
E56: 131-02 | F56: Phải thu của khách hàng | G56: 2
E57: 131-03 | F57: Phải thu của khách hàng | G57: 2
E58: 131-04 | F58: Phải thu của khách hàng | G58: 2
E59: 131-05 | F59: Phải thu của khách hàng | G59: 2
E60: 131-06 | F60: Phải thu của khách hàng | G60: 2
E61: 131-07 | F61: Phải thu của khách hàng | G61: 2
E62: 131-08 | F62: Phải thu của khách hàng | G62: 2
E63: 131-09 | F63: Phải thu của khách hàng | G63: 2
E64: 131-10 | F64: Phải thu của khách hàng | G64: 2
E65: 131-11 | F65: Phải thu của khách hàng | G65: 2
E66: 131-12 | F66: Phải thu của khách hàng | G66: 2
... E120: 131-66 | F120: Phải thu của khách hàng | G120: 2
E121: 133 | F121: THUẾ GTGT ĐƯỢC KHẤU TRỪ | G121: 1
E122: 1331 | F122: Thuế GTGT được khấu trừ của hàng hóa - dịch vụ | G122: 2
E123: 1332 | F123: Thuế GTGT được khấu trừ của TSCĐ | G123: 2
E124: 133CN | F124: Thuế GTGT được khấu trừ của chi nhánh | G124: 2
E125: 136 | F125: PHẢI THU NỘI BỘ | G125: 1
E126: 1361 | F126: Vốn kinh doanh ở các đơn vị trực thuộc | G126: 2
E127: 1362 | F127: Phải thu nội bộ về chênh lệch tỷ giá | G127: 2
E128: 1363 | F128: Phải thu nội bộ về chi phí đi vay đủ điều kiện được vốn hoá | G128: 2
E129: 1368 | F129: Phải thu nội bộ khác | G129: 2
E130: 138 | F130: PHẢI THU KHÁC | G130: 1
E131: 1381 | F131: Tài sản thiếu chờ xử lý | G131: 2
E132: 1383 | F132: Thuế TTĐB của hàng nhập khẩu | G132: 2
E133: 1388 | F133: Phải thu khác | G133: 2
E134: 13881 | F134: Phải thu khác - mua vào | G134: 3
E135: 13888 | F135: Phải thu khác | G135: 3
E136: 141 | F136: TẠM ỨNG | G136: 1
... E226: 331 | F226: PHẢI TRẢ CHO NGƯỜI BÁN | G226: 1
E227: 331-01 | F227: Phải trả cho người bán | G227: 2
E228: 331-02 | F228: Phải trả cho người bán | G228: 2
E229: 331-03 | F229: Phải trả cho người bán | G229: 2
E230: 331-04 | F230: Phải trả cho người bán | G230: 2
E231: 331-05 | F231: Phải trả cho người bán | G231: 2
E232: 331-06 | F232: Phải trả cho người bán | G232: 2
E233: 331-07 | F233: Phải trả cho người bán | G233: 2
E234: 331-08 | F234: Phải trả cho người bán | G234: 2
E235: 331-09 | F235: Phải trả cho người bán | G235: 2
E236: 331-10 | F236: Phải trả cho người bán | G236: 2
E237: 331-11 | F237: Phải trả cho người bán | G237: 2
E238: 331-12 | F238: Phải trả cho người bán | G238: 2
... E276: 331-50 | F276: Phải trả cho người bán | G276: 2
E277: 332 | F277: PHẢI TRẢ CỔ TỨC, LỢI NHUẬN | G277: 1
E278: 333 | F278: THUẾ và CÁC KHOẢN PHẢI NỘP NHÀ NƯỚC | G278: 1
E279: 3331 | F279: Thuế giá trị gia tăng phải nộp | G279: 2
E280: 33311 | F280: Thuế GTGT đầu ra | G280: 3
E281: 33312 | F281: Thuế GTGT hàng nhập khẩu | G281: 3
E282: 3331CN | F282: Thuế GTGT đầu ra chi nhánh | G282: 3
E283: 3332 | F283: Thuế tiêu thụ đặc biệt | G283: 2
E284: 3333 | F284: Thuế xuất, nhập khẩu | G284: 2
E285: 3334 | F285: Thuế thu nhập doanh nghiệp | G285: 2
E286: 3335 | F286: Thuế thu nhập cá nhân | G286: 2
...

Sheet Giai_Trinh
D4: 1 | E4: 2 | F4: 3 | G4: 4 | H4: 5 | I4: 6 | J4: 7 | K4: 8 | L4: 9 | M4: 10 | N4: 11 | O4: 12
B5: Đ/C 152 | C5: Đầu kỳ
C6: Nhập
C7: Xuất
C8: Cuối kỳ
B10: Đ/C 153 | C10: Đầu kỳ
C11: Nhập
C12: Xuất
C13: Cuối kỳ
B15: Đ/C 154 | C15: Đầu kỳ
C16: Nhập
C17: Xuất
C18: Cuối kỳ
B20: Đ/C 155 | C20: Đầu kỳ
C21: Nhập
C22: Xuất
C23: Cuối kỳ
B25: Đ/C 156 | C25: Đầu kỳ
C26: Nhập
C27: Xuất
C28: Cuối kỳ
B30: Đ/C phân bổ | C30: Đầu kỳ
C31: Nhập
C32: Xuất
C33: Cuối kỳ
B35: Đ/C 211 | C35: Đầu kỳ
C36: PS tăng
C37: PS giảm
C38: Cuối kỳ
B40: Đ/C 2141 | C40: Đầu kỳ
C41: PS tăng
C42: PS giảm
C43: Cuối kỳ
B45: Đ/C 212 | C45: Đầu kỳ
C46: PS tăng
C47: PS giảm
C48: Cuối kỳ
B50: Đ/C 2142 | C50: Đầu kỳ
C51: PS tăng
C52: PS giảm
C53: Cuối kỳ
B55: Đ/C 213 | C55: Đầu kỳ
C56: PS tăng
C57: PS giảm
C58: Cuối kỳ
B60: Đ/C 2143 | C60: Đầu kỳ
C61: PS tăng
C62: PS giảm
C63: Cuối kỳ
B65: Đ/C 217 | C65: Đầu kỳ
C66: PS tăng
C67: PS giảm
C68: Cuối kỳ
B70: Đ/C 2147 | C70: Đầu kỳ
C71: PS tăng
C72: PS giảm
C73: Cuối kỳ
B75: Đ/C 215 | C75: Đầu kỳ
C76: PS tăng
C77: PS giảm
C78: Cuối kỳ
B80: Đ/C 215122 | C80: Đầu kỳ
C81: PS tăng
C82: PS giảm
C83: Cuối kỳ

Sheet GTGT
C1: ="Chọn "&RIGHT(KB_LoaiVat,LEN(KB_LoaiVat)-5)& " kết chuyển:" -> Chọn tháng kết chuyển: | D1: III | F1: Thuế GTGT còn được khấu trừ đầu năm: | H1: 0
B5: CỘNG HÒA XÃ HỘI CHỦ NGHĨA VIỆT NAM | J5: BẢNG ĐIỀU CHỈNH VAT ( THEO THÁNG ) | N5: BẢNG ĐIỀU CHỈNH VAT ( THEO QUÝ)
B6: Độc lập - Tự do - Hạnh phúc | J6: Tháng | K6: Điều chỉnh giảm [37] | L6: Điều chỉnh tăng [38] | N6: Quý | O6: Điều chỉnh giảm [37] | P6: Điều chỉnh tăng [38]
B7: TỜ KHAI THUẾ GIÁ TRỊ GIA TĂNG | J7: 1 | K7: =SUMIFS(DC_3738!$F$6:$F$505,DC_3738!$C$6:$C$505,$J7) -> 0 | L7: =SUMIFS(DC_3738!$G$6:$G$505,DC_3738!$C$6:$C$505,$J7) -> 0 | N7: I | O7: =SUM($K$7:$K$9) -> 0 | P7: =SUM($L$7:$L$9) -> 0
B8: (Dành cho người nộp thuế khai thuế giá trị gia tăng theo phương pháp khấu trừ) | J8: 2 | K8: =SUMIFS(DC_3738!$F$6:$F$505,DC_3738!$C$6:$C$505,$J8) -> 0 | L8: =SUMIFS(DC_3738!$G$6:$G$505,DC_3738!$C$6:$C$505,$J8) -> 0 | N8: II | O8: =SUM($K$10:$K$12) -> 0 | P8: =SUM($L$10:$L$12) -> 0
B9: ="[01] Kỳ tính thuế: "&RIGHT(KB_LoaiVat,LEN(KB_LoaiVat)-5)&" "&$D$1&" năm "&YEAR(KB_Den) -> [01] Kỳ tính thuế: tháng III năm 2026 | J9: 3 | K9: =SUMIFS(DC_3738!$F$6:$F$505,DC_3738!$C$6:$C$505,$J9) -> 0 | L9: =SUMIFS(DC_3738!$G$6:$G$505,DC_3738!$C$6:$C$505,$J9) -> 0 | N9: III | O9: =SUM($K$13:$K$15) -> 0 | P9: =SUM($L$13:$L$15) -> 0
B10: [02] Lần đầu [ ] [03] Bổ sung lần thứ [ ] | J10: 4 | K10: =SUMIFS(DC_3738!$F$6:$F$505,DC_3738!$C$6:$C$505,$J10) -> 0 | L10: =SUMIFS(DC_3738!$G$6:$G$505,DC_3738!$C$6:$C$505,$J10) -> 0 | N10: IV | O10: =SUM($K$16:$K$18) -> 0 | P10: =SUM($L$16:$L$18) -> 0
C11: ="[04] Tên người nộp thuế: "&KB_CTy -> [04] Tên người nộp thuế: | J11: 5 | K11: =SUMIFS(DC_3738!$F$6:$F$505,DC_3738!$C$6:$C$505,$J11) -> 0 | L11: =SUMIFS(DC_3738!$G$6:$G$505,DC_3738!$C$6:$C$505,$J11) -> 0
C12: ="[05] Mã số thuế: "&KB_MST -> [05] Mã số thuế: | J12: 6 | K12: =SUMIFS(DC_3738!$F$6:$F$505,DC_3738!$C$6:$C$505,$J12) -> 0 | L12: =SUMIFS(DC_3738!$G$6:$G$505,DC_3738!$C$6:$C$505,$J12) -> 0
C13: [06] Tên đại lý thuế (nếu có):……………………………………………………………………………… | J13: 7 | K13: =SUMIFS(DC_3738!$F$6:$F$505,DC_3738!$C$6:$C$505,$J13) -> 0 | L13: =SUMIFS(DC_3738!$G$6:$G$505,DC_3738!$C$6:$C$505,$J13) -> 0
C14: [07] Mã số thuế:……………………………………………………………………………………………………. | J14: 8 | K14: =SUMIFS(DC_3738!$F$6:$F$505,DC_3738!$C$6:$C$505,$J14) -> 0 | L14: =SUMIFS(DC_3738!$G$6:$G$505,DC_3738!$C$6:$C$505,$J14) -> 0
C15: [08] Hợp đồng đại lý thuế: Số……………………………Ngày:……………………………………………….. | J15: 9 | K15: =SUMIFS(DC_3738!$F$6:$F$505,DC_3738!$C$6:$C$505,$J15) -> 0 | L15: =SUMIFS(DC_3738!$G$6:$G$505,DC_3738!$C$6:$C$505,$J15) -> 0
C16: [09] Tên đơn vị phụ thuộc/ĐĐKD của hoạt động sản xuất kinh doanh khác tỉnh nơi đóng trụ sở chính: ……………. | J16: 10 | K16: =SUMIFS(DC_3738!$F$6:$F$505,DC_3738!$C$6:$C$505,$J16) -> 0 | L16: =SUMIFS(DC_3738!$G$6:$G$505,DC_3738!$C$6:$C$505,$J16) -> 0
C17: [10] Mã số thuế đơn vị phụ thuộc/Mã số địa điểm kinh doanh:……………………………………………………………………… | J17: 11 | K17: =SUMIFS(DC_3738!$F$6:$F$505,DC_3738!$C$6:$C$505,$J17) -> 0 | L17: =SUMIFS(DC_3738!$G$6:$G$505,DC_3738!$C$6:$C$505,$J17) -> 0
C18: [11] Địa chỉ nơi có hoạt động sản xuất kinh doanh khác tỉnh nơi đóng trụ sở chính: | J18: 12 | K18: =SUMIFS(DC_3738!$F$6:$F$505,DC_3738!$C$6:$C$505,$J18) -> 0 | L18: =SUMIFS(DC_3738!$G$6:$G$505,DC_3738!$C$6:$C$505,$J18) -> 0
C19: [11a] Phường/xã………………….… [11b] Quận/Huyện …………………… [11c] Tỉnh/Thành phố……………………… | J19: KC 06/07: | K19: 0 | L19: 0
H20: Đơn vị tính: đồng Việt Nam
B21: STT | C21: Chỉ tiêu | F21: Giá trị HHDV (chưa có thuế GTGT) | H21: Thuế giá trị gia tăng
B22: A | C22: Không phát sinh hoạt động mua, bán trong kỳ (đánh dấu "X") | E22: [21] | J22: BẢNG PHÂN BỔ THUẾ GTGT KHẤU TRỪ ( PL01-4A ) | Q22: BẢNG PHÂN BỔ THUẾ GTGT KHẤU TRỪ ( PL01-4B )
B23: B | C23: Thuế GTGT còn được khấu trừ kỳ trước chuyển sang | G23: [22] | H23: 0 | J23: STT | K23: Chỉ tiêu | O23: Số tiền | Q23: STT | R23: Chỉ tiêu | V23: Số tiền
B24: C | C24: Kê khai thuế GTGT phải nộp Ngân sách nhà nước | J24: A | K24: Thuế GTGT của HHDV mua vào trong kỳ: | Q24: A | R24: Thuế GTGT của HHDV mua vào trong năm:
B25: I | C25: Hàng hoá, dịch vụ (HHDV) mua vào trong kỳ | K25: Trong đó: | R25: Trong đó:
B26: 1 | C26: Giá trị và thuế GTGT của hàng hoá, dịch vụ mua vào | E26: [23] | G26: [24] | H26: 53704 | K26: _Thuế GTGT dùng riêng chịu thuế được khấu trừ | O26: 0 | R26: _Thuế GTGT dùng riêng chịu thuế được khấu trừ
C27: Trong đó: hàng hóa, dịch vụ nhập khẩu | E27: [23a] | F27: 0 | G27: [24a] | H27: 0 | K27: _Thuế GTGT không được khấu trừ | O27: 0 | R27: _Thuế GTGT không được khấu trừ | V27: 0
B28: 2 | C28: Thuế giá trị gia tăng của HHDV mua vào được khấu trừ kỳ này | G28: [25] | H28: 53704 | K28: _Thuế GTGT dùng chung được khấu trừ | O28: 0 | R28: _Thuế GTGT dùng chung được khấu trừ | V28: 0
B29: II | C29: Hàng hoá, dịch vụ bán ra trong kỳ | J29: B | K29: Phân bổ thuế GTGT: | Q29: B | R29: Phân bổ thuế GTGT:
B30: 1 | C30: Hàng hóa, dịch vụ bán ra không chịu thuế GTGT | E30: [26] | F30: 0 | J30: 1 | K30: Tổng doanh thu HHDV bán ra trong kỳ | Q30: 1 | R30: Tổng doanh thu HHDV bán ra trong năm
B31: 2 | C31: Hàng hóa, dịch vụ bán ra chịu thuế GTGT ([27]=[29]+[30]+[32]+[32a]; [28]=[31]+[33]) | E31: [27] | F31: =+SUM(F32:F35) -> 0 | G31: [28] | H31: =+H33+H34 -> 0 | J31: 2 | K31: Doanh thu HHDV bán ra chịu thuế trong kỳ | Q31: 2 | R31: Doanh thu HHDV bán ra chịu thuế trong năm
B32: a | C32: Hàng hoá, dịch vụ bán ra chịu thuế suất 0% | E32: [29] | F32: 0 | J32: 3 | K32: Tỷ lệ % doanh thu HHDV chịu thuế / tổng doanh thu bán ra | O32: 1 | Q32: 3 | R32: Tỷ lệ % doanh thu HHDV chịu thuế / tổng doanh thu bán ra | V32: 1
B33: b | C33: Hàng hoá, dịch vụ bán ra chịu thuế suất 5% | E33: [30] | F33: 0 | G33: [31] | H33: 0 | J33: 4 | K33: Thuế GTGT của HHDV mua vào cần phân bổ trong kỳ | O33: 0 | Q33: 4 | R33: Thuế GTGT của HHDV mua vào cần phân bổ trong năm | V33: 0
B34: c | C34: Hàng hoá, dịch vụ bán ra chịu thuế suất 10% | E34: [32] | G34: [33] | J34: 5 | K34: Thuế GTGT của HHDV mua vào được khấu trừ trong kỳ | O34: 0 | Q34: 5 | R34: Thuế GTGT của HHDV mua vào được khấu trừ trong năm | V34: 0
B35: d | C35: Hàng hoá, dịch vụ bán ra không tính thuế | E35: [32a] | F35: 0 | Q35: 6 | R35: Thuế GTGT đầu vào đã kê khai khấu trừ trong năm | V35: 0
B36: 3 | C36: Tổng doanh thu và thuế GTGT của HHDV bán ra ([34]=[26]+[27]; [35]=[28]) | E36: [34] | F36: =+F30+F31 -> 0 | G36: [35] | H36: =+H31 -> 0 | Q36: 7 | R36: Điều chỉnh tăng (+), giảm (-) thuế GTGT đầu vào được khấu trừ trong năm | V36: 0
B37: III | C37: Thuế GTGT phát sinh trong kỳ ([36]=[35]-[25]) | G37: [36] | H37: =+H36-H28 -> -53704
B38: IV | C38: Điều chỉnh tăng, giảm thuế GTGT còn được khấu trừ của các kỳ trước
B39: 1 | C39: Điều chỉnh giảm | G39: [37] | H39: 0
B40: 2 | C40: Điều chỉnh tăng | G40: [38] | H40: 0
B41: V | C41: Thuế giá trị gia tăng nhận bàn giao được khấu trừ trong kỳ | G41: [39a] | H41: 0
B42: VI | C42: Xác định nghĩa vụ thuế GTGT phải nộp trong kỳ
B43: 1 | C43: Thuế GTGT phải nộp của hoạt động sản xuất kinh doanh trong kỳ ([40a]=[36]-[22]+[37]-[38] - [39a]≥ 0) | G43: [40a] | H43: =+MAX(H37-H23+H39-H40-H41,0) -> 0
B44: 2 | C44: Thuế GTGT mua vào của dự án đầu tư được bù trừ với thuế GTGT còn phải nộp của hoạt động sản xuất kinh doanh cùng kỳ tính thuế ([40b]≤[40a]) | G44: [40b]
B45: 3 | C45: Thuế GTGT còn phải nộp trong kỳ ([40]=[40a]-[40b]) | G45: [40] | H45: =+H43-H44 -> 0
B46: 4 | C46: Thuế GTGT chưa khấu trừ hết kỳ này (nếu [41]=[36]-[22]+[37]-[38]-[39a] < 0) | G46: [41] | H46: =-MIN(H37-H23+H39-H40-H41,0) -> 53704
B47: 4.1 | C47: Thuế giá trị gia tăng đề nghị hoàn ([42] ≤ [41]) | G47: [42]
B48: 4.2 | C48: Thuế GTGT còn được khấu trừ chuyển kỳ sau ([43]=[41]-[42]) | G48: [43] | H48: =+H46-H47 -> 53704
C49: Tôi cam đoan số liệu khai trên là đúng và chịu trách nhiệm trước pháp luật về những số liệu đã khai./.
G50: ...., ngày ......tháng ...... năm .........
C51: NHÂN VIÊN ĐẠI LÝ THUẾ | G51: NGƯỜI NỘP THUẾ hoặc
C52: Họ và tên:............................ | G52: ĐẠI DIỆN HỢP PHÁP CỦA NGƯỜI NỘP THUẾ
C53: Chứng chỉ hành nghề số:.......................... | G53: (Ký, ghi rõ họ tên; chức vụ và đóng dấu (nếu có))
F59: =KB_GD -> 0
C61: Ghi chú:
C62: - GTGT: Giá trị Gia tăng
C63: - HHDV: Hàng hoá dịch vụ

Sheet GTGT_89
C1: Chọn quý kết chuyển: | D1: III
B5: CỘNG HÒA XÃ HỘI CHỦ NGHĨA VIỆT NAM
B6: Độc lập - Tự do - Hạnh phúc
B7: TỜ KHAI THUẾ GIÁ TRỊ GIA TĂNG
B8: (Áp dụng đối với người nộp thuế tính thuế theo phương pháp khấu trừ có hoạt động sản xuất kinh doanh)
C9: [01a] Tên hoạt động sản xuất kinh doanh: Hoạt động sản xuất kinh doanh thông thường
B10: ="[01b] Kỳ tính thuế: "&RIGHT(KB_LoaiVat,LEN(KB_LoaiVat)-5)&" "&GTGT!$D$1&" năm "&YEAR(KB_Den) -> [01b] Kỳ tính thuế: tháng III năm 2026
B11: [02] Lần đầu [ ] [03] Bổ sung lần thứ [ ]
C12: ="[04] Tên người nộp thuế: "&KB_CTy -> [04] Tên người nộp thuế:
C13: ="[05] Mã số thuế: "&KB_MST -> [05] Mã số thuế:
C14: [06] Tên tổ chức, cá nhân cung cấp dịch vụ làm thủ tục về thuế (nếu có):…………………………………………
C15: [07] Mã số thuế:……………………………………………………………………………………………………..
C16: [08] Hợp đồng dịch vụ làm thủ tục về thuế: Số……………………………Ngày:……………………………………
C17: [09] Tên đơn vị phụ thuộc/ĐĐKD của hoạt động sản xuất kinh doanh khác tỉnh nơi đóng trụ sở chính: …………….
C18: [10] Mã số thuế đơn vị phụ thuộc/Mã số địa điểm kinh doanh:………………………………………………………………
C19: [11] Địa chỉ nơi có hoạt động sản xuất kinh doanh khác tỉnh nơi đóng trụ sở chính:
C20: [11a] Xã/Phường/Đặc khu………………….… [11c] Tỉnh/Thành phố………………………
H21: Đơn vị tính: đồng Việt Nam
B22: STT | C22: Chỉ tiêu | F22: Giá trị HHDV (chưa có thuế GTGT) | H22: Thuế giá trị gia tăng
B23: A | C23: Không phát sinh hoạt động mua, bán trong kỳ (đánh dấu "X") | E23: [21]
B24: B | C24: Thuế GTGT còn được khấu trừ kỳ trước chuyển sang | G24: [22] | H24: =GTGT!H23 -> 0
B25: C | C25: Kê khai thuế GTGT phải nộp ngân sách nhà nước
B26: I | C26: Hàng hoá, dịch vụ (HHDV) mua vào trong kỳ
B27: 1 | C27: Giá trị và thuế GTGT của hàng hóa, dịch vụ mua vào | E27: [23] | F27: =GTGT!F26 -> 0 | G27: [24] | H27: =GTGT!H26 -> 53704
C28: Trong đó: hàng hóa nhập khẩu | E28: [23a] | F28: =GTGT!F27 -> 0 | G28: [24a] | H28: =GTGT!H27 -> 0
B29: 2 | C29: Thuế giá trị gia tăng của HHDV mua vào được khấu trừ kỳ này | G29: [25] | H29: =GTGT!H28 -> 53704
B30: II | C30: Hàng hoá, dịch vụ bán ra trong kỳ
B31: 1 | C31: Hàng hóa, dịch vụ bán ra không chịu thuế GTGT | E31: [26] | F31: =GTGT!F30 -> 0
B32: 2 | C32: Hàng hóa, dịch vụ bán ra chịu thuế GTGT ([27]=[29]+[30]+[32]+[32a]-[32b]; [28]=[31]+[33]) | E32: [27] | F32: =+F33+F34+F35+F36-F37 -> 0 | G32: [28] | H32: =+H34+H35 -> 0
B33: a | C33: Hàng hoá, dịch vụ bán ra chịu thuế suất 0% | E33: [29] | F33: =GTGT!F32 -> 0
B34: b | C34: Hàng hoá, dịch vụ bán ra chịu thuế suất 5% | E34: [30] | F34: =GTGT!F33 -> 0 | G34: [31] | H34: =GTGT!H33 -> 0
B35: c | C35: Hàng hoá, dịch vụ bán ra chịu thuế suất 10% | E35: [32] | F35: =GTGT!F34 -> 0 | G35: [33] | H35: =GTGT!H34 -> 0
B36: d | C36: Hàng hoá, dịch vụ bán ra không kê khai tính nộp thuế | E36: [32a] | F36: =GTGT!F35 -> 0
B37: e | C37: Hàng hoá, dịch vụ bán ra không tính vào giá tính thuế GTGT | E37: [32b] | F37: =GTGT_32b -> 0
B38: 3 | C38: Hàng hoá, dịch vụ bán ra không thuộc phạm vi điều chỉnh của pháp luật thuế GTGT | E38: [34a] | F38: =GTGT_34a -> 0
B39: 4 | C39: Tổng doanh thu và thuế GTGT của HHDV bán ra ([34]=[26]+[27]+[34a]; [35]=[28]) | E39: [34] | F39: =+F31+F32+F38 -> 0 | G39: [35] | H39: =+H32 -> 0
B40: III | C40: Thuế GTGT phát sinh trong kỳ ([36]=[35]-[25]) | G40: [36] | H40: =+H39-H29 -> -53704
B41: IV | C41: Điều chỉnh tăng, giảm thuế GTGT còn được khấu trừ của các kỳ trước
B42: 1 | C42: Điều chỉnh giảm | G42: [37] | H42: =GTGT!H39 -> 0
B43: 2 | C43: Điều chỉnh tăng | G43: [38] | H43: =GTGT!H40 -> 0
B44: V | C44: Thuế giá trị gia tăng nhận bàn giao được khấu trừ trong kỳ | G44: [39a] | H44: =GTGT!H41 -> 0
B45: VI | C45: Xác định nghĩa vụ thuế GTGT phải nộp trong kỳ
B46: 1 | C46: Thuế GTGT phải nộp của hoạt động sản xuất kinh doanh trong kỳ {[40a]=([36]-[22]+[37]-[38]-[39a]) ≥ 0} | G46: [40a] | H46: =+MAX(H40-H24+H42-H43-H44,0) -> 0
B47: 2 | C47: Thuế GTGT mua vào của dự án đầu tư được bù trừ với thuế GTGT còn phải nộp của hoạt động sản xuất kinh doanh cùng kỳ tính thuế ([40b]≤[40a]) | G47: [40b]
B48: 3 | C48: Thuế GTGT còn phải nộp trong kỳ ([40]=[40a]-[40b]) | G48: [40] | H48: =+H46-H47 -> 0
B49: 4 | C49: Thuế GTGT chưa khấu trừ hết kỳ này {[41]=([36]-[22]+[37]-[38]-[39a]) ≤ 0} | G49: [41] | H49: =-MIN(H40-H24+H42-H43-H44,0) -> 53704
B50: 4.1 | C50: Thuế giá trị gia tăng đề nghị hoàn ([42] ≤ [41]) | G50: [42]
B51: 4.2 | C51: Thuế GTGT còn được khấu trừ chuyển kỳ sau ([43]=[41]-[42]) | G51: [43] | H51: =+H49-H50 -> 53704
C52: Tôi cam đoan số liệu khai trên là đúng và chịu trách nhiệm trước pháp luật về số liệu đã khai./.
G53: ...., ngày ......tháng ...... năm .........
C54: NGƯỜI TRỰC TIẾP THỰC HIỆN DỊCH VỤ LÀM THỦ TỤC VỀ THUẾ | G54: NGƯỜI NỘP THUẾ hoặc
C55: Họ và tên:............................ | G55: ĐẠI DIỆN HỢP PHÁP CỦA NGƯỜI NỘP THUẾ
C56: Chứng chỉ nghiệp vụ chuyên môn về thuế số:.......... | G56: (Ký, ghi rõ họ tên; chức vụ và đóng dấu (nếu có)/Ký điện tử)
F62: =KB_GD -> 0
C64: Ghi chú:
C65: - GTGT: Giá trị Gia tăng - HHDV: Hàng hoá dịch vụ
C66: - Số liệu lấy sang từ sheet GTGT (bảng kết chuyển thuế GTGT). Chỉ tiêu [32b] và [34a] nhập tay.

Sheet DC_3738
B2: SỔ THEO DÕI ĐIỀU CHỈNH THUẾ GTGT CÒN ĐƯỢC KHẤU TRỪ - CHỈ TIÊU [37] / [38] | K2: Tự động hoá đơn muộn (kê khai trễ kỳ) → KHBS kỳ gốc + [37]/[38]: | L2: Không
B3: Mỗi nghiệp vụ điều chỉnh ghi MỘT DÒNG. Hai bảng trên sheet GTGT tự cộng từ sổ này theo THÁNG KÊ KHAI - không nhập tay vào GTGT nữa. | K3: Có: hóa đơn Mua Vào có THÁNG GHI SỔ (cột S) thuộc kỳ trước THÁNG KÊ KHAI (cột Q) là hóa đơn muộn - bấm Kết chuyển tờ khai GTGT thì máy tự bỏ khỏi [23]-[35] kỳ này, ghi [37]/[38] + giải trình KHBS (cột N:R); nút «Kết Chuyển» trên sổ này để chạy lại. Không: kê theo cột tháng kê khai như cũ. | L3: HĐ điều chỉnh của người bán: ghi mã ở cột T 'Mã Đ/C' của MV → máy tự ghi [37]/[38]. Ứng viên TTCH (mua trả chậm ≥ ngưỡng): bảng cột T:AE, đánh 'x' cột AE rồi bấm lại → ghi TTCH; đã thanh toán qua NH (khớp FIFO theo 331-xx) → CTTT tự sinh.
T4: ỨNG VIÊN TTCH — mua trả chậm (ĐK Có 331-xx) ≥ ngưỡng TTKDTM. Đánh 'x' cột AE → bấm '1. Kết chuyển' → ghi TTCH [TU DONG]; đã TT qua NH (FIFO theo 331-xx) → CTTT tự sinh.
A5: STT | B5: Ngày chứng từ | C5: Tháng kê khai | D5: Mã lý do | E5: Số hóa đơn | F5: Điều chỉnh GIẢM [37] | G5: Điều chỉnh TĂNG [38] | H5: Diễn giải | I5: Trạng thái | K5: MÃ LÝ DO | L5: (TT94/2026/TT-BTC, NĐ252/2026/NĐ-CP, Luật 48/2024 & ghi chú 4 mẫu 01/GTGT TT89) — người MUA ghi sổ này
A6: =IF(COUNTA(B6:G6)=0,"",ROW()-5) | I6: =IF($D6="TTCH",IF(COUNTIFS($D$6:$D$505,"CTTT",$E$6:$E$505,$E6)=0,"CON TREO",""),"") | K6: TTCH | L6: Mua trả chậm/trả góp ≥ ngưỡng, CHƯA có chứng từ thanh toán KDTM → tạm giảm [37] kỳ phát sinh
K7: CTTT | L7: Đã có chứng từ thanh toán KDTM bổ sung cho dòng TTCH → tăng [38], ghi CÙNG SỐ HĐ với dòng TTCH
K8: SS | L8: Sai/BỎ SÓT thuế đầu vào phát hiện ở kỳ sau, CHỈ ảnh hưởng số còn được khấu trừ chuyển kỳ sau → [37]/[38] kỳ phát hiện
K9: HDDC | L9: Nhận HĐ điều chỉnh/thay thế do SAI SÓT của người bán, chỉ ảnh hưởng số còn khấu trừ → kỳ nhận hóa đơn
K10: TLHH | L10: Trả lại hàng (mình là bên MUA): nhận HĐ điều chỉnh của người bán hoặc mình lập HĐ trả lại theo thỏa thuận → giảm [37] kỳ nhận/kỳ lập
K11: CKTM | L11: Chiết khấu thương mại được hưởng → giảm [37] kỳ nhận HĐ chiết khấu/điều chỉnh
K12: QTGG | L12: Giá trị thay đổi do quyết toán, thanh toán thực tế → [37]/[38] kỳ nhận HĐ mới/HĐ điều chỉnh chênh lệch
K13: HPHI | L13: Hoàn phí, giảm phí, giảm hoa hồng (bảo hiểm, môi giới…) → giảm [37] kỳ nhận HĐ điều chỉnh
K14: HUYGD | L14: Hủy/chấm dứt giao dịch đã lập HĐ thu tiền trước → giảm [37] kỳ nhận HĐ điều chỉnh
K15: CDPP | L15: Chuyển đổi phương pháp tính thuế (khấu trừ ↔ trực tiếp)
K16: KHAC | L16: Trường hợp khác theo Đ12 NĐ252/2026 và pháp luật quản lý thuế
K18: ⚠ KHÔNG ghi vào sổ này | L18: 3 trường hợp sau kê khai KHÁC, ghi vào đây là SAI KỲ:
K19: • KHBS kỳ gốc | L19: Sai sót/bỏ sót đầu vào làm TĂNG số thuế phải nộp hoặc GIẢM số được hoàn → khai BỔ SUNG tại KỲ GỐC
... K23: • Ứng viên TTCH (T:AE) | L23: HĐ có ĐK Có 331-xx, tổng ≥ ngưỡng TTKDTM (THAMSO), VAT khấu trừ > 0. Máy không biết hạn thanh toán → bạn đánh 'x' cột AE cho HĐ chưa có chứng từ KDTM, bấm lại → dòng TTCH; NH trả đủ (FIFO) → CTTT tự sinh.

Sheet SDHD
B5: KHAI BÁO TÌNH HÌNH HÓA ĐƠN | J5: Hủy hóa đơn
B6: STT | C6: Tên Hóa Đơn | D6: K.Hiệu mẫu HĐ | E6: Ký hiệu HĐ | F6: Từ số | G6: Đến số | H6: Tổng | I6: dd/mm/yy | J6: Ngày | K6: Từ số | L6: Đến số | O6: Lưu Ý:
B7: =IF(C7="","",1) | H7: =IF(OR(F7="",G7=""),"",G7-F7+1) | O7: Nếu trong năm phát hành thêm
B8: =IF(C8="","",1+B7) | H8: =IF(OR(F8="",G8=""),"",G8-F8+1) | O8: _ Đổi mẫu thì ký hiệu mẫu HĐ phải khác
B9: =IF(C9="","",1+B8) | H9: =IF(OR(F9="",G9=""),"",G9-F9+1) | O9: _ Không đổi mẫu thì số phát hành phải liên tục
B10: =IF(C10="","",1+B9) | H10: =IF(OR(F10="",G10=""),"",G10-F10+1) | O10: _ Luôn chừa 1 dòng trống trong phần khai báo tình hình hóa đơn
B11: =IF(C11="","",1+B10) | H11: =IF(OR(F11="",G11=""),"",G11-F11+1)
B12: =IF(C12="","",1+B11) | H12: =IF(OR(F12="",G12=""),"",G12-F12+1)
B13: =IF(C13="","",1+B12) | H13: =IF(OR(F13="",G13=""),"",G13-F13+1)
B14: =IF(C14="","",1+B13) | H14: =IF(OR(F14="",G14=""),"",G14-F14+1)
B15: =IF(C15="","",1+B14) | H15: =IF(OR(F15="",G15=""),"",G15-F15+1)
B16: =IF(C16="","",1+B15) | H16: =IF(OR(F16="",G16=""),"",G16-F16+1)
B17: =IF(C17="","",1+B16) | H17: =IF(OR(F17="",G17=""),"",G17-F17+1)
B18: =IF(C18="","",1+B17) | H18: =IF(OR(F18="",G18=""),"",G18-F18+1)
B20: =COUNT(B7:B19) -> 0 | C20: Tổng cộng
B22: BÁO CÁO TÌNH HÌNH SỬ DỤNG HÓA ĐƠN
K23: TỪ THÁNG 1 ĐẾN THÁNG 3
B25: STT | C25: Tên hóa đơn | D25: Ký hiệu mẫu hóa đơn | E25: Ký hiệu hóa đơn | F25: Số tồn đầu kỳ, mua/ phát hành trong kỳ | K25: Số sử dụng, xóa bỏ, mất, hủy trong kỳ | U25: Tồn cuối kỳ
F26: Tổng số | G26: Số tồn đầu | I26: Số mua/ phát hành trong kỳ | K26: Tổng số sử dụng, xóa bỏ, mất, hủy | N26: Trong đó
N27: Số lượng đã sử dụng | O27: Xóa bỏ | Q27: Mất | S27: Hủy
G28: Từ số | H28: Đến số | I28: Từ số | J28: Đến số | K28: Từ số | L28: Đến số | M28: Cộng | O28: Số lượng | P28: Số | Q28: Số lượng | R28: Số | S28: Số lượng | T28: Số | U28: Từ số | V28: Đến số | W28: Số lượng
B29: [1] | C29: [2] | D29: [3] | E29: [4] | F29: [5] | G29: [6] | H29: [7] | I29: [8] | J29: [9] | K29: [10] | L29: [11] | M29: [12] | N29: [13] | O29: [14] | P29: [15] | Q29: [16] | R29: [17] | S29: [18] | T29: [19] | U29: [20] | V29: [21] | W29: [22]
B30: 1 | C30: Giá trị gia tăng | D30: 01GTKT0/001 | E30: AA/20E | F30: 500 | G30: 1 | H30: 500 | K30: 1 | L30: 1 | M30: 1 | N30: 1 | O30: 0 | S30: 0 | U30: 2 | V30: 500 | W30: 499
C32: Tổng cộng | F32: =+SUM(F30:F31) -> 500 | M32: =+SUM(M30:M31) -> 1 | N32: =+SUM(N30:N31) -> 1 | O32: =+SUM(O30:O31) -> 0 | Q32: =+SUM(Q30:Q31) -> 0 | S32: =+SUM(S30:S31) -> 0 | W32: =+SUM(W30:W31) -> 499

Sheet TNDN03_80
E6: CỘNG HÒA XÃ HỘI CHỦ NGHĨA VIỆT NAM
E7: Độc lập - Tự do - Hạnh phúc
E8: _____________________
E10: TỜ KHAI QUYẾT TOÁN THUẾ THU NHẬP DOANH NGHIỆP
E11: (Áp dụng đối với phương pháp doanh thu - chi phí)
E12: ="[01] Kỳ tính thuế: từ "&TEXT(DATE(KB_Nam,1,1),"DD/MM/YYYY")&" đến "&TEXT(KB_Den,"DD/MM/YYYY") -> [01] Kỳ tính thuế: từ 01/01/2026 đến 31/12/2026
E13: [02] Lần đầu  [03] Bổ sung lần thứ: 
E14: [04] Ngành nghề có tỷ lệ doanh thu cao nhất:….........................
E15: [05] Tỷ lệ (%): ….............%
E16: ="[06] Tên người nộp thuế : "&KB_CTy -> [06] Tên người nộp thuế :
E17: ="[07] Mã số thuế: "&KB_MST -> [07] Mã số thuế:
E18: [08] Tên đại lý thuế (nếu có):............................................................................................................................................
E19: [09] Mã số thuế:…………………………………………………………………………………………………………..
E20: [10] Hợp đồng đại lý thuế: số:......................................ngày:...........................................................................................
H21: Đơn vị tính: đồng Việt Nam
E22: STT | F22: Chỉ tiêu | G22: Mã chỉ tiêu | H22: Số tiền
E23: [1] | F23: [2] | G23: [3] | H23: [4]
E24: A | F24: Kết quả kinh doanh ghi nhận theo báo cáo tài chính | G24: A | H24: =+H25 -> 0
E25: 1 | F25: Tổng lợi nhuận kế toán trước thuế thu nhập doanh nghiệp | G25: A1 | H25: =+PL_03TN80!$D$34 -> 0
E26: B | F26: Xác định thu nhập chịu thuế theo Luật thuế thu nhập doanh nghiệp | G26: B
E27: 1 | F27: Điều chỉnh tăng tổng lợi nhuận trước thuế thu nhập doanh nghiệp (B1= B2+B3+B4+B5+B6+B7) | G27: B1 | H27: =+H28+H29+H30+H31+H32+H33 -> 0
E28: 1.1 | F28: Các khoản điều chỉnh tăng doanh thu | G28: B2
E29: 1.2 | F29: Chi phí của phần doanh thu điều chỉnh giảm | G29: B3
E30: 1.3 | F30: Các khoản chi không được trừ khi xác định thu nhập chịu thuế | G30: B4
E31: 1.4 | F31: Thuế thu nhập đã nộp cho phần thu nhập nhận được ở nước ngoài | G31: B5
E32: 1.5 | F32: Điều chỉnh tăng lợi nhuận do xác định giá thị trường đối với giao dịch liên kết | G32: B6
E33: 1.6 | F33: Các khoản điều chỉnh làm tăng lợi nhuận trước thuế khác | G33: B7
E34: 2 | F34: Điều chỉnh giảm tổng lợi nhuận trước thuế thu nhập doanh nghiệp (B8=B9+B10+B11+B12) | G34: B8 | H34: =+H35+H36+H37+H38 -> 0
E35: 2.1 | F35: Giảm trừ các khoản doanh thu đã tính thuế năm trước | G35: B9
E36: 2.2 | F36: Chi phí của phần doanh thu điều chỉnh tăng | G36: B10
E37: 2.3 | F37: Chi phí lãi vay không được trừ kỳ trước được chuyển sang kỳ này của doanh nghiệp có giao dịch liên kết | G37: B11
E38: 2.4 | F38: Các khoản điều chỉnh làm giảm lợi nhuận trước thuế khác | G38: B12
E39: 3 | F39: Tổng thu nhập chịu thuế (B13=A1+B1-B8) | G39: B13 | H39: =+H25+H27-H34 -> 0
E40: 3.1 | F40: Thu nhập chịu thuế từ hoạt động sản xuất kinh doanh | G40: B14 | J40: <= Vui lòng gõ số
E41: 3.2 | F41: Thu nhập chịu thuế từ hoạt động chuyển nhượng bất động sản | G41: B15 | H41: =+H39-H40 -> 0
E42: C | F42: Xác định thuế thu nhập doanh nghiệp ( TNDN) phải nộp từ hoạt động sản xuất kinh doanh | G42: C
E43: 1 | F43: Thu nhập chịu thuế (C1 = B14) | G43: C1 | H43: =+H40 -> 0
E44: 2 | F44: Thu nhập miễn thuế | G44: C2
E45: 3 | F45: Chuyển lỗ và bù trừ lãi, lỗ (C3=C3a+C3b) | G45: C3 | H45: =+H46+H47 -> 0
E46: 3.1 | F46: Lỗ từ hoạt động SXKD được chuyển trong kỳ | G46: C3a | H46: =PL_03TN80!$K$22 -> 0
E47: 3.2 | F47: Lỗ từ chuyển nhượng BĐS được bù trừ với lãi của hoạt động SXKD | G47: C3b
E48: 4 | F48: Thu nhập tính thuế (TNTT) (C4=C1-C2-C3) | G48: C4 | H48: =MAX(H43-H44-H46-H47,0) -> 0
E49: 5 | F49: Trích lập quỹ khoa học công nghệ (nếu có) | G49: C5
E50: 6 | F50: TNTT sau khi đã trích lập quỹ khoa học công nghệ (C6=C4-C5=C7+C8+C9) | G50: C6 | H50: =+H48-H49 -> 0
E51: 6.1 | F51: Trong đó: + Thu nhập tính thuế tính theo thuế suất 20% | G51: C7 | H51: =+IF(TTDN!$F$16=20%,H50,0) -> 0
E52: 6.2 | F52: + Thu nhập tính thuế tính theo thuế suất không ưu đãi khác | G52: C8
E53: 6.3 | F53: + Thuế suất không ưu đãi khác (%) | G53: C8a
E54: 7 | F54: Thuế TNDN từ hoạt động SXKD tính theo thuế suất không ưu đãi (C9 =(C7 x 20%) + (C8 x C8a)) | G54: C9 | H54: =+H51*20%+H52*H53 -> 0
E55: 8 | F55: Thuế TNDN được ưu đãi theo Luật thuế TNDN (C10 = C11 + C12 + C13) | G55: C10 | H55: =+SUM(H56:H58) -> 0
E56: 8.1 | F56: Trong đó: + Thuế TNDN chênh lệch do áp dụng mức thuế suất ưu đãi | G56: C11
E57: 8.2 | F57: + Thuế TNDN được miễn trong kỳ | G57: C12
E58: 8.3 | F58: + Thuế TNDN được giảm trong kỳ | G58: C13
E59: 9 | F59: Thuế TNDN được miễn, giảm theo Hiệp định thuế | G59: C14
E60: 10 | F60: Thuế TNDN được miễn, giảm theo từng thời kỳ | G60: C15
E61: 11 | F61: Thuế thu nhập đã nộp ở nước ngoài được trừ trong kỳ tính thuế | G61: C16
E62: 12 | F62: Thuế TNDN phải nộp của hoạt động sản xuất kinh doanh (C17=C9-C10-C14-C15-C16) | G62: C17 | H62: =+H54-H55-H59-H60-H61 -> 0
E63: D | F63: Thuế TNDN phải nộp từ hoạt động chuyển nhượng BĐS | G63: D
E64: 1 | F64: Thu nhập chịu thuế (D1=B15) | G64: D1 | H64: =+H41 -> 0
E65: 2 | F65: Lỗ từ hoạt động chuyển nhượng BĐS được chuyển trong kỳ | G65: D2
E66: 3 | F66: Thu nhập tính thuế (D3=D1-D2) | G66: D3 | H66: =+H64-H65 -> 0
E67: 4 | F67: Trích lập quỹ khoa học công nghệ (nếu có) | G67: D4
E68: 5 | F68: TNTT sau khi đã trích lập quỹ khoa học công nghệ (D5=D3-D4) | G68: D5 | H68: =+H66-H67 -> 0
E69: 6 | F69: Thuế TNDN phải nộp của hoạt động chuyển nhượng BĐS trong kỳ | G69: D6
E70: 7 | F70: Thuế TNDN chênh lệch do áp dụng mức thuế suất ưu đãi đối với thu nhập từ thực hiện dự án đầu tư - kinh doanh nhà ở xã hội để bán, cho thuê, cho thuê mua | G70: D7
E71: 8 | F71: Thuế TNDN của hoạt động chuyển nhượng BĐS còn phải nộp kỳ này (D8=D6-D7) | G71: D8 | H71: =+H69-H70 -> 0
E72: E | F72: Số thuế TNDN phải nộp quyết toán trong kỳ (E=E1+E2+E5) | G72: E | H72: =+H73+H74+H77 -> 0
E73: 1 | F73: Thuế TNDN của hoạt động sản xuất kinh doanh | G73: E1 | H73: =+H62 -> 0
E74: 2 | F74: Thuế TNDN từ hoạt động chuyển nhượng bất động sản (E2=E3+E4) | G74: E2 | H74: =+H75+H76 -> 0
E75: 2.1 | F75: Thuế TNDN từ hoạt động chuyển nhượng bất động sản | G75: E3
E76: 2.2 | F76: Thuế TNDN từ hoạt động chuyển nhượng cơ sở hạ tầng, nhà có thu tiền theo tiến độ | G76: E4
E77: 3 | F77: Thuế TNDN phải nộp khác (nếu có) | G77: E5
E78: 3.1 | F78: Trong đó thuế TNDN từ xử lý Quỹ phát triển khoa học công nghệ | G78: E6
E79: G | F79: Số thuế TNDN đã tạm nộp (G = G1+G2+G3+G4+G5) | G79: G | H79: =+H81+H82+H84+H85+H86 -> 0
E80: 1 | F80: Thuế TNDN đã tạm nộp của hoạt động sản xuất kinh doanh
E81: 1.1 | F81: Thuế TNDN nộp thừa kỳ trước chuyển sang kỳ này | G81: G1 | J81: Điền số thuế TNDN đã nộp thừa năm trước
E82: 1.2 | F82: Thuế TNDN đã tạm nộp trong năm | G82: G2 | J82: Điền số thuế TNDN đã tạm nộp trong năm
E83: 2 | F83: Thuế TNDN đã tạm nộp của hoạt động chuyển nhượng BĐS
E84: 2.1 | F84: Thuế TNDN nộp thừa kỳ trước chuyển sang kỳ này của hoạt động chuyển nhượng BĐS | G84: G3
E85: 2.2 | F85: Thuế TNDN đã tạm nộp trong năm của hoạt động chuyển nhượng BĐS | G85: G4
E86: 2.3 | F86: Thuế TNDN đã tạm nộp các kỳ trước và trong năm quyết toán của hoạt động chuyển nhượng cơ sở hạ tầng, nhà có thu tiền theo tiến độ | G86: G5
E87: H | F87: Chênh lệch giữa số thuế phải nộp và số thuế đã tạm nộp | G87: H | H87: =+H88+H89+H90 -> 0
E88: 1 | F88: Chênh lệch giữa số thuế phải nộp và số thuế đã tạm nộp trong năm của hoạt động sản xuất kinh doanh (H1=E1+E5-G2) | G88: H1 | H88: =+H73+H77-H82 -> 0
E89: 2 | F89: Chênh lệch giữa số thuế phải nộp và số thuế đã tạm nộp trong năm của hoạt động chuyển nhượng BĐS (H2=E3-G4) | G89: H2 | H89: =+H75-H85 -> 0
E90: 3 | F90: Chênh lệch giữa số thuế phải nộp và số thuế đã tạm nộp của hoạt động chuyển nhượng cơ sở hạ tầng, nhà có thu tiền theo tiến độ (H3=E4-G5) | G90: H3 | H90: =+H76-H86 -> 0
E91: I | F91: Số thuế TNDN còn phải nộp đến thời hạn nộp hồ sơ khai quyết toán thuế (I=E-G=I1+I2) | G91: I | H91: =+H92+H93 -> 0
E92: 1 | F92: Thuế TNDN còn phải nộp của hoạt động sản xuất kinh doanh | G92: I1 | H92: =+H73+H77-H81-H82 -> 0
E93: 2 | F93: Thuế TNDN còn phải nộp của hoạt động chuyển nhượng BĐS | G93: I2 | H93: =+H74-H84-H85-H86 -> 0
F95: Tôi cam đoan là các số liệu, tài liệu kê khai này là đúng và tự chịu trách nhiệm trước pháp luật về số liệu, tài liệu đã kê khai./.
G96: ...., ngày ......tháng ...... năm .........
E97: NHÂN VIÊN ĐẠI LÝ THUẾ | G97: NGƯỜI NỘP THUẾ hoặc
E98: Họ và tên:……….. | G98: ĐẠI DIỆN HỢP PHÁP CỦA NGƯỜI NỘP THUẾ
E99: Chứng chỉ hành nghề số:............... | G99: (Ký, ghi rõ họ tên; chức vụ và đóng dấu (nếu có))
G105: =KB_GD -> 0
E106: Ghi chú:
E107: - TNDN: Thu nhập doanh nghiệp

Sheet TNDN03
E6: CỘNG HÒA XÃ HỘI CHỦ NGHĨA VIỆT NAM
E7: Độc lập - Tự do - Hạnh phúc
E8: _____________________
E10: TỜ KHAI QUYẾT TOÁN THUẾ THU NHẬP DOANH NGHIỆP
E11: (Áp dụng đối với phương pháp doanh thu - chi phí)
E12: ="[01] Kỳ tính thuế: từ "&TEXT(DATE(KB_Nam,1,1),"DD/MM/YYYY")&" đến "&TEXT(KB_Den,"DD/MM/YYYY") -> [01] Kỳ tính thuế: từ 01/01/2026 đến 31/12/2026
E13: [02] Lần đầu  [03] Bổ sung lần thứ: 
E14: [04] Ngành nghề có tỷ lệ doanh thu cao nhất:….........................
E15: [05] Tỷ lệ (%): ….............%
E16: ="[06] Tên người nộp thuế : "&KB_CTy -> [06] Tên người nộp thuế :
E17: ="[07] Mã số thuế: "&KB_MST -> [07] Mã số thuế:
E18: [08] Tên tổ chức, cá nhân cung cấp dịch vụ làm thủ tục về thuế (nếu có):................................................
E19: [09] Mã số thuế:……………………………………………………………………………………………………..
E20: [10] Hợp đồng dịch vụ làm thủ tục về thuế: Số:......................................ngày:......................................
H21: Đơn vị tính: đồng Việt Nam
E22: STT | F22: Chỉ tiêu | G22: Mã chỉ tiêu | H22: Số tiền
E23: [1] | F23: [2] | G23: [3] | H23: [4]
E24: A | F24: Kết quả kinh doanh ghi nhận theo báo cáo tài chính | G24: A | H24: =+H25 -> 0
E25: 1 | F25: Tổng lợi nhuận kế toán trước thuế thu nhập doanh nghiệp | G25: A1 | H25: =+PL_03TNDN!$E$34 -> 0
E26: B | F26: Xác định thu nhập chịu thuế theo Luật thuế thu nhập doanh nghiệp | G26: B
E27: 1 | F27: Điều chỉnh tăng tổng lợi nhuận trước thuế thu nhập doanh nghiệp (B1= B2+B3+B4+B5+B6+B7) | G27: B1 | H27: =+H28+H29+H30+H31+H32+H33 -> 0
E28: 1.1 | F28: Các khoản điều chỉnh tăng doanh thu | G28: B2
E29: 1.2 | F29: Chi phí của phần doanh thu điều chỉnh giảm | G29: B3
E30: 1.3 | F30: Các khoản chi không được trừ khi xác định thu nhập chịu thuế | G30: B4
E31: 1.4 | F31: Thuế thu nhập đã nộp cho phần thu nhập nhận được ở nước ngoài | G31: B5
E32: 1.5 | F32: Điều chỉnh tăng lợi nhuận do xác định giá thị trường đối với giao dịch liên kết | G32: B6
E33: 1.6 | F33: Các khoản điều chỉnh làm tăng lợi nhuận trước thuế khác | G33: B7
E34: 2 | F34: Điều chỉnh giảm tổng lợi nhuận trước thuế thu nhập doanh nghiệp (B8=B9+B10+B11+B12) | G34: B8 | H34: =+H35+H36+H37+H38 -> 0
E35: 2.1 | F35: Giảm trừ các khoản doanh thu đã tính thuế năm trước | G35: B9
E36: 2.2 | F36: Chi phí của phần doanh thu điều chỉnh tăng | G36: B10
E37: 2.3 | F37: Chi phí lãi vay không được trừ kỳ trước được chuyển sang kỳ này của doanh nghiệp có giao dịch liên kết | G37: B11
E38: 2.4 | F38: Các khoản điều chỉnh làm giảm lợi nhuận trước thuế khác | G38: B12
F39: Trong đó: Chi phí được trừ bổ sung của hoạt động nghiên cứu và phát triển | G39: B12a
E40: 3 | F40: Tổng thu nhập chịu thuế (B13=A1+B1-B8) | G40: B13 | H40: =+H25+H27-H34 -> 0
E41: 3.1 | F41: Thu nhập chịu thuế từ hoạt động sản xuất kinh doanh | G41: B14 | J41: <= Vui lòng gõ số
E42: 3.2 | F42: Thu nhập chịu thuế từ hoạt động chuyển nhượng BĐS | G42: B15 | H42: =+H40-H41 -> 0
E43: C | F43: Thuế thu nhập doanh nghiệp (TNDN) phải nộp từ hoạt động sản xuất kinh doanh | G43: C
E44: 1 | F44: Thu nhập chịu thuế (C1 = B14) | G44: C1 | H44: =+H41 -> 0
E45: 2 | F45: Thu nhập miễn thuế (Loại thu nhập miễn thuế: …………………………) | G45: C2
E46: 3 | F46: Chuyển lỗ và bù trừ lãi, lỗ (C3=C3a+C3b) | G46: C3 | H46: =+H47+H48 -> 0
E47: 3.1 | F47: Trong đó: + Lỗ từ hoạt động SXKD được chuyển trong kỳ | G47: C3a | H47: =PL_03TNDN!$L$22 -> 0
E48: 3.2 | F48: + Lỗ từ chuyển nhượng BĐS được bù trừ với lãi của hoạt động SXKD | G48: C3b
E49: 4 | F49: Thu nhập tính thuế (TNTT) (C4=C1-C2-C3) | G49: C4 | H49: =MAX(H44-H45-H46,0) -> 0
E50: 5 | F50: Trích lập quỹ khoa học công nghệ (nếu có) | G50: C5
E51: 6 | F51: TNTT sau khi đã trích lập quỹ khoa học công nghệ (C6=C4-C5=C7+C8) | G51: C6 | H51: =+H49-H50 -> 0
E52: 6.1 | F52: Trong đó: + Thu nhập tính thuế áp dụng thuế suất phổ thông | G52: C7 | H52: =+H51-H54 -> 0
E53: 6.2 | F53: + Thuế suất phổ thông (%) | G53: C7a | H53: =TTDN!$F$16 -> 0
E54: 6.3 | F54: + Thu nhập tính thuế tính theo thuế suất không ưu đãi khác | G54: C8
E55: 6.4 | F55: + Thuế suất không ưu đãi khác (%) | G55: C8a
E56: 7 | F56: Thuế TNDN từ hoạt động SXKD tính theo thuế suất không ưu đãi (C9 =(C7 x C7a) + (C8 x C8a)) | G56: C9 | H56: =+H52*H53+H54*H55 -> 0
E57: 8 | F57: Thuế TNDN được ưu đãi theo Luật thuế TNDN (C10 = C11 + C12 + C13) | G57: C10 | H57: =+SUM(H58:H60) -> 0
E58: 8.1 | F58: Trong đó: + Thuế TNDN chênh lệch do áp dụng mức thuế suất ưu đãi | G58: C11
E59: 8.2 | F59: + Thuế TNDN được miễn trong kỳ | G59: C12
E60: 8.3 | F60: + Thuế TNDN được giảm trong kỳ | G60: C13
E61: 9 | F61: Thuế TNDN được miễn, giảm theo Hiệp định thuế | G61: C14
E62: 10 | F62: Thuế TNDN được miễn, giảm theo từng thời kỳ | G62: C15
E63: 11 | F63: Thuế TNDN đã nộp đối với thu nhập ở nước ngoài được trừ trong kỳ tính thuế | G63: C16
E64: 12 | F64: Thuế TNDN phải nộp của hoạt động sản xuất kinh doanh (C17=C9-C10-C14-C15-C16) | G64: C17 | H64: =+H56-H57-H61-H62-H63 -> 0
E65: D | F65: Thuế TNDN phải nộp từ hoạt động chuyển nhượng BĐS | G65: D
E66: 1 | F66: Thu nhập chịu thuế (D1 = B15) | G66: D1 | H66: =+H42 -> 0
E67: 2 | F67: Chuyển lỗ và bù trừ lãi, lỗ (D2=D2a+D2b) | G67: D2 | H67: =+H68+H69 -> 0
E68: 2.1 | F68: Trong đó: + Lỗ từ hoạt động chuyển nhượng BĐS được chuyển trong kỳ | G68: D2a | H68: =PL_03TNDN!$L$30 -> 0
E69: 2.2 | F69: + Lỗ từ hoạt động SXKD được bù trừ với lãi từ chuyển nhượng BĐS | G69: D2b
E70: 3 | F70: Thu nhập tính thuế (D3=D1-D2) | G70: D3 | H70: =+H66-H67 -> 0
E71: 4 | F71: Trích lập quỹ khoa học công nghệ (nếu có) | G71: D4
E72: 5 | F72: TNTT sau khi đã trích lập quỹ khoa học công nghệ (D5=D3-D4) | G72: D5 | H72: =+H70-H71 -> 0
E73: 6 | F73: Thuế TNDN phải nộp của hoạt động chuyển nhượng BĐS trong kỳ | G73: D6
E74: 7 | F74: Thuế TNDN chênh lệch do áp dụng mức thuế suất ưu đãi đối với thu nhập từ thực hiện dự án đầu tư - kinh doanh nhà ở xã hội để bán, cho thuê, cho thuê mua | G74: D7
E75: 8 | F75: Thuế TNDN của hoạt động chuyển nhượng BĐS còn phải nộp kỳ này (D8=D6-D7) | G75: D8 | H75: =+H73-H74 -> 0
E76: E | F76: Số thuế TNDN phải nộp quyết toán trong kỳ (E=E1+E2+E5) | G76: E | H76: =+H77+H78+H81 -> 0
E77: 1 | F77: Thuế TNDN của hoạt động sản xuất kinh doanh | G77: E1 | H77: =+H64 -> 0
E78: 2 | F78: Thuế TNDN từ hoạt động chuyển nhượng BĐS (E2=E3+E4) | G78: E2 | H78: =+H79+H80 -> 0
E79: 2.1 | F79: Thuế TNDN từ hoạt động chuyển nhượng BĐS | G79: E3
E80: 2.2 | F80: Thuế TNDN từ hoạt động chuyển nhượng cơ sở hạ tầng, nhà có thu tiền theo tiến độ | G80: E4
E81: 3 | F81: Thuế TNDN phải nộp khác (nếu có) | G81: E5
E82: 3.1 | F82: Trong đó thuế TNDN từ xử lý Quỹ phát triển khoa học công nghệ | G82: E6
E83: G | F83: Số thuế TNDN đã tạm nộp (G=G1+G2+G3+G4+G5) | G83: G | H83: =+H85+H86+H88+H89+H90 -> 0
E84: 1 | F84: Thuế TNDN đã tạm nộp của hoạt động sản xuất kinh doanh
E85: 1.1 | F85: Thuế TNDN nộp thừa kỳ trước chuyển sang kỳ này | G85: G1 | J85: Điền số thuế TNDN đã nộp thừa năm trước
E86: 1.2 | F86: Thuế TNDN đã tạm nộp trong năm | G86: G2 | J86: Điền số thuế TNDN đã tạm nộp trong năm
E87: 2 | F87: Thuế TNDN đã tạm nộp của hoạt động chuyển nhượng BĐS
E88: 2.1 | F88: Thuế TNDN nộp thừa kỳ trước chuyển sang kỳ này của hoạt động chuyển nhượng BĐS | G88: G3
E89: 2.2 | F89: Thuế TNDN đã tạm nộp trong năm của hoạt động chuyển nhượng BĐS | G89: G4
E90: 2.3 | F90: Thuế TNDN đã tạm nộp các kỳ trước và trong năm quyết toán của hoạt động chuyển nhượng cơ sở hạ tầng, nhà có thu tiền theo tiến độ | G90: G5
E91: H | F91: Chênh lệch giữa số thuế phải nộp và số thuế đã tạm nộp | G91: H | H91: =+H92+H93+H94 -> 0
E92: 1 | F92: Chênh lệch giữa số thuế phải nộp và số thuế đã tạm nộp trong năm của hoạt động sản xuất kinh doanh (H1=E1+E5-G2) | G92: H1 | H92: =+H77+H81-H86 -> 0
E93: 2 | F93: Chênh lệch giữa số thuế phải nộp và số thuế đã tạm nộp trong năm của hoạt động chuyển nhượng BĐS (H2=E3-G4) | G93: H2 | H93: =+H79-H89 -> 0
E94: 3 | F94: Chênh lệch giữa số thuế phải nộp và số thuế đã tạm nộp của hoạt động chuyển nhượng cơ sở hạ tầng, nhà có thu tiền theo tiến độ (H3=E4-G5) | G94: H3 | H94: =+H80-H90 -> 0
E95: I | F95: Số thuế TNDN còn phải nộp đến thời hạn nộp hồ sơ khai quyết toán thuế (I=E-G=I1+I2) | G95: I | H95: =+H96+H97 -> 0
E96: 1 | F96: Thuế TNDN còn phải nộp của hoạt động sản xuất kinh doanh (I1=E1+E5-G1-G2) | G96: I1 | H96: =+H77+H81-H85-H86 -> 0
E97: 2 | F97: Thuế TNDN còn phải nộp của hoạt động chuyển nhượng BĐS (I2=E2-G3-G4-G5) | G97: I2 | H97: =+H78-H88-H89-H90 -> 0
F99: Tôi cam đoan là các số liệu, tài liệu kê khai này là đúng và tự chịu trách nhiệm trước pháp luật về số liệu, tài liệu đã kê khai./.
G100: ...., ngày ......tháng ...... năm .........
E101: NGƯỜI TRỰC TIẾP THỰC HIỆN DỊCH VỤ LÀM THỦ TỤC VỀ THUẾ | G101: NGƯỜI NỘP THUẾ hoặc
E102: Họ và tên:……….. | G102: ĐẠI DIỆN HỢP PHÁP CỦA NGƯỜI NỘP THUẾ
E103: Chứng chỉ nghiệp vụ chuyên môn về thuế số:............... | G103: (Chữ ký, ghi rõ họ tên; chức vụ và đóng dấu (nếu có)/Ký điện tử)
G109: =KB_GD -> 0
E110: Ghi chú:
E111: - TNDN: Thu nhập doanh nghiệp; BĐS: Bất động sản

Sheet PL_03TN80
A1: Phụ lục — 03-1A/TNDN & 03-2/TNDN
A5: PHỤ LỤC | G5: PHỤ LỤC
A6: KẾT QUẢ HOẠT ĐỘNG SẢN XUẤT KINH DOANH | G6: CHUYỂN LỖ
A7: Áp dụng đối với ngành sản xuất, thương mại, dịch vụ (trừ công ty an ninh, quốc phòng) (Kèm theo tờ khai quyết toán thuế thu nhập doanh nghiệp số 03/TNDN) | G7: (Kèm theo tờ khai quyết toán thuế thu nhập doanh nghiệp số 03/TNDN)
A8: ="[01] Kỳ tính thuế: từ "&TEXT(DATE(KB_Nam,1,1),"DD/MM/YYYY")&" đến "&TEXT(KB_Den,"DD/MM/YYYY") -> [01] Kỳ tính thuế: từ 01/01/2026 đến 31/12/2026 | G8: ="[01] Kỳ tính thuế: từ "&TEXT(DATE(KB_Nam,1,1),"DD/MM/YYYY")&" đến "&TEXT(KB_Den,"DD/MM/YYYY") -> [01] Kỳ tính thuế: từ 01/01/2026 đến 31/12/2026
A9: ________________________ | G9: ________________________
A10: ="[02] Tên người nộp thuế: "&KB_CTy -> [02] Tên người nộp thuế: | G10: ="[02] Tên người nộp thuế: "&KB_CTy -> [02] Tên người nộp thuế:
A11: ="[03] Mã số thuế: "&KB_MST -> [03] Mã số thuế: | G11: ="[03] Mã số thuế: "&KB_MST -> [03] Mã số thuế:
D12: Đơn vị tính: đồng Việt Nam | L12: Đơn vị tính: đồng Việt Nam
A13: STT | B13: Chỉ tiêu | C13: Mã chỉ tiêu | D13: Số tiền | G13: STT | H13: Năm phát sinh lỗ | I13: Số lỗ phát sinh | J13: Sỗ lỗ đã chuyển trong các kỳ tính thuế trước | K13: Số lỗ được chuyển trong kỳ tính thuế này | L13: Số lỗ còn được chuyển sang các kỳ tính thuế sau
A14: [1] | B14: [2] | C14: [3] | D14: [4] | G14: [1] | H14: [2] | I14: [3] | J14: [4] | K14: [5] | L14: [6]
B15: Kết quả kinh doanh ghi nhận theo báo cáo tài chính: | G15: I | H15: Lỗ của hoạt động sản xuất kinh doanh được chuyển trong kỳ
A16: 1 | B16: Doanh thu bán hàng và cung cấp dịch vụ | C16: [04] | D16: =KQKD!$H$13 -> 0 | G16: 1 | H16: =KB_Nam-5 -> 2021 | L16: =I16-J16-K16 -> 0
B17: Trong đó: - Doanh thu bán hàng hoá, dịch vụ xuất khẩu | C17: [05] | G17: 2 | H17: =KB_Nam-4 -> 2022 | L17: =I17-J17-K17 -> 0
A18: 2 | B18: Các khoản giảm trừ doanh thu([06]=[07]+[08]+[09]) | C18: [06] | D18: =KQKD!H14 -> 0 | G18: 3 | H18: =KB_Nam-3 -> 2023 | L18: =I18-J18-K18 -> 0
A19: a | B19: Chiết khấu thương mại | C19: [07] | D19: =+VLOOKUP(5211,Bang_CDSPS,6,0) -> 0 | G19: 4 | H19: =KB_Nam-2 -> 2024 | L19: =I19-J19-K19 -> 0
A20: b | B20: Giảm giá hàng bán | C20: [08] | D20: =+VLOOKUP(5212,Bang_CDSPS,6,0) -> 0 | G20: 5 | H20: =KB_Nam-1 -> 2025 | L20: =I20-J20-K20 -> 0
A21: c | B21: Giá trị hàng bán bị trả lại | C21: [09] | D21: =+VLOOKUP(5213,Bang_CDSPS,6,0) -> 0 | L21: =I21-J21-K21 -> 0
A22: 3 | B22: Doanh thu hoạt động tài chính | C22: [10] | D22: =KQKD!$H$19 -> 0 | G22: Tổng cộng [04] | I22: =SUM(I16:I20) -> 0 | J22: =SUM(J16:J20) -> 0 | K22: =SUM(K16:K20) -> 0 | L22: =I22-J22-K22 -> 0
B23: Trong đó: - Doanh thu từ lãi tiền gửi | C23: [11] | D23: =+VLOOKUP(5151,Bang_CDSPS,6,0) -> 0 | G23: II | H23: Lỗ của hoạt động chuyển nhượng bất động sản được chuyển trong kỳ
A24: 4 | B24: Chi phí sản xuất, kinh doanh hàng hoá, dịch vụ ([12]=[13]+[14]+[15]) | C24: [12] | D24: =+D25+D26+D27 -> 0 | G24: 1 | H24: =KB_Nam-5 -> 2021 | L24: =I24-J24-K24 -> 0
A25: a | B25: Giá vốn hàng bán | C25: [13] | D25: =KQKD!$H$16 -> 0 | G25: 2 | H25: =KB_Nam-4 -> 2022 | L25: =I25-J25-K25 -> 0
A26: b | B26: Chi phí bán hàng | C26: [14] | D26: =KQKD!$H$22 -> 0 | G26: 3 | H26: =KB_Nam-3 -> 2023 | L26: =I26-J26-K26 -> 0
A27: c | B27: Chi phí quản lý doanh nghiệp | C27: [15] | D27: =KQKD!$H$23 -> 0 | G27: 4 | H27: =KB_Nam-2 -> 2024 | L27: =I27-J27-K27 -> 0
A28: 5 | B28: Chi phí tài chính | C28: [16] | D28: =KQKD!$H$20 -> 0 | G28: 5 | H28: =KB_Nam-1 -> 2025 | L28: =I28-J28-K28 -> 0
B29: Trong đó: Chi phí lãi tiền vay dùng cho sản xuất, kinh doanh | C29: [17] | D29: =KQKD!$H$21 -> 0
A30: 6 | B30: Lợi nhuận thuần từ hoạt động kinh doanh ([18]=[04]-[06]+[10]-[12]-[16]) | C30: [18] | D30: =+D16-D18+D22-D24-D28 -> 0 | G30: Tổng cộng [05] | I30: =SUM(I24:I28) -> 0 | J30: =SUM(J24:J28) -> 0 | K30: =SUM(K24:K28) -> 0 | L30: =SUM(L15:L29) -> 0
A31: 7 | B31: Thu nhập khác | C31: [19] | D31: =KQKD!$H$25 -> 0
A32: 8 | B32: Chi phí khác | C32: [20] | D32: =KQKD!$H$26 -> 0 | H32: Tôi cam đoan là các số liệu, tài liệu kê khai này là đúng và tự chịu trách nhiệm trước pháp luật về số liệu, tài liệu đã kê khai./.
A33: 9 | B33: Lợi nhuận khác ([21]=[19]-[20]) | C33: [21] | D33: =+D31-D32 -> 0
A34: 10 | B34: Tổng lợi nhuận kế toán trước thuế thu nhập doanh nghiệp ([22]=[18]+[21]) | C34: [22] | D34: =+D30+D33 -> 0 | K34: ...., ngày ......tháng ...... năm .........
G35: NHÂN VIÊN ĐẠI LÝ THUẾ | K35: NGƯỜI NỘP THUẾ hoặc
B36: Tôi cam đoan là các số liệu, tài liệu kê khai này là đúng và tự chịu trách nhiệm trước pháp luật về số liệu, tài liệu đã kê khai./. | G36: Họ và tên:……….. | K36: ĐẠI DIỆN HỢP PHÁP CỦA NGƯỜI NỘP THUẾ
C37: ...., ngày ......tháng ...... năm ......... | G37: Chứng chỉ hành nghề số:............... | K37: (Ký, ghi rõ họ tên; chức vụ và đóng dấu (nếu có))
A38: NHÂN VIÊN ĐẠI LÝ THUẾ | C38: NGƯỜI NỘP THUẾ hoặc
A39: Họ và tên:……….. | C39: ĐẠI DIỆN HỢP PHÁP CỦA NGƯỜI NỘP THUẾ
A40: Chứng chỉ hành nghề số:............... | C40: (Ký, ghi rõ họ tên; chức vụ và đóng dấu (nếu có))
K43: =KB_GD -> 0
C46: =KB_GD -> 0
A47: Ghi chú: | G47: Ghi chú:
B48: - Số liệu tại chỉ tiêu [22] của Phụ lục này được ghi vào chỉ tiêu mã số A1 của Tờ khai quyết toán thuế TNDN của cùng kỳ tính thuế.B54 | H48: - Số liệu chỉ tiêu [04] được tổng hợp vào chỉ tiêu C3a của Tờ khai 03/TNDN
H49: - Số liệu chỉ tiêu [05] được tổng hợp vào chỉ tiêu D2 của Tờ khai 03/TNDN

Sheet PL_03TNDN
B5: PHỤ LỤC | H5: PHỤ LỤC
B6: KẾT QUẢ HOẠT ĐỘNG SẢN XUẤT KINH DOANH | H6: CHUYỂN LỖ
B7: Bảng tính nội bộ để lấy chỉ tiêu A1 của Tờ khai 03/TNDN. TT89 không ban hành phụ lục này. | H7: Mẫu số 03-2/TNDN - (Kèm theo tờ khai quyết toán thuế thu nhập doanh nghiệp số 03/TNDN)
B8: ="[01] Kỳ tính thuế: từ "&TEXT(DATE(KB_Nam,1,1),"DD/MM/YYYY")&" đến "&TEXT(KB_Den,"DD/MM/YYYY") -> [01] Kỳ tính thuế: từ 01/01/2026 đến 31/12/2026 | H8: ="[01] Kỳ tính thuế: từ "&TEXT(DATE(KB_Nam,1,1),"DD/MM/YYYY")&" đến "&TEXT(KB_Den,"DD/MM/YYYY") -> [01] Kỳ tính thuế: từ 01/01/2026 đến 31/12/2026
B9: ________________________ | H9: ________________________
B10: ="[02] Tên người nộp thuế: "&KB_CTy -> [02] Tên người nộp thuế: | H10: ="[02] Tên người nộp thuế: "&KB_CTy -> [02] Tên người nộp thuế:
B11: ="[03] Mã số thuế: "&KB_MST -> [03] Mã số thuế: | H11: ="[03] Mã số thuế: "&KB_MST -> [03] Mã số thuế:
E12: Đơn vị tính: đồng Việt Nam | M12: Đơn vị tính: đồng Việt Nam
B13: STT | C13: Chỉ tiêu | D13: Mã chỉ tiêu | E13: Số tiền | H13: STT | I13: Năm phát sinh lỗ | J13: Số lỗ phát sinh | K13: Sỗ lỗ đã chuyển trong các kỳ tính thuế trước | L13: Số lỗ được chuyển trong kỳ tính thuế này | M13: Số lỗ còn được chuyển sang các kỳ tính thuế sau
B14: [1] | C14: [2] | D14: [3] | E14: [4] | H14: [1] | I14: [2] | J14: [3] | K14: [4] | L14: [5] | M14: [6]
C15: Kết quả kinh doanh ghi nhận theo báo cáo tài chính: | H15: I | I15: Lỗ của hoạt động sản xuất kinh doanh được chuyển trong kỳ
B16: 1 | C16: Doanh thu bán hàng và cung cấp dịch vụ | D16: [04] | E16: =KQKD!$H$13 -> 0 | H16: 1 | I16: =KB_Nam-5 -> 2021 | M16: =J16-K16-L16 -> 0
C17: Trong đó: - Doanh thu bán hàng hoá, dịch vụ xuất khẩu | D17: [05] | H17: 2 | I17: =KB_Nam-4 -> 2022 | M17: =J17-K17-L17 -> 0
B18: 2 | C18: Các khoản giảm trừ doanh thu([06]=[07]+[08]+[09]) | D18: [06] | E18: =KQKD!H14 -> 0 | H18: 3 | I18: =KB_Nam-3 -> 2023 | M18: =J18-K18-L18 -> 0
B19: a | C19: Chiết khấu thương mại | D19: [07] | E19: =+VLOOKUP(5211,Bang_CDSPS,6,0) -> 0 | H19: 4 | I19: =KB_Nam-2 -> 2024 | M19: =J19-K19-L19 -> 0
B20: b | C20: Giảm giá hàng bán | D20: [08] | E20: =+VLOOKUP(5212,Bang_CDSPS,6,0) -> 0 | H20: 5 | I20: =KB_Nam-1 -> 2025 | M20: =J20-K20-L20 -> 0
B21: c | C21: Giá trị hàng bán bị trả lại | D21: [09] | E21: =+VLOOKUP(5213,Bang_CDSPS,6,0) -> 0 | M21: =J21-K21-L21 -> 0
B22: 3 | C22: Doanh thu hoạt động tài chính | D22: [10] | E22: =KQKD!$H$19 -> 0 | H22: Tổng cộng | I22: [04] | J22: =SUM(J16:J20) -> 0 | K22: =SUM(K16:K20) -> 0 | L22: =SUM(L16:L20) -> 0 | M22: =J22-K22-L22 -> 0
C23: Trong đó: - Doanh thu từ lãi tiền gửi | D23: [11] | E23: =+VLOOKUP(5151,Bang_CDSPS,6,0) -> 0 | H23: II | I23: Lỗ của hoạt động chuyển nhượng bất động sản được chuyển trong kỳ
B24: 4 | C24: Chi phí sản xuất, kinh doanh hàng hoá, dịch vụ ([12]=[13]+[14]+[15]) | D24: [12] | E24: =+E25+E26+E27 -> 0 | H24: 1 | I24: =KB_Nam-5 -> 2021 | M24: =J24-K24-L24 -> 0
B25: a | C25: Giá vốn hàng bán | D25: [13] | E25: =KQKD!$H$16 -> 0 | H25: 2 | I25: =KB_Nam-4 -> 2022 | M25: =J25-K25-L25 -> 0
B26: b | C26: Chi phí bán hàng | D26: [14] | E26: =KQKD!$H$22 -> 0 | H26: 3 | I26: =KB_Nam-3 -> 2023 | M26: =J26-K26-L26 -> 0
B27: c | C27: Chi phí quản lý doanh nghiệp | D27: [15] | E27: =KQKD!$H$23 -> 0 | H27: 4 | I27: =KB_Nam-2 -> 2024 | M27: =J27-K27-L27 -> 0
B28: 5 | C28: Chi phí tài chính | D28: [16] | E28: =KQKD!$H$20 -> 0 | H28: 5 | I28: =KB_Nam-1 -> 2025 | M28: =J28-K28-L28 -> 0
C29: Trong đó: Chi phí lãi tiền vay dùng cho sản xuất, kinh doanh | D29: [17] | E29: =KQKD!$H$21 -> 0
B30: 6 | C30: Lợi nhuận thuần từ hoạt động kinh doanh ([18]=[04]-[06]+[10]-[12]-[16]) | D30: [18] | E30: =+E16-E18+E22-E24-E28 -> 0 | H30: Tổng cộng | I30: [05] | J30: =SUM(J24:J28) -> 0 | K30: =SUM(K24:K28) -> 0 | L30: =SUM(L24:L28) -> 0 | M30: =J30-K30-L30 -> 0
B31: 7 | C31: Thu nhập khác | D31: [19] | E31: =KQKD!$H$25 -> 0
B32: 8 | C32: Chi phí khác | D32: [20] | E32: =KQKD!$H$26 -> 0 | I32: Tôi cam đoan là các số liệu, tài liệu kê khai này là đúng và tự chịu trách nhiệm trước pháp luật về số liệu, tài liệu đã kê khai./.
B33: 9 | C33: Lợi nhuận khác ([21]=[19]-[20]) | D33: [21] | E33: =+E31-E32 -> 0
B34: 10 | C34: Tổng lợi nhuận kế toán trước thuế thu nhập doanh nghiệp ([22]=[18]+[21]) | D34: [22] | E34: =+E30+E33 -> 0
C36: Tôi cam đoan là các số liệu, tài liệu kê khai này là đúng và tự chịu trách nhiệm trước pháp luật về số liệu, tài liệu đã kê khai./.
D37: ...., ngày ......tháng ...... năm ......... | L37: ...., ngày ......tháng ...... năm .........
B38: NHÂN VIÊN ĐẠI LÝ THUẾ | D38: NGƯỜI NỘP THUẾ hoặc | H38: NGƯỜI TRỰC TIẾP THỰC HIỆN DỊCH VỤ LÀM THỦ TỤC VỀ THUẾ | L38: NGƯỜI NỘP THUẾ hoặc
B39: Họ và tên:……….. | D39: ĐẠI DIỆN HỢP PHÁP CỦA NGƯỜI NỘP THUẾ | H39: Họ và tên:……….. | L39: ĐẠI DIỆN HỢP PHÁP CỦA NGƯỜI NỘP THUẾ
B40: Chứng chỉ hành nghề số:............... | D40: (Ký, ghi rõ họ tên; chức vụ và đóng dấu (nếu có)) | H40: Chứng chỉ nghiệp vụ chuyên môn về thuế số:............... | L40: (Chữ ký, ghi rõ họ tên; chức vụ và đóng dấu (nếu có)/Ký điện tử)
D46: =KB_GD -> 0 | L46: =KB_GD -> 0
B47: Ghi chú: | H47: Ghi chú:
C48: - Số liệu tại chỉ tiêu [22] của bảng này được ghi vào chỉ tiêu mã số A1 của Tờ khai quyết toán thuế TNDN cùng kỳ. | I48: - Số liệu chỉ tiêu [04] được tổng hợp vào chỉ tiêu C3a và chỉ tiêu D2b của Tờ khai 03/TNDN
I49: - Số liệu chỉ tiêu [05] được tổng hợp vào chỉ tiêu D2a và chỉ tiêu C3b của Tờ khai 03/TNDN

Sheet GDLK
A3: XÁC ĐỊNH VỀ GIAO DỊCH LIÊN KẾT | D3: <== Về Phục Lục 01
A4: Văn bản pháp lý: NĐ 132/2020
A5: Điều 5. Các bên có quan hệ liên kết
A6: KHÁI NIỆM LIÊN KẾT | B6: 1. Các bên có quan hệ liên kết (sau đây viết tắt là “bên liên kết”) là các bên có mối quan hệ thuộc một trong các trường hợp:
B7: a) Một bên tham gia trực tiếp hoặc gián tiếp vào việc điều hành, kiểm soát, góp vốn hoặc đầu tư vào bên kia;
B8: b) Các bên trực tiếp hay gián tiếp cùng chịu sự điều hành, kiểm soát, góp vốn hoặc đầu tư của một bên khác.
A9: TỶ LỆ NẮM GIỮ VỐN TRONG LIÊN KẾT | B9: a) Một doanh nghiệp nắm giữ trực tiếp hoặc gián tiếp ít nhất 25% vốn góp của chủ sở hữu của doanh nghiệp kia;
B10: b) Cả hai doanh nghiệp đều có ít nhất 25% vốn góp của chủ sở hữu do một bên thứ ba nắm giữ trực tiếp hoặc gián tiếp;
B11: c) Một doanh nghiệp là cổ đông lớn nhất về vốn góp của chủ sở hữu và nắm giữ trực tiếp hoặc gián tiếp ít nhất 10% tổng số cổ phần của doanh nghiệp kia;
A12: QUYỀN QUYẾT ĐỊNH KIỂM SOÁT CHI PHỐI VÀO DN LIÊN KẾT | B12: đ) Một doanh nghiệp chỉ định thành viên ban lãnh đạo điều hành hoặc nắm quyền kiểm soát của một doanh nghiệp khác với điều kiện số lượng các thành viên được doanh nghiệp thứ nhất chỉ định chiếm trên 50% tổng số thành viên ban lãnh đạo điều hành hoặc nắm quyền kiểm soát của doanh nghiệp thứ hai; hoặc một thành viên được doanh nghiệp thứ nhất chỉ định có quyền quyết định các chính sách tài chính hoặc hoạt động kinh doanh của doanh nghiệp thứ hai;
B13: e) Hai doanh nghiệp cùng có trên 50% thành viên ban lãnh đạo hoặc cùng có một thành viên ban lãnh đạo có quyền quyết định các chính sách tài chính hoặc hoạt động kinh doanh được chỉ định bởi một bên thứ ba;
B14: g) Hai doanh nghiệp được điều hành hoặc chịu sự kiểm soát về nhân sự, tài chính và hoạt động kinh doanh bởi các cá nhân thuộc một trong các mối quan hệ vợ, chồng; cha mẹ đẻ, cha mẹ nuôi, cha dượng, mẹ kế, cha mẹ vợ, cha mẹ chồng; con đẻ, con nuôi, con riêng của vợ hoặc chồng, con dâu, con rể; anh, chị, em cùng cha mẹ, anh, chị em cùng cha khác mẹ, anh, chị, em cùng mẹ khác cha, anh rể, em rể, chị dâu, em dâu của người cùng cha mẹ hoặc cùng cha khác mẹ, cùng mẹ khác cha; ông bà nội, ông bà ngoại; cháu nội, cháu ngoại; cô, dì, chú, cậu, bác ruột và cháu ruột;
B15: h) Hai cơ sở kinh doanh có mối quan hệ trụ sở chính và cơ sở thường trú hoặc cùng là cơ sở thường trú của tổ chức, cá nhân nước ngoài;
B16: i) Các doanh nghiệp chịu sự kiểm soát của một cá nhân thông qua vốn góp của cá nhân này vào doanh nghiệp đó hoặc trực tiếp tham gia điều hành doanh nghiệp;
B17: k) Các trường hợp khác trong đó doanh nghiệp chịu sự điều hành, kiểm soát, quyết định trên thực tế đối với hoạt động sản xuất kinh doanh của doanh nghiệp kia;
A18: BẢN CHẤT GIAO DỊCH TRONG LIÊN KẾT | B18: l) Doanh nghiệp có phát sinh các giao dịch nhượng, nhận chuyển nhượng vốn góp ít nhất 25% vốn góp của chủ sở hữu của doanh nghiệp trong kỳ tính thuế; vay, cho vay ít nhất 10% vốn góp của chủ sở hữu tại thời điểm phát sinh giao dịch trong kỳ tính thuế với cá nhân điều hành, kiểm soát doanh nghiệp hoặc với cá nhân thuộc trong một các mối quan hệ theo quy định tại điểm g khoản này.
B19: Điều 1. Phạm vi điều chỉnh
B20: 2. Các giao dịch liên kết thuộc phạm vi điều chỉnh của Nghị định này là các giao dịch mua, bán, trao đổi, thuê, cho thuê, mượn, cho mượn, chuyển giao, chuyển nhượng hàng hóa, cung cấp dịch vụ; vay, cho vay, dịch vụ tài chính, đảm bảo tài chính và các công cụ tài chính khác; mua, bán, trao đổi, thuê, cho thuê, mượn, cho mượn, chuyển giao, chuyển nhượng tài sản hữu hình, tài sản vô hình và thỏa thuận mua, bán, sử dụng chung nguồn lực như tài sản, vốn, lao động, chia sẻ chi phí giữa các bên có quan hệ liên kết, trừ các giao dịch kinh doanh đối với hàng hoá, dịch vụ thuộc phạm vi điều chỉnh giá của Nhà nước thực hiện theo quy định của pháp luật về giá.
A27: STT | B27: Phương pháp xác định giá
A28: 1 | B28: PP1: Phương pháp so sánh giá giao dịch liên kết với giá giao dịch độc lập.
A29: 2.1 | B29: PP2-1: Phương pháp so sánh tỷ suất lợi nhuận gộp trên doanh thu (phương pháp giá bán lại).
A30: 2.2 | B30: PP2-2: Phương pháp so sánh tỷ suất lợi nhuận gộp trên giá vốn (phương pháp giá vốn cộng lãi).
A31: 2.3 | B31: PP2-3: Phương pháp so sánh tỷ suất lợi nhuận thuần.
A32: 3 | B32: PP3: Phương pháp phân bổ lợi nhuận giữa các bên liên kết.
A66: HƯỚNG DẪN KÊ KHAI MỤC I | D66: <== Về Phục Lục 01
A68: Chỉ tiêu (1) | B68: STT - Tự nhảy khi chúng ta thêm dòng
A69: Chỉ tiêu (2) | B69: Tên bên liên kết - Bắt buộc nhập, dạng text, tối đa 200 ký tự
A70: Chỉ tiêu (3) | B70: Quốc gia - Bắt buộc nhập, chọn trong danh mục quốc gia
A71: Chỉ tiêu (4) | B71: Mã số thuế - Bắt buộc nhập
B72: Nếu là nước ngoài: không kiểm tra cấu trúc mã số thuế (cho nhập tối đa 200 ký tự)
A73: Chỉ tiêu (5) | B73: Hình thức quan hệ liên kết - Khi khai hình thức liên kết chúng ta tích chọn, chỉ bắt buộc chọn ít nhất 1 loại hình thức quan hệ liên kết và cho phép tích chọn nhiều loại hình thức với mã (A, B, C, D, Đ E, G, H, I, K) tương ứng như sau:
A74: A | B74: Một doanh nghiệp nắm giữ trực tiếp hoặc gián tiếp ít nhất 25% vốn góp của chủ sở hữu của doanh nghiệp kia;
A75: B | B75: Cả hai doanh nghiệp đều có ít nhất 25% vốn góp của chủ sở hữu do một bên thứ ba nắm giữ trực tiếp hoặc gián tiếp;
A76: C | B76: Một doanh nghiệp là cổ đông lớn nhất về vốn góp của chủ sở hữu và nắm giữ trực tiếp hoặc gián tiếp ít nhất 10% tổng số cổ phần của doanh nghiệp kia; | E76: TK 341 của từng khoản vay trên CDPS Vay Và Nợ Thuê Tài Chính | F76: TK 411 trên CDPS Vốn chủ sở hữu | G76: Chỉ tiêu 330 trên CDKT - Tổng khoản vay trung dài hạn trong năm
A77: D | B77: Một doanh nghiệp bảo lãnh hoặc cho một doanh nghiệp khác vay vốn dưới bất kỳ hình thức nào (bao gồm cả các khoản vay từ bên thứ ba được đảm bảo từ nguồn tài chính của bên liên kết và các giao dịch tài chính có bản chất tương tự) với điều kiện khoản vốn vay ít nhất bằng 25% vốn góp của chủ sở hữu của doanh nghiệp đi vay và chiếm trên 50% tổng giá trị các khoản nợ trung và dài hạn của doanh nghiệp đi vay; | D77: TH áp dụng: Vay ngân hàng, Vay tổ chức khác ==> Yêu cầu cập nhật thông tin như bảng bên cạnh để xác định có phải thuộc trường hợp này hay không? | E77: =+VLOOKUP(341,Bang_CDSPS,6,0) -> 0 | F77: =VLOOKUP(411,Bang_CDSPS,8,0) -> 0 | G77: =+CDKT!H115 -> 0
A78: Đ | B78: Một doanh nghiệp chỉ định thành viên ban lãnh đạo điều hành hoặc nắm quyền kiểm soát của một doanh nghiệp khác với điều kiện số lượng các thành viên được doanh nghiệp thứ nhất chỉ định chiếm trên 50% tổng số thành viên ban lãnh đạo điều hành hoặc nắm quyền kiểm soát của doanh nghiệp thứ hai; hoặc một thành viên được doanh nghiệp thứ nhất chỉ định có quyền quyết định các chính sách tài chính hoặc hoạt động kinh doanh của doanh nghiệp thứ hai; | E78: Kết quả | F78: =+IF(SUM(E77:G77)=0,"",IF(AND($E$77>=$F$77*25%,$E$77>$G$77*50%),"Giao dịch liên kết, phải làm phụ lục liên kết","Chưa đủ điều kiện để là giao dịch liên kết"))
A79: E | B79: Hai doanh nghiệp cùng có trên 50% thành viên ban lãnh đạo hoặc cùng có một thành viên ban lãnh đạo có quyền quyết định các chính sách tài chính hoặc hoạt động kinh doanh được chỉ định bởi một bên thứ ba;
A80: G | B80: Hai doanh nghiệp được điều hành hoặc chịu sự kiểm soát về nhân sự, tài chính và hoạt động kinh doanh bởi các cá nhân thuộc một trong các mối quan hệ vợ, chồng; cha mẹ đẻ, cha mẹ nuôi, cha dượng, mẹ kế, cha mẹ vợ, cha mẹ chồng; con đẻ, con nuôi, con riêng của vợ hoặc chồng, con dâu, con rể; anh, chị, em cùng cha mẹ, anh, chị em cùng cha khác mẹ, anh, chị, em cùng mẹ khác cha, anh rể, em rể, chị dâu, em dâu của người cùng cha mẹ hoặc cùng cha khác mẹ, cùng mẹ khác cha; ông bà nội, ông bà ngoại; cháu nội, cháu ngoại; cô, dì, chú, cậu, bác ruột và cháu ruột;
A81: H | B81: Hai cơ sở kinh doanh có mối quan hệ trụ sở chính và cơ sở thường trú hoặc cùng là cơ sở thường trú của tổ chức, cá nhân nước ngoài;
A82: I | B82: Các doanh nghiệp chịu sự kiểm soát của một cá nhân thông qua vốn góp của cá nhân này vào doanh nghiệp đó hoặc trực tiếp tham gia điều hành doanh nghiệp;
A83: K | B83: Các trường hợp khác trong đó doanh nghiệp chịu sự điều hành, kiểm soát, quyết định trên thực tế đối với hoạt động sản xuất kinh doanh của doanh nghiệp kia; | E83: Giá trị giao dịch nhượng, chuyển nhượng vốn góp | F83: Tất cả giá trị vay, cho vay, mượn, cho mượn | G83: TK 411 trên CDPS Vốn chủ sở hữu
A84: L | B84: Doanh nghiệp có phát sinh các giao dịch nhượng, nhận chuyển nhượng vốn góp ít nhất 25% vốn góp của chủ sở hữu của doanh nghiệp trong kỳ tính thuế; vay, cho vay ít nhất 10% vốn góp của chủ sở hữu tại thời điểm phát sinh giao dịch trong kỳ tính thuế với cá nhân điều hành, kiểm soát doanh nghiệp hoặc với cá nhân thuộc trong một các mối quan hệ theo quy định tại điểm g khoản này. | D84: TH áp dụng: Vay, mượn tiền ban quản trị, giám đốc, các cá nhân tại khoản G ==> Yêu cầu cập nhật thông tin như bảng bên cạnh để xác định có phải thuộc trường hợp này hay không? | G84: =+VLOOKUP(411,Bang_CDSPS,8,0) -> 0
E85: Kết quả | F85: =+IF(SUM(E84:G84)=0,"",IF(OR($E$18>=$G$18*25%,$F$18>=$G$18*10%),"Giao dịch liên kết, phải làm phụ lục liên kết","Chưa đủ điều kiện để là giao dịch liên kết"))
A158: HƯỚNG DẪN KÊ KHAI MỤC III | D158: <== Về Phục Lục 01
B177: Lưu ý: chỉ kê khai những khoản có liên quan đến giao dịch liên kết
B179: Chỉ tiêu | D179: Giá trị bán ra cho bên liên kết (giá trị ghi nhận cho GDLK) | E179: Giá trị mua vào cho bên liên kết (giá trị ghi nhận cho GDLK) | F179: Tổng giá trị thu hộ | G179: Tổng giá trị chi hộ
B180: (2) | D180: (3) | E180: (7) | F180: (12a) | G180: (12b)
B181: 1. Hàng hóa | D181: Doanh thu bán hàng hóa trong năm TK 5111
B182: 1.1 Hàng hóa hình thành tài sản cố định
B183: a. Bên liên kết A
B184: b. Bên liên kết B
B185: …
B186: 1.2 Hàng hóa không hình thành tài sản cố định
B187: a. Bên liên kết A
B188: b. Bên liên kết B
B189: …
B190: 2. Dịch vụ | D190: Doanh thu cung cấp dịch vụ trong năm TK 5113
B191: 2.1 Nghiên cứu, phát triển
B192: a. Bên liên kết A
B193: b. Bên liên kết B
B194: …
B195: 2.2 Quảng cáo, tiếp thị
B196: a. Bên liên kết A
B197: b. Bên liên kết B
B198: …
B199: 2.3 Quản lý kinh doanh và tư vấn, đào tạo
B200: a. Bên liên kết A
B201: b. Bên liên kết B
B202: …
... B207: …
B208: 2.4.2 Lãi vay | D208: Doanh thu lãi vay TK 5151 | E208: Chi Phí lãi vay TK 635
B209: a. Bên liên kết A
B210: b. Bên liên kết B
B211: …
B212: 2.5 Dịch vụ khác | F212: Tổng các khoản người nộp thuế chi hộ cho bên liên kết - TK 3388 | G212: Tổng các khoản người nộp thuế thu hộ cho bên liên kết - TK 1388
B213: a. Bên liên kết A
B214: b. Bên liên kết B
B215: …
A312: HƯỚNG DẪN KÊ KHAI MỤC IV | D312: <== Về Phục Lục 01
B314: Chỉ tiêu | C314: Mã số | D314: Năm nay
B315: [1] | C315: [2] | D315: [4]
B316: Trong đó: Chi phí lãi vay | C316: 23 | D316: =+KQKD!H21 -> 0
B317: 10. Lợi nhuận thuần từ hoạt động kinh doanh | C317: 30 | D317: =+KQKD!H24 -> 0
B318: Doanh thu bán hàng hoá, dịch vụ xuất khẩu | E318: <= điền số liệu nếu có phát sinh
B319: Lãi tiền gửi và lãi cho vay | E319: <= điền số liệu nếu có phát sinh
B320: Chi phí lãi vay được trừ trong kỳ | D320: =+IF(D322<0,0,MIN(D322*30%,D316)) -> 0
B321: Chi phí khấu hao phát sinh trong kỳ - TK 214 trong kỳ | D321: =+VLOOKUP(214,Bang_CDSPS,6,0) -> 0
D322: =+D316+D317+D321 -> 0
B323: Nếu chọn 2B mục II hoặc không chọn thì điền thêm bảng dưới
B324: Chi phí lãi vay của các kỳ trước chuyển sang, trong đó: | C324: Mã số | D324: Số tiền
B325: =+"- Phần chi phí lãi vay không được trừ từ năm "&PHU_LUC_01!$Z$5-1&" chuyển sang kỳ tính thuế "&PHU_LUC_01!$Z$5 -> - Phần chi phí lãi vay không được trừ từ năm -1 chuyển sang kỳ tính thuế | C325: 15.1 | E325: <= điền số liệu nếu có phát sinh
B326: =+"- Phần chi phí lãi vay không được trừ từ năm "&PHU_LUC_01!$Z$5-2&" chuyển sang kỳ tính thuế "&PHU_LUC_01!$Z$5 -> - Phần chi phí lãi vay không được trừ từ năm -2 chuyển sang kỳ tính thuế | C326: 15.2 | E326: <= điền số liệu nếu có phát sinh
B327: =+"- Phần chi phí lãi vay không được trừ từ năm "&PHU_LUC_01!$Z$5-3&" chuyển sang kỳ tính thuế "&PHU_LUC_01!$Z$5 -> - Phần chi phí lãi vay không được trừ từ năm -3 chuyển sang kỳ tính thuế | C327: 15.3 | E327: <= điền số liệu nếu có phát sinh
B328: =+"- Phần chi phí lãi vay không được trừ từ năm "&PHU_LUC_01!$Z$5-4&" chuyển sang kỳ tính thuế "&PHU_LUC_01!$Z$5 -> - Phần chi phí lãi vay không được trừ từ năm -4 chuyển sang kỳ tính thuế | C328: 15.4 | E328: <= điền số liệu nếu có phát sinh
B329: =+"- Phần chi phí lãi vay không được trừ từ năm "&PHU_LUC_01!$Z$5-5&" chuyển sang kỳ tính thuế "&PHU_LUC_01!$Z$5 -> - Phần chi phí lãi vay không được trừ từ năm -5 chuyển sang kỳ tính thuế | C329: 15.5 | E329: <= điền số liệu nếu có phát sinh

Sheet PHU_LUC_01
B2: Phụ lục I
B3: (Kèm theo Nghị định số 132/2020/NĐ-CP ngày 05 tháng 11 năm 2020 của Chính phủ)
B4: ________
B5: THÔNG TIN VỀ QUAN HỆ LIÊN KẾT VÀ GIAO DỊCH LIÊN KẾT
B6: (Kèm theo Tờ khai quyết toán thuế thu nhập doanh nghiệp)
B7: Kỳ tính thuế: Từ ...................... đến ........................
B9: =+"[01] Tên người nộp thuế: "&TTDN!F5 -> [01] Tên người nộp thuế:
B10: [02] Mã số thuế: | D10: =+LEFT(KB_MST,1) | E10: =+MID(KB_MST,2,1) | F10: =+MID(KB_MST,3,1) | G10: =+MID(KB_MST,4,1) | H10: =+MID(KB_MST,5,1) | I10: =+MID(KB_MST,6,1) | J10: =+MID(KB_MST,7,1) | K10: =+MID(KB_MST,8,1) | L10: =+MID(KB_MST,9,1) | M10: =+RIGHT(KB_MST,1)
B11: =+"[03] Địa chỉ: "&KB_DC -> [03] Địa chỉ:
B12: [04] Quận/huyện: ......................................................... [05] Tỉnh/thành phố: .........................................................................
B13: [06] Điện thoại: .......................................... [07] Fax: .................................... [08] Email: ...................................................................
B14: [09] Tên đại lý thuế (nếu có): .......................................................................................................................................................
B15: [10] Mã số thuế:
B17: MỤC I. THÔNG TIN VỀ CÁC BÊN LIÊN KẾT
B18: STT | C18: Tên bên liên kết | D18: Quốc gia | I18: Mã số thuế | M18: Hình thức quan hệ liên kết1
B19: 1 | C19: 2 | D19: 3 | I19: 4 | M19: 5
M20: A | N20: B | O20: C | P20: D | Q20: Đ | R20: E | S20: G | T20: H | U20: I | V20: K | W20: L
B21: 1
B22: 2
B23: 3
B24: ....
B26: ----------------------
B27: 1 Người nộp thuế đánh dấu “x” vào cột hình thức quan hệ liên kết kê khai theo quy định tại khoản 2 Điều 5 Nghị định số ......../2020/NĐ-CP ngày ..../.... /2020 của Chính phủ. Trường hợp bên liên kết thuộc nhiều hơn một hình thức quan hệ liên kết, người nộp thuế đánh dấu “x” vào các ô tương ứng.
B29: MỤC II. CÁC TRƯỜNG HỢP ĐƯỢC MIỄN KÊ KHAI, MIỄN LẬP HỒ SƠ XÁC ĐỊNH GIÁ GIAO DỊCH LIÊN KẾT
B30: STT | C30: Trường hợp miễn trừ | S30: Thuộc diện miễn trừ
B31: 1 | C31: 2 | S31: 3 | Z31: Người nộp thuế đánh dấu “x” vào dòng trường hợp miễn trừ áp dụng tương ứng
B32: 1 | C32: Miễn kê khai xác định giá giao dịch liên kết tại mục III, mục IV và được miễn lập Hồ sơ xác định giá giao dịch liên kết | AA32: - Nếu không thuộc trường hợp miễn trừ nào thì bỏ qua không tích chọn.
B33: a | C33: Người nộp thuế chỉ phát sinh giao dịch với các bên liên kết là đối tượng nộp thuế thu nhập doanh nghiệp tại Việt Nam, áp dụng cùng mức thuế suất thuế thu nhập doanh nghiệp với người nộp thuế và không bên nào được hưởng ưu đãi thuế thu nhập doanh nghiệp trong kỳ tính thuế | AA33: - Nếu thuộc trường hợp miễn trừ thì chỉ được chọn 1a hoặc 2a hoặc 2b hoặc 2c. Trường hợp chọn 2c thì bắt buộc phải chọn ít nhất 1 trong 3 loại, hoặc chọn nhiều loại cùng lúc.
B34: 2 | C34: Miễn lập Hồ sơ xác định giá giao dịch liên kết
B35: a | C35: Người nộp thuế có phát sinh giao dịch liên kết nhưng tổng doanh thu phát sinh của kỳ tính thuế dưới 50 tỷ đồng và tổng giá trị tất cả các giao dịch liên kết phát sinh trong kỳ tính thuế dưới 30 tỷ đồng | S35: x
B36: b | C36: Người nộp thuế đã ký kết Thoả thuận trước về phương pháp xác định giá tính thuế thực hiện nộp Báo cáo thường niên theo quy định pháp luật về Thoả thuận trước về phương pháp xác định giá tính thuế
B37: c | C37: Người nộp thuế thực hiện kinh doanh với chức năng đơn giản, không phát sinh doanh thu, chi phí từ hoạt động khai thác, sử dụng tài sản vô hình, có doanh thu dưới 200 tỷ đồng, áp dụng tỷ suất lợi nhuận thuần trước lãi vay và thuế thu nhập doanh nghiệp trên doanh thu, bao gồm các lĩnh vực như sau:
C38: - Phân phối: Từ 5% trở lên
C39: - Sản xuất: Từ 10% trở lên
C40: - Gia công: Từ 15% trở lên
B42: MỤC III. THÔNG TIN XÁC ĐỊNH GIÁ GIAO DỊCH LIÊN KẾT
AU43: Đơn vị tiền: Đồng Việt Nam
B44: STT | C44: Nội dung | D44: Giá trị bán ra cho bên liên kết | T44: Giá trị mua vào từ bên liên kết | AJ44: Lợi nhuận tăng do xác định lại theo giá giao dịch độc lập | AN44: Thu hộ, chi hộ, phân bổ cơ sở thường trú3 | AV44: Giao dịch thuộc phạm vi áp dụng APA4
D45: Giá trị ghi nhận của giao dịch liên kết | H45: Giá trị xác định lại theo giá giao dịch độc lập | L45: Chênh lệch | P45: Phương pháp xác định giá | T45: Giá trị ghi nhận của giao dịch liên kết | X45: Giá trị xác định lại theo giá giao dịch độc lập | AB45: Chênh lệch | AF45: Phương pháp xác định giá | AN45: Tổng giá trị thu hộ | AP45: Tổng giá trị chi hộ | AR45: Tổng giá trị doanh thu phân bổ cho cơ sở thường trú | AT45: Tổng giá trị chi phí phân bổ cho cơ sở thường trú
B46: 1 | C46: 2 | D46: 3 | H46: 4 | L46: (5)=(4)-(3) | P46: 6 | T46: 7 | X46: 8 | AB46: (9)=(8)-(7) | AF46: 10 | AJ46: (11=(5)+(9) | AN46: (12a) | AP46: (12b) | AR46: (12c) | AT46: (12d) | AV46: 13
B47: I | C47: Tổng giá trị giao dịch phát sinh từ hoạt động kinh doanh | D47: =+IF(OR($S$35="x",$S$36="x",$S$37="x"),KQKD!H13+KQKD!H19+KQKD!H25,0) -> 0 | T47: =+IF(OR($S$35="x",$S$36="x",$S$37="x"),KQKD!H16+KQKD!H20+KQKD!H22+KQKD!H23+KQKD!H26,0) -> 0
B48: II | C48: Tổng giá trị giao dịch phát sinh từ hoạt động liên kết | D48: =+D49+D58 -> 0 | H48: =+H49+H58 -> 0 | L48: =+IF(OR($S$35="x",$S$37="x"),0,H48-D48) -> 0 | T48: =+T49+T58 -> 0 | X48: =+X49+X58 -> 0 | AB48: =+IF(OR($S$35="x",$S$37="x"),0,X48-T48) -> 0 | AJ48: =+L48+AB48 -> 0 | AN48: =+AN49+AN58 -> 0 | AP48: =+AP49+AP58 -> 0 | AR48: =+AR49+AR58 -> 0 | AT48: =+AT49+AT58 -> 0
B49: 1 | C49: Hàng hóa | D49: =+D50+D54 -> 0 | H49: =+H50+H54 -> 0 | L49: =+IF(OR($S$35="x",$S$37="x"),0,H49-D49) -> 0 | T49: =+T50+T54 -> 0 | X49: =+X50+X54 -> 0 | AB49: =+IF(OR($S$35="x",$S$37="x"),0,X49-T49) -> 0 | AJ49: =+L49+AB49 -> 0 | AN49: =+AN50+AN54 -> 0 | AP49: =+AP50+AP54 -> 0 | AR49: =+AR50+AR54 -> 0 | AT49: =+AT50+AT54 -> 0
B50: 1.1 | C50: Hàng hóa hình thành tài sản cố định | D50: =+SUM(D51:G53) -> 0 | H50: =+SUM(H51:K53) -> 0 | L50: =+IF(OR($S$35="x",$S$37="x"),0,H50-D50) -> 0 | T50: =+SUM(T51:W53) -> 0 | X50: =+SUM(X51:AA53) -> 0 | AB50: =+IF(OR($S$35="x",$S$37="x"),0,X50-T50) -> 0 | AJ50: =+L50+AB50 -> 0 | AN50: =+SUM(AN51:AO53) -> 0 | AP50: =+SUM(AP51:AQ53) -> 0 | AR50: =+SUM(AR51:AS53) -> 0 | AT50: =+SUM(AT51:AU53) -> 0
B51: a | C51: Bên liên kết A | L51: =+IF(OR($S$35="x",$S$37="x"),0,H51-D51) -> 0 | X51: =+IF(OR($S$35="x",$S$37="x"),0,T51) -> 0 | AB51: =+IF(OR($S$35="x",$S$37="x"),0,X51-T51) -> 0 | AJ51: =+L51+AB51 -> 0
B52: b | C52: Bên liên kết B | L52: =+IF(OR($S$35="x",$S$37="x"),0,H52-D52) -> 0 | X52: =+IF(OR($S$35="x",$S$37="x"),0,T52) -> 0 | AB52: =+IF(OR($S$35="x",$S$37="x"),0,X52-T52) -> 0 | AJ52: =+L52+AB52 -> 0
C53: … | L53: =+IF(OR($S$35="x",$S$37="x"),0,H53-D53) -> 0 | X53: =+IF(OR($S$35="x",$S$37="x"),0,T53) -> 0 | AB53: =+IF(OR($S$35="x",$S$37="x"),0,X53-T53) -> 0 | AJ53: =+L53+AB53 -> 0
B54: 1.2 | C54: Hàng hóa không hình thành tài sản cố định | D54: =+SUM(D55:G57) -> 0 | H54: =+SUM(H55:K57) -> 0 | L54: =+IF(OR($S$35="x",$S$37="x"),0,H54-D54) -> 0 | T54: =+SUM(T55:W57) -> 0 | X54: =+SUM(X55:AA57) -> 0 | AB54: =+IF(OR($S$35="x",$S$37="x"),0,X54-T54) -> 0 | AJ54: =+L54+AB54 -> 0 | AN54: =+SUM(AN55:AO57) -> 0 | AP54: =+SUM(AP55:AQ57) -> 0 | AR54: =+SUM(AR55:AS57) -> 0 | AT54: =+SUM(AT55:AU57) -> 0
B55: a | C55: Bên liên kết A | L55: =+IF(OR($S$35="x",$S$37="x"),0,H55-D55) -> 0 | X55: =+IF(OR($S$35="x",$S$37="x"),0,T55) -> 0 | AB55: =+IF(OR($S$35="x",$S$37="x"),0,X55-T55) -> 0 | AJ55: =+L55+AB55 -> 0
B56: b | C56: Bên liên kết B | L56: =+IF(OR($S$35="x",$S$37="x"),0,H56-D56) -> 0 | X56: =+IF(OR($S$35="x",$S$37="x"),0,T56) -> 0 | AB56: =+IF(OR($S$35="x",$S$37="x"),0,X56-T56) -> 0 | AJ56: =+L56+AB56 -> 0
C57: … | L57: =+IF(OR($S$35="x",$S$37="x"),0,H57-D57) -> 0 | X57: =+IF(OR($S$35="x",$S$37="x"),0,T57) -> 0 | AB57: =+IF(OR($S$35="x",$S$37="x"),0,X57-T57) -> 0 | AJ57: =+L57+AB57 -> 0
B58: 2 | C58: Dịch vụ | D58: =+D59+D63+D67+D71+D80 -> 0 | H58: =+H59+H63+H67+H71+H80 -> 0 | L58: =+IF(OR($S$35="x",$S$37="x"),0,H58-D58) -> 0 | T58: =+T59+T63+T67+T71+T80 -> 0 | X58: =+X59+X63+X67+X71+X80 -> 0 | AB58: =+IF(OR($S$35="x",$S$37="x"),0,X58-T58) -> 0 | AJ58: =+L58+AB58 -> 0 | AN58: =+AN59+AN63+AN67+AN71+AN80 -> 0 | AP58: =+AP59+AP63+AP67+AP71+AP80 -> 0 | AR58: =+AR59+AR63+AR67+AR71+AR80 -> 0 | AT58: =+AT59+AT63+AT67+AT71+AT80 -> 0
B59: 2.1 | C59: Nghiên cứu, phát triển | D59: =+SUM(D60:G62) -> 0 | H59: =+SUM(H60:K62) -> 0 | L59: =+IF(OR($S$35="x",$S$37="x"),0,H59-D59) -> 0 | T59: =+SUM(T60:W62) -> 0 | X59: =+SUM(X60:AA62) -> 0 | AB59: =+IF(OR($S$35="x",$S$37="x"),0,X59-T59) -> 0 | AJ59: =+L59+AB59 -> 0 | AN59: =+SUM(AN60:AO62) -> 0 | AP59: =+SUM(AP60:AQ62) -> 0 | AR59: =+SUM(AR60:AS62) -> 0 | AT59: =+SUM(AT60:AU62) -> 0
B60: a | C60: Bên liên kết A | L60: =+IF(OR($S$35="x",$S$37="x"),0,H60-D60) -> 0 | X60: =+IF(OR($S$35="x",$S$37="x"),0,T60) -> 0 | AB60: =+IF(OR($S$35="x",$S$37="x"),0,X60-T60) -> 0 | AJ60: =+L60+AB60 -> 0
B61: b | C61: Bên liên kết B | L61: =+IF(OR($S$35="x",$S$37="x"),0,H61-D61) -> 0 | X61: =+IF(OR($S$35="x",$S$37="x"),0,T61) -> 0 | AB61: =+IF(OR($S$35="x",$S$37="x"),0,X61-T61) -> 0 | AJ61: =+L61+AB61 -> 0
C62: … | L62: =+IF(OR($S$35="x",$S$37="x"),0,H62-D62) -> 0 | X62: =+IF(OR($S$35="x",$S$37="x"),0,T62) -> 0 | AB62: =+IF(OR($S$35="x",$S$37="x"),0,X62-T62) -> 0 | AJ62: =+L62+AB62 -> 0
B63: 2.2 | C63: Quảng cáo, tiếp thị | D63: =+SUM(D64:G66) -> 0 | H63: =+SUM(H64:K66) -> 0 | L63: =+IF(OR($S$35="x",$S$37="x"),0,H63-D63) -> 0 | T63: =+SUM(T64:W66) -> 0 | X63: =+SUM(X64:AA66) -> 0 | AB63: =+IF(OR($S$35="x",$S$37="x"),0,X63-T63) -> 0 | AJ63: 0 | AN63: =+SUM(AN64:AO66) -> 0 | AP63: =+SUM(AP64:AQ66) -> 0 | AR63: =+SUM(AR64:AS66) -> 0 | AT63: =+SUM(AT64:AU66) -> 0
B64: a | C64: Bên liên kết A | L64: =+IF(OR($S$35="x",$S$37="x"),0,H64-D64) -> 0 | X64: =+IF(OR($S$35="x",$S$37="x"),0,T64) -> 0 | AB64: =+IF(OR($S$35="x",$S$37="x"),0,X64-T64) -> 0 | AJ64: =+L64+AB64 -> 0
B65: b | C65: Bên liên kết B | L65: =+IF(OR($S$35="x",$S$37="x"),0,H65-D65) -> 0 | X65: =+IF(OR($S$35="x",$S$37="x"),0,T65) -> 0 | AB65: =+IF(OR($S$35="x",$S$37="x"),0,X65-T65) -> 0 | AJ65: =+L65+AB65 -> 0
C66: … | L66: =+IF(OR($S$35="x",$S$37="x"),0,H66-D66) -> 0 | X66: =+IF(OR($S$35="x",$S$37="x"),0,T66) -> 0 | AB66: =+IF(OR($S$35="x",$S$37="x"),0,X66-T66) -> 0 | AJ66: =+L66+AB66 -> 0
B67: 2.3 | C67: Quản lý kinh doanh và tư vấn, đào tạo | D67: =+SUM(D68:G70) -> 0 | H67: =+SUM(H68:K70) -> 0 | L67: =+IF(OR($S$35="x",$S$37="x"),0,H67-D67) -> 0 | T67: =+SUM(T68:W70) -> 0 | X67: =+SUM(X68:AA70) -> 0 | AB67: =+IF(OR($S$35="x",$S$37="x"),0,X67-T67) -> 0 | AJ67: =+L67+AB67 -> 0 | AN67: =+SUM(AN68:AO70) -> 0 | AP67: =+SUM(AP68:AQ70) -> 0 | AR67: =+SUM(AR68:AS70) -> 0 | AT67: =+SUM(AT68:AU70) -> 0
B68: a | C68: Bên liên kết A | L68: =+IF(OR($S$35="x",$S$37="x"),0,H68-D68) -> 0 | X68: =+IF(OR($S$35="x",$S$37="x"),0,T68) -> 0 | AB68: =+IF(OR($S$35="x",$S$37="x"),0,X68-T68) -> 0 | AJ68: =+L68+AB68 -> 0
B69: b | C69: Bên liên kết B | L69: =+IF(OR($S$35="x",$S$37="x"),0,H69-D69) -> 0 | X69: =+IF(OR($S$35="x",$S$37="x"),0,T69) -> 0 | AB69: =+IF(OR($S$35="x",$S$37="x"),0,X69-T69) -> 0 | AJ69: =+L69+AB69 -> 0
C70: … | L70: =+IF(OR($S$35="x",$S$37="x"),0,H70-D70) -> 0 | X70: =+IF(OR($S$35="x",$S$37="x"),0,T70) -> 0 | AB70: =+IF(OR($S$35="x",$S$37="x"),0,X70-T70) -> 0 | AJ70: =+L70+AB70 -> 0
B71: 2.4 | C71: Hoạt động tài chính | D71: =+D72+D76 -> 0 | H71: =+H72+H76 -> 0 | L71: =+IF(OR($S$35="x",$S$37="x"),0,H71-D71) -> 0 | T71: =+T72+T76 -> 0 | X71: =+X72+X76 -> 0 | AB71: =+IF(OR($S$35="x",$S$37="x"),0,X71-T71) -> 0 | AJ71: =+L71+AB71 -> 0 | AN71: =+AN72+AN76 -> 0 | AP71: =+AP72+AP76 -> 0 | AR71: =+AR72+AR76 -> 0 | AT71: =+AT72+AT76 -> 0
B72: 2.4.1 | C72: Phí bản quyền và các khoản tương tự | D72: =+SUM(D73:G75) -> 0 | H72: =+SUM(H73:K75) -> 0 | L72: =+IF(OR($S$35="x",$S$37="x"),0,H72-D72) -> 0 | T72: =+SUM(T73:W75) -> 0 | X72: =+SUM(X73:AA75) -> 0 | AB72: =+IF(OR($S$35="x",$S$37="x"),0,X72-T72) -> 0 | AJ72: =+L72+AB72 -> 0 | AN72: =+SUM(AN73:AO75) -> 0 | AP72: =+SUM(AP73:AQ75) -> 0 | AR72: =+SUM(AR73:AS75) -> 0 | AT72: =+SUM(AT73:AU75) -> 0
B73: a | C73: Bên liên kết A | L73: =+IF(OR($S$35="x",$S$37="x"),0,H73-D73) -> 0 | X73: =+IF(OR($S$35="x",$S$37="x"),0,T73) -> 0 | AB73: =+IF(OR($S$35="x",$S$37="x"),0,X73-T73) -> 0 | AJ73: =+L73+AB73 -> 0
B74: b | C74: Bên liên kết B | L74: =+IF(OR($S$35="x",$S$37="x"),0,H74-D74) -> 0 | X74: =+IF(OR($S$35="x",$S$37="x"),0,T74) -> 0 | AB74: =+IF(OR($S$35="x",$S$37="x"),0,X74-T74) -> 0 | AJ74: =+L74+AB74 -> 0
C75: … | L75: =+IF(OR($S$35="x",$S$37="x"),0,H75-D75) -> 0 | X75: =+IF(OR($S$35="x",$S$37="x"),0,T75) -> 0 | AB75: =+IF(OR($S$35="x",$S$37="x"),0,X75-T75) -> 0 | AJ75: =+L75+AB75 -> 0
B76: 2.4.2 | C76: Lãi vay | D76: =+SUM(D77:G79) -> 0 | H76: =+SUM(H77:K79) -> 0 | L76: =+IF(OR($S$35="x",$S$37="x"),0,H76-D76) -> 0 | T76: =+SUM(T77:W79) -> 0 | X76: =+SUM(X77:AA79) -> 0 | AB76: =+IF(OR($S$35="x",$S$37="x"),0,X76-T76) -> 0 | AJ76: =+L76+AB76 -> 0 | AN76: =+SUM(AN77:AO79) -> 0 | AP76: =+SUM(AP77:AQ79) -> 0 | AR76: =+SUM(AR77:AS79) -> 0 | AT76: =+SUM(AT77:AU79) -> 0
B77: a | C77: Bên liên kết A | L77: =+IF(OR($S$35="x",$S$37="x"),0,H77-D77) -> 0 | X77: =+IF(OR($S$35="x",$S$37="x"),0,T77) -> 0 | AB77: =+IF(OR($S$35="x",$S$37="x"),0,X77-T77) -> 0 | AJ77: =+L77+AB77 -> 0
B78: b | C78: Bên liên kết B | L78: =+IF(OR($S$35="x",$S$37="x"),0,H78-D78) -> 0 | X78: =+IF(OR($S$35="x",$S$37="x"),0,T78) -> 0 | AB78: =+IF(OR($S$35="x",$S$37="x"),0,X78-T78) -> 0 | AJ78: =+L78+AB78 -> 0
C79: … | L79: =+IF(OR($S$35="x",$S$37="x"),0,H79-D79) -> 0 | X79: =+IF(OR($S$35="x",$S$37="x"),0,T79) -> 0 | AB79: =+IF(OR($S$35="x",$S$37="x"),0,X79-T79) -> 0 | AJ79: =+L79+AB79 -> 0
B80: 2.5 | C80: Dịch vụ khác | D80: =+SUM(D81:G83) -> 0 | H80: =+SUM(H81:K83) -> 0 | L80: =+IF(OR($S$35="x",$S$37="x"),0,H80-D80) -> 0 | T80: =+SUM(T81:W83) -> 0 | X80: =+SUM(X81:AA83) -> 0 | AB80: =+IF(OR($S$35="x",$S$37="x"),0,X80-T80) -> 0 | AJ80: =+L80+AB80 -> 0 | AN80: =+SUM(AN81:AO83) -> 0 | AP80: =+SUM(AP81:AQ83) -> 0 | AR80: =+SUM(AR81:AS83) -> 0 | AT80: =+SUM(AT81:AU83) -> 0
B81: a | C81: Bên liên kết A | L81: =+IF(OR($S$35="x",$S$37="x"),0,H81-D81) -> 0 | X81: =+IF(OR($S$35="x",$S$37="x"),0,T81) -> 0 | AB81: =+IF(OR($S$35="x",$S$37="x"),0,X81-T81) -> 0 | AJ81: =+L81+AB81 -> 0
B82: b | C82: Bên liên kết B | L82: =+IF(OR($S$35="x",$S$37="x"),0,H82-D82) -> 0 | X82: =+IF(OR($S$35="x",$S$37="x"),0,T82) -> 0 | AB82: =+IF(OR($S$35="x",$S$37="x"),0,X82-T82) -> 0 | AJ82: =+L82+AB82 -> 0
C83: … | L83: =+IF(OR($S$35="x",$S$37="x"),0,H83-D83) -> 0 | X83: =+IF(OR($S$35="x",$S$37="x"),0,T83) -> 0 | AB83: =+IF(OR($S$35="x",$S$37="x"),0,X83-T83) -> 0 | AJ83: =+L83+AB83 -> 0
B84: _________________________
B85: 3 Giá trị phân bổ cho cơ sở thường trú cần kê khai và chú thích rõ là phân bổ doanh thu hay chi phí cho cơ sở thường trú.
B86: 4 Người nộp thuế kê khai “x” đối với giao dịch thuộc phạm vi áp dụng APA và “không” đối với giao dịch không thuộc phạm vi áp dụng APA.
B88: MỤC IV. KẾT QUẢ SẢN XUẤT KINH DOANH SAU KHI XÁC ĐỊNH GIÁ GIAO DỊCH LIÊN KẾT
B90: 1. Dành cho người nộp thuế thuộc các ngành sản xuất, thương mại, dịch vụ
B91: Người nộp thuế đã ký thỏa thuận trước về phương pháp xác định giá tính thuế (APA) | P91: Có □ | T91: Không □ | Z91: - Nếu đã tích chọn vào phần 1 ở mục II thì chúng ta không phải kê khai mục này.
W92: Đơn vị tiền: Đồng Việt Nam
B93: STT | C93: Chỉ tiêu | H93: Giá trị giao dịch liên kết | P93: Giá trị giao dịch với các bên độc lập | T93: Tổng giá trị phát sinh từ hoạt động kinh doanh trong kỳ | Z93: - Nếu đã chọn 2a tại Mục II thì copy số liệu như bên sheet "Mục IV", file tự lấy số liệu.
H94: Giá trị xác định theo Hồ sơ xác định giá giao dịch liên kết | L94: Giá trị xác định giá theo APA | Z94: - Nếu đã chọn 2b tại Mục II thì bắt buộc chọn Có/Không tại mục "Người nộp thuế đã ký thoả thuận trước về phương pháp xác định giá tính thuế (APA)"
B95: 1 | C95: 2 | H95: 3 | L95: 4 | P95: 5 | T95: (6)=(3)+(4)+(5)
B96: 1 | C96: Doanh thu bán hàng và cung cấp dịch vụ | H96: =+IF($S$33="x","",IF(OR($S$35="x",$S$37="x"),0,0)) -> 0 | L96: =+IF($S$33="x","",IF(OR($S$35="x",$S$37="x"),0,0)) -> 0 | P96: =+IF($S$33="x","",IF(OR($S$35="x",$S$37="x"),0,KQKD!H13)) -> 0 | T96: =+IF($S$33="x",0,IF(OR($S$35="x",$S$36="x",$S$37="x"),KQKD!H13,0)) -> 0
C97: Trong đó: Doanh thu bán hàng hóa, dịch vụ xuất khẩu | H97: =+IF($S$33="x","",IF(OR($S$35="x",$S$37="x"),0,0)) -> 0 | L97: =+IF($S$33="x","",IF(OR($S$35="x",$S$37="x"),0,0)) -> 0 | P97: =+IF($S$33="x","",IF(OR($S$35="x",$S$37="x"),0,GDLK!D318)) -> 0 | T97: =+IF($S$33="x",0,IF(OR($S$35="x",$S$36="x",$S$37="x"),GDLK!D318,0)) -> 0
B98: 2 | C98: Các khoản giảm trừ doanh thu | H98: =+IF($S$33="x","",IF(OR($S$35="x",$S$37="x"),0,0)) -> 0 | L98: =+IF($S$33="x","",IF(OR($S$35="x",$S$37="x"),0,0)) -> 0 | P98: =+IF($S$33="x","",IF(OR($S$35="x",$S$37="x"),0,KQKD!H14)) -> 0 | T98: =+IF($S$33="x",0,IF(OR($S$35="x",$S$36="x",$S$37="x"),KQKD!H14,0)) -> 0
B99: 3 | C99: Doanh thu thuần về bán hàng và cung cấp dịch vụ (3)=(1)-(2) | H99: =+IF($S$33="x","",IF(OR($S$35="x",$S$37="x"),0,H96-H98)) -> 0 | L99: =+IF($S$33="x","",IF(OR($S$35="x",$S$37="x"),0,L96-L98)) -> 0 | P99: =+IF($S$33="x","",IF(OR($S$35="x",$S$37="x"),0,P96-P98)) -> 0 | T99: =+T96-T98 -> 0
B100: 4 | C100: Giá vốn hàng bán | H100: =+IF($S$33="x","",IF(OR($S$35="x",$S$37="x"),0,0)) -> 0 | L100: =+IF($S$33="x","",IF(OR($S$35="x",$S$37="x"),0,0)) -> 0 | P100: =+IF($S$33="x","",IF(OR($S$35="x",$S$37="x"),0,KQKD!H16)) -> 0 | T100: =+IF($S$33="x",0,IF(OR($S$35="x",$S$36="x",$S$37="x"),KQKD!H16,0)) -> 0
B101: 5 | C101: Lợi nhuận gộp về bán hàng và cung cấp dịch vụ (5)=(3)-(4) | H101: =+IF($S$33="x","",IF(OR($S$35="x",$S$37="x"),0,H99-H100)) -> 0 | L101: =+IF($S$33="x","",IF(OR($S$35="x",$S$37="x"),0,L99-L100)) -> 0 | P101: =+IF($S$33="x","",IF(OR($S$35="x",$S$37="x"),0,P99-P100)) -> 0 | T101: =+T99-T100 -> 0
B102: 6 | C102: Chi phí bán hàng | H102: =+IF($S$33="x","",IF(OR($S$35="x",$S$37="x"),0,0)) -> 0 | L102: =+IF($S$33="x","",IF(OR($S$35="x",$S$37="x"),0,0)) -> 0 | P102: =+IF($S$33="x","",IF(OR($S$35="x",$S$37="x"),0,KQKD!H22)) -> 0 | T102: =+IF($S$33="x",0,IF(OR($S$35="x",$S$36="x",$S$37="x"),KQKD!H22,0)) -> 0
B103: 7 | C103: Chi phí quản lý doanh nghiệp | H103: =+IF($S$33="x","",IF(OR($S$35="x",$S$37="x"),0,0)) -> 0 | L103: =+IF($S$33="x","",IF(OR($S$35="x",$S$37="x"),0,0)) -> 0 | P103: =+IF($S$33="x","",IF(OR($S$35="x",$S$37="x"),0,KQKD!H23)) -> 0 | T103: =+IF($S$33="x",0,IF(OR($S$35="x",$S$36="x",$S$37="x"),KQKD!H23,0)) -> 0
B104: 8 | C104: Doanh thu hoạt động tài chính | H104: =+IF($S$33="x","",IF(OR($S$35="x",$S$37="x"),0,0)) -> 0 | L104: =+IF($S$33="x","",IF(OR($S$35="x",$S$37="x"),0,0)) -> 0 | P104: =+IF($S$33="x","",IF(OR($S$35="x",$S$37="x"),0,0)) -> 0 | T104: =+IF($S$33="x",0,IF(OR($S$35="x",$S$36="x",$S$37="x"),KQKD!H19,0)) -> 0
B105: 8.1 | C105: Trong đó: Lãi tiền gửi và lãi cho vay | H105: =+IF($S$33="x","",IF(OR($S$35="x",$S$37="x"),0,0)) -> 0 | L105: =+IF($S$33="x","",IF(OR($S$35="x",$S$37="x"),0,0)) -> 0 | P105: =+IF($S$33="x","",IF(OR($S$35="x",$S$37="x"),0,0)) -> 0 | T105: =+IF($S$33="x",0,IF(OR($S$35="x",$S$36="x",$S$37="x"),GDLK!D319,0)) -> 0
B106: 9 | C106: Chi phí tài chính | H106: =+IF($S$33="x","",IF(OR($S$35="x",$S$37="x"),0,0)) -> 0 | L106: =+IF($S$33="x","",IF(OR($S$35="x",$S$37="x"),0,0)) -> 0 | P106: =+IF($S$33="x","",IF(OR($S$35="x",$S$37="x"),0,0)) -> 0 | T106: =+IF($S$33="x",0,IF(OR($S$35="x",$S$36="x",$S$37="x"),KQKD!H20,0)) -> 0
B107: 9.1 | C107: Trong đó: Chi phí lãi vay | H107: =+IF($S$33="x","",IF(OR($S$35="x",$S$37="x"),0,0)) -> 0 | L107: =+IF($S$33="x","",IF(OR($S$35="x",$S$37="x"),0,0)) -> 0 | P107: =+IF($S$33="x","",IF(OR($S$35="x",$S$37="x"),0,0)) -> 0 | T107: =+IF($S$33="x",0,IF(OR($S$35="x",$S$36="x",$S$37="x"),KQKD!H21,0)) -> 0
B108: 9.1.a | C108: Chi phí lãi vay được trừ trong kỳ | H108: =+IF($S$33="x","",IF(OR($S$35="x",$S$37="x"),0,0)) -> 0 | L108: =+IF($S$33="x","",IF(OR($S$35="x",$S$37="x"),0,0)) -> 0 | P108: =+IF($S$33="x","",IF(OR($S$35="x",$S$37="x"),0,0)) -> 0 | T108: =+IF($S$33="x",0,IF(OR($S$35="x",$S$36="x",$S$37="x"),GDLK!D320,0)) -> 0
...

Sheet 05QTT
E5: CỘNG HÒA XÃ HỘI CHỦ NGHĨA VIỆT NAM
E6: Độc lập - Tự do - Hạnh phúc
E7: _____________________
E9: TỜ KHAI QUYẾT TOÁN THUẾ THU NHẬP CÁ NHÂN
E10: (Áp dụng đối với tổ chức, cá nhân trả thu nhập chịu thuế từ tiền lương, tiền công)
E11: ="[01] Kỳ tính thuế: Năm "&YEAR(KB_Den) -> [01] Kỳ tính thuế: Năm 2026
E12: [02] Lần đầu [ ] [03] Bổ sung lần thứ: …
E13: [04] Tổ chức có quyết toán thuế theo uỷ quyền của cá nhân được điều chuyển từ tổ chức cũ đến tổ chức mới do sáp nhập, hợp nhất, chia, tách, chuyển đổi loại hình doanh nghiệp hoặc điều chuyển trong cùng hệ thống: [ ]
E14: ="[05] Tên người nộp thuế: "&KB_CTy -> [05] Tên người nộp thuế:
E15: ="[06] Mã số thuế: "&KB_MST -> [06] Mã số thuế:
E16: ="[07] Địa chỉ: "&KB_DC -> [07] Địa chỉ:
E17: ="[08] Xã/Phường/Đặc khu: [09] Tỉnh/thành phố: "&KB_TTP -> [08] Xã/Phường/Đặc khu: [09] Tỉnh/thành phố:
E18: ="[10] Điện thoại: "&KB_DT&" [11] Email: "&KB_Email -> [10] Điện thoại: [11] Email:
E19: [12] Tên tổ chức, cá nhân cung cấp dịch vụ làm thủ tục về thuế (nếu có):..................................................
E20: [13] Mã số thuế:……………………………………………………………………………………………………………
E21: [14] Hợp đồng dịch vụ làm thủ tục về thuế: Số:........................ngày:.................................................
E22: I. NGHĨA VỤ KHẤU TRỪ THUẾ CỦA TỔ CHỨC, CÁ NHÂN TRẢ THU NHẬP
I23: Đơn vị tiền: Đồng Việt Nam
E24: STT | F24: Chỉ tiêu | G24: Mã chỉ tiêu | H24: Đơn vị tính | I24: Số người/Số tiền
E25: [1] | F25: [2] | G25: [3] | H25: [4] | I25: [5]
E26: 1 | F26: Tổng số người lao động: | G26: [15] | H26: Người | I26: =COUNTA(PL_051!$C$23:$C$24)+COUNTA(PL_052!$C$20:$C$21) -> 0
F27: Trong đó: Cá nhân cư trú có hợp đồng lao động | G27: [16] | H27: Người | I27: =COUNTA(PL_051!$C$23:$C$24) -> 0
E28: 2 | F28: Tổng số cá nhân đã khấu trừ thuế [17]=[18]+[19] | G28: [17] | H28: Người | I28: =+I29+I30 -> 0
E29: 2.1 | F29: Cá nhân cư trú | G29: [18] | H29: Người | I29: =COUNTIF(PL_051!$P$23:$P$24,">0") -> 0
E30: 2.2 | F30: Cá nhân không cư trú | G30: [19] | H30: Người | I30: =COUNTIF(PL_052!$K$20:$K$21,">0") -> 0
E31: 3 | F31: Tổng số cá nhân thuộc diện được miễn, giảm thuế theo Hiệp định tránh đánh thuế hai lần | G31: [20] | H31: Người | I31: =COUNTIF(PL_051!$I$23:$I$24,">0") -> 0
E32: 4 | F32: Tổng số cá nhân giảm trừ gia cảnh | G32: [21] | H32: Người | I32: =PL_051!J25 -> 0
E33: 5 | F33: Tổng thu nhập chịu thuế trả cho cá nhân [22]=[23]+[24] | G33: [22] | H33: VNĐ | I33: =+I34+I35 -> 0
E34: 5.1 | F34: Cá nhân cư trú | G34: [23] | H34: VNĐ | I34: =PL_051!G25 -> 0
E35: 5.2 | F35: Cá nhân không cư trú | G35: [24] | H35: VNĐ | I35: =PL_052!G22 -> 0
E36: 5.3 | F36: Trong đó: Tổng thu nhập chịu thuế từ tiền phí mua bảo hiểm nhân thọ, bảo hiểm không bắt buộc khác của doanh nghiệp bảo hiểm không thành lập tại Việt Nam cho người lao động | G36: [25] | H36: VNĐ
E37: 6 | F37: Tổng thu nhập được miễn trong kỳ [26]=[27]+[28]+[29] | G37: [26] | H37: VNĐ | I37: =+I38+I39+I40 -> 0
E38: 6.1 | F38: Theo quy định của Hợp đồng dầu khí | G38: [27] | H38: VNĐ
E39: 6.2 | F39: Từ thực hiện nhiệm vụ khoa học, công nghệ và đổi mới sáng tạo | G39: [28] | H39: VNĐ
E40: 6.3 | F40: Thu nhập của chuyên gia hỗ trợ khởi nghiệp sáng tạo | G40: [29] | H40: VNĐ
E41: 7 | F41: Tổng thu nhập chịu thuế trả cho cá nhân thuộc diện phải khấu trừ thuế [30]=[31]+[32] | G41: [30] | H41: VNĐ | I41: =+I42+I43 -> 0
E42: 7.1 | F42: Cá nhân cư trú | G42: [31] | H42: VNĐ | I42: =SUMIFS(PL_051!$G$23:$G$24,PL_051!$P$23:$P$24,">0") -> 0
E43: 7.2 | F43: Cá nhân không cư trú | G43: [32] | H43: VNĐ | I43: =SUMIFS(PL_052!$G$20:$G$21,PL_052!$K$20:$K$21,">0") -> 0
E44: 8 | F44: Tổng số thuế thu nhập cá nhân đã khấu trừ [33]=[34]+[35] | G44: [33] | H44: VNĐ | I44: =+I45+I46 -> 0
E45: 8.1 | F45: Cá nhân cư trú | G45: [34] | H45: VNĐ | I45: =PL_051!P25 -> 0
E46: 8.2 | F46: Cá nhân không cư trú | G46: [35] | H46: VNĐ | I46: =PL_052!K22 -> 0
E47: 8.3 | F47: Trong đó: Tổng số thuế thu nhập cá nhân đã khấu trừ trên tiền phí mua bảo hiểm nhân thọ, bảo hiểm không bắt buộc khác của doanh nghiệp bảo hiểm không thành lập tại Việt Nam cho người lao động | G47: [36] | H47: VNĐ
E49: II. NGHĨA VỤ QUYẾT TOÁN THAY CHO CÁ NHÂN
E50: STT | F50: Chỉ tiêu | G50: Mã chỉ tiêu | H50: Đơn vị tính | I50: Số người/Số tiền
E51: [1] | F51: [2] | G51: [3] | H51: [4] | I51: [5]
E52: 1 | F52: Tổng số cá nhân uỷ quyền cho tổ chức, cá nhân trả thu nhập quyết toán thay | G52: [37] | H52: Người
E53: 2 | F53: Tổng số thuế thu nhập cá nhân đã khấu trừ | G53: [38] | H53: VNĐ
F54: Trong đó: Số thuế thu nhập cá nhân đã khấu trừ tại tổ chức trước khi điều chuyển (trường hợp có đánh dấu vào chỉ tiêu [04]) | G54: [39] | H54: VNĐ
E55: 3 | F55: Tổng số thuế thu nhập cá nhân phải nộp | G55: [40] | H55: VNĐ | I55: =PL_051!R25 -> 0
E56: 4 | F56: Tổng số thuế thu nhập cá nhân được miễn do cá nhân có số thuế còn phải nộp sau ủy quyền quyết toán từ 50.000 đồng trở xuống | G56: [41] | H56: VNĐ
E57: 5 | F57: Tổng số thuế thu nhập cá nhân được miễn của cá nhân là nhân lực công nghiệp công nghệ số chất lượng cao | G57: [42] | H57: VNĐ
E58: 6 | F58: Tổng số thuế thu nhập cá nhân được miễn của cá nhân là nhân lực công nghệ cao | G58: [43] | H58: VNĐ
E59: 7 | F59: Tổng số thuế thu nhập cá nhân còn phải nộp [44] = ([40]-[38]-[41]-[42]-[43]) > 0 | G59: [44] | H59: VNĐ | I59: =MAX(I55-I53-I56-I57-I58,0) -> 0
E60: 8 | F60: Tổng số thuế thu nhập cá nhân đã nộp thừa [45] = ([40]-[38]-[41]-[42]-[43]) < 0 | G60: [45] | H60: VNĐ | I60: =-MIN(I55-I53-I56-I57-I58,0) -> 0
F62: Tôi cam đoan số liệu khai trên là đúng và chịu trách nhiệm trước pháp luật về những số liệu đã khai./.
G63: ..., ngày ... tháng … năm …
E64: NGƯỜI TRỰC TIẾP THỰC HIỆN DỊCH VỤ LÀM THỦ TỤC VỀ THUẾ | G64: NGƯỜI NỘP THUẾ hoặc
E65: Họ và tên:……….. | G65: ĐẠI DIỆN HỢP PHÁP CỦA NGƯỜI NỘP THUẾ
E66: Chứng chỉ nghiệp vụ chuyên môn về thuế số:............... | G66: (Chữ ký, ghi rõ họ tên; chức vụ và đóng dấu (nếu có)/Xác nhận điện tử/Ký điện tử)
G72: =KB_GD -> 0

Sheet 05KK_89
F1: Khai theo: | G1: quý
F2: =IF($G$1="","","Chọn "&$G$1&" kết chuyển:") -> Chọn quý kết chuyển:
E5: CỘNG HÒA XÃ HỘI CHỦ NGHĨA VIỆT NAM
E6: Độc lập - Tự do - Hạnh phúc
E7: _____________________
E9: TỜ KHAI THUẾ THU NHẬP CÁ NHÂN
E10: (Áp dụng đối với tổ chức, cá nhân trả các khoản thu nhập từ tiền lương, tiền công)
E11: ="[01] Kỳ tính thuế: "&IF('05KK_02KK'!$G$95="tháng","Tháng ","Quý ")&'05KK_02KK'!$G$96&" năm "&YEAR(KB_Den) -> [01] Kỳ tính thuế: Quý III năm 2026
E12: [02] Lần đầu [ ] [03] Bổ sung lần thứ: …
E13: ="[04] Tên người nộp thuế: "&KB_CTy -> [04] Tên người nộp thuế:
E14: ="[05] Mã số thuế: "&KB_MST -> [05] Mã số thuế:
E15: ="[06] Địa chỉ: "&KB_DC -> [06] Địa chỉ:
E16: ="[07] Xã/Phường/Đặc khu: [08] Tỉnh/thành phố: "&KB_TTP -> [07] Xã/Phường/Đặc khu: [08] Tỉnh/thành phố:
E17: ="[09] Điện thoại: "&KB_DT&" [10] Email: "&KB_Email -> [09] Điện thoại: [10] Email:
E18: [11] Mã số thuế:……………………………………………………………………………………………………………
E19: [12] Tên tổ chức, cá nhân cung cấp dịch vụ làm thủ tục về thuế (nếu có):..................................................
E20: [13] Hợp đồng dịch vụ làm thủ tục về thuế: Số:........................ngày:.................................................
E21: [14] Phân bổ thuế do có đơn vị hạch toán phụ thuộc tại địa bàn cấp tỉnh khác nơi có trụ sở chính: [ ]
I22: Đơn vị tiền: Đồng Việt Nam
E23: STT | F23: Chỉ tiêu | G23: Mã chỉ tiêu | H23: Đơn vị tính | I23: Số người/Số tiền
E24: [1] | F24: [2] | G24: [3] | H24: [4] | I24: [5]
E25: 1 | F25: Tổng số người lao động: | G25: [15] | H25: Người | I25: ='05KK_02KK'!I119 -> 1
F26: Trong đó: Cá nhân cư trú có hợp đồng lao động | G26: [16] | H26: Người | I26: ='05KK_02KK'!I120 -> 1
E27: 2 | F27: Tổng số cá nhân đã khấu trừ thuế [17]=[18]+[19] | G27: [17] | H27: Người | I27: =+I28+I29 -> 0
E28: 2.1 | F28: Cá nhân cư trú | G28: [18] | H28: Người | I28: ='05KK_02KK'!I122 -> 0
E29: 2.2 | F29: Cá nhân không cư trú | G29: [19] | H29: Người | I29: ='05KK_02KK'!I123 -> 0
E30: 3 | F30: Tổng thu nhập chịu thuế trả cho cá nhân [20]=[21]+[22] | G30: [20] | H30: VNĐ | I30: =+I31+I32 -> 0
E31: 3.1 | F31: Cá nhân cư trú | G31: [21] | H31: VNĐ | I31: ='05KK_02KK'!I125 -> 0
E32: 3.2 | F32: Cá nhân không cư trú | G32: [22] | H32: VNĐ | I32: ='05KK_02KK'!I126 -> 0
E33: 3.3 | F33: Trong đó: Tổng thu nhập chịu thuế từ tiền phí mua bảo hiểm nhân thọ, bảo hiểm không bắt buộc khác của doanh nghiệp bảo hiểm không thành lập tại Việt Nam cho người lao động | G33: [23] | H33: VNĐ | I33: ='05KK_02KK'!I127 -> 0
E34: 4 | F34: Tổng thu nhập được miễn trong kỳ [24]=[25]+[26]+[27]+[28] | G34: [24] | H34: VNĐ | I34: =+I35+I36+I37+I38 -> 0
E35: 4.1 | F35: Theo quy định của Hợp đồng dầu khí | G35: [25] | H35: VNĐ | I35: ='05KK_02KK'!I128 -> 0
E36: 4.2 | F36: Từ thực hiện nhiệm vụ khoa học, công nghệ và đổi mới sáng tạo | G36: [26] | H36: VNĐ
E37: 4.3 | F37: Thu nhập của chuyên gia hỗ trợ khởi nghiệp sáng tạo theo quy định | G37: [27] | H37: VNĐ
E38: 4.4 | F38: Thu nhập được miễn khác | G38: [28] | H38: VNĐ
E39: 5 | F39: Tổng thu nhập chịu thuế trả cho cá nhân thuộc diện phải khấu trừ thuế [29]=[30]+[31] | G39: [29] | H39: VNĐ | I39: =+I40+I41 -> 0
E40: 5.1 | F40: Cá nhân cư trú | G40: [30] | H40: VNĐ | I40: ='05KK_02KK'!I130 -> 0
E41: 5.2 | F41: Cá nhân không cư trú | G41: [31] | H41: VNĐ | I41: ='05KK_02KK'!I131 -> 0
E42: 6 | F42: Thu nhập tính thuế [32]=[33]+[34] | G42: [32] | H42: VNĐ | I42: =+I43+I44 -> 0
E43: 6.1 | F43: Cá nhân cư trú | G43: [33] | H43: VNĐ
E44: 6.2 | F44: Cá nhân không cư trú | G44: [34] | H44: VNĐ
E45: 7 | F45: Số thuế thu nhập cá nhân phải khấu trừ trong kỳ | G45: [35] | H45: VNĐ
E46: 8 | F46: Số thuế được miễn trong kỳ ([36]=[38]+[40]+[41]) | G46: [36] | H46: VNĐ | I46: =+I48+I50+I51 -> 0
E47: 8.1 | F47: Tổng thu nhập của cá nhân là nhân lực công nghiệp công nghệ số chất lượng cao thuộc trường hợp được miễn thuế | G47: [37] | H47: VNĐ
E48: 8.2 | F48: Số thuế được miễn của cá nhân là nhân lực công nghiệp công nghệ số chất lượng cao | G48: [38] | H48: VNĐ
E49: 8.3 | F49: Tổng thu nhập của cá nhân là nhân lực công nghệ cao thuộc trường hợp được miễn thuế | G49: [39] | H49: VNĐ
E50: 8.4 | F50: Số thuế được miễn của cá nhân là nhân lực công nghệ cao thực hiện hoạt động nghiên cứu và phát triển công nghệ cao hoặc công nghệ chiến lược | G50: [40] | H50: VNĐ
E51: 8.5 | F51: Số thuế được miễn khác theo quy định | G51: [41] | H51: VNĐ
E52: 9 | F52: Tổng số thuế thu nhập cá nhân đã khấu trừ [42]=[43]+[44] | G52: [42] | H52: VNĐ | I52: =+I53+I54 -> 0
E53: 9.1 | F53: Cá nhân cư trú | G53: [43] | H53: VNĐ | I53: ='05KK_02KK'!I133 -> 0
E54: 9.2 | F54: Cá nhân không cư trú | G54: [44] | H54: VNĐ | I54: ='05KK_02KK'!I134 -> 0
E55: 9.3 | F55: Trong đó: Tổng số thuế thu nhập cá nhân đã khấu trừ trên tiền phí mua bảo hiểm nhân thọ, bảo hiểm không bắt buộc khác của doanh nghiệp bảo hiểm không thành lập tại Việt Nam cho người lao động | G55: [45] | H55: VNĐ | I55: ='05KK_02KK'!I135 -> 0
F57: Tôi cam đoan số liệu khai trên là đúng và chịu trách nhiệm trước pháp luật về những số liệu đã khai./.
G58: …, ngày ... tháng … năm ...
E59: NGƯỜI TRỰC TIẾP THỰC HIỆN DỊCH VỤ LÀM THỦ TỤC VỀ THUẾ | G59: NGƯỜI NỘP THUẾ hoặc
E60: Họ và tên:……….. | G60: ĐẠI DIỆN HỢP PHÁP CỦA NGƯỜI NỘP THUẾ
E61: Chứng chỉ nghiệp vụ chuyên môn về thuế số:............... | G61: (Chữ ký, ghi rõ họ tên; chức vụ và đóng dấu (nếu có)/Ký điện tử)
G67: =KB_GD -> 0

Sheet 05KK_02KK
E5: CỘNG HÒA XÃ HỘI CHỦ NGHĨA VIỆT NAM
E6: Độc lập - Tự do - Hạnh phúc
E7: _____________________
E9: TỜ KHAI QUYẾT TOÁN THUẾ THU NHẬP CÁ NHÂN
E10: (Dành cho tổ chức, cá nhân trả thu nhập chịu thuế từ tiền lương, tiền công cho cá nhân)
E11: ="[01] Kỳ tính thuế: năm "&YEAR(KB_Den) -> [01] Kỳ tính thuế: năm 2026
E12: [02] Lần đầu  [03] Bổ sung lần thứ: 
E13: ="[04] Tên người nộp thuế: "&KB_CTy -> [04] Tên người nộp thuế:
E14: ="[05] Mã số thuế: "&KB_MST -> [05] Mã số thuế:
E15: ="[06] Địa chỉ: "&KB_DC -> [06] Địa chỉ:
E16: ="[07] Quận/huyện: [08] Tỉnh/Thành phố: "&KB_TTP -> [07] Quận/huyện: [08] Tỉnh/Thành phố:
E17: ="[09] Điện thoại: "&KB_DT&" [10] Fax: "&KB_Fax&" [11] Email: "&KB_Email -> [09] Điện thoại: [10] Fax: [11] Email:
E18: [12] Tên đại lý thuế (nếu có):.............................................................................................................................................
E19: [13] Mã số thuế:……………………………………………………………………………………………………………
E20: [14] Địa chỉ:...........................................................................................................................................................................
E21: [15] Quận/huyện:..........................................[16] Tỉnh/Thành phố:.................................................................................
E22: [17] Điện thoại:............................................[18] Fax:.................................[19] Email:.......................................................
E23: [20] Hợp đồng đại lý thuế: số:........................ngày:.........................................................................................................
I24: Đơn vị tính: đồng Việt Nam
E25: STT | F25: Chỉ tiêu | G25: Mã chỉ tiêu | H25: Đơn vị tính | I25: Số người/Số tiền
E26: [1] | F26: [2] | G26: [3] | H26: [4] | I26: [5]
E27: 1 | F27: Tổng số người lao động: | G27: [21] | H27: Người | I27: =COUNTA(PL_051!$C$23:$C$24)+COUNTA(PL_052!$C$20:$C$21) -> 0
F28: Trong đó: Cá nhân cư trú có hợp đồng lao động | G28: [22] | H28: Người | I28: =COUNTA(PL_051!$C$23:$C$24) -> 0
E29: 2 | F29: Tổng số cá nhân đã khấu trừ thuế [23]=[24]+[25] | G29: [23] | H29: Người | I29: =I30+I31 -> 0
E30: 2.1 | F30: Cá nhân cư trú | G30: [24] | H30: Người | I30: =COUNTIF(PL_051!$P$23:$P$24,">0") -> 0
E31: 2.2 | F31: Cá nhân không cư trú | G31: [25] | H31: Người | I31: =+COUNTIF(PL_052!$K$20:$K$21,">0") -> 0
E32: 3 | F32: Tổng số cá nhân thuộc diện được miễn, giảm thuế theo Hiệp định tránh đánh thuế hai lần | G32: [26] | H32: Người | I32: =COUNTIF(PL_051!$I$23:$I$24,">0") -> 0
E33: 4 | F33: Tổng số cá nhân giảm trừ gia cảnh | G33: [27] | H33: Người | I33: =PL_051!J25 -> 0
E34: 5 | F34: Tổng thu nhập chịu thuế (TNCT) trả cho cá nhân [28]=[29]+[30] | G34: [28] | H34: VNĐ | I34: =I35+I36 -> 0
E35: 5.1 | F35: Cá nhân cư trú | G35: [29] | H35: VNĐ | I35: =PL_051!G25 -> 0
E36: 5.2 | F36: Cá nhân không cư trú | G36: [30] | H36: VNĐ | I36: =PL_052!G22 -> 0
E37: 6 | F37: Tổng TNCT trả cho cá nhân thuộc diện phải khấu trừ thuế [31]=[32]+[33] | G37: [31] | H37: VNĐ | I37: =I38+I39 -> 0
E38: 6.1 | F38: Cá nhân cư trú | G38: [32] | H38: VNĐ | I38: =+SUMIFS(PL_051!$G$23:$G$24,PL_051!$P$23:$P$24,">0") -> 0
E39: 6.2 | F39: Cá nhân không cư trú | G39: [33] | H39: VNĐ | I39: =SUMIFS(PL_052!$G$20:$G$21,PL_052!$K$20:$K$21,">0") -> 0
E40: 7 | F40: Tổng số thuế thu nhập cá nhân (TNCN) đã khấu trừ [34]=[35]+[36] | G40: [34] | H40: VNĐ | I40: =I41+I42 -> 0
E41: 7.1 | F41: Cá nhân cư trú | G41: [35] | H41: VNĐ | I41: =PL_051!P25 -> 0
E42: 7.2 | F42: Cá nhân không cư trú | G42: [36] | H42: VNĐ | I42: =PL_052!K22 -> 0
E43: 8 | F43: Tổng số thuế được giảm do làm việc tại khu kinh tế [37]=[38]+[39] | G43: [37] | H43: VNĐ | I43: =I44+I45 -> 0
E44: 8.1 | F44: Cá nhân cư trú | G44: [38] | H44: VNĐ | I44: =PL_051!Q25 -> 0
E45: 8.2 | F45: Cá nhân không cư trú | G45: [39] | H45: VNĐ | I45: =PL_052!M22 -> 0
E46: 9 | F46: Tổng TNCT từ tiền phí mua bảo hiểm nhân thọ, bảo hiểm không bắt buộc khác của doanh nghiệp bảo hiểm không thành lập tại Việt Nam cho người lao động | G46: [40] | H46: VNĐ
E47: 10 | F47: Tổng số thuế TNCN đã khấu trừ trên tiền phí mua bảo hiểm nhân thọ, bảo hiểm không bắt buộc khác của doanh nghiệp bảo hiểm không thành lập tại Việt Nam cho người lao động | G47: [41] | H47: VNĐ
E49: II. Nghĩa vụ quyết toán thay cho cá nhân:
E50: STT | F50: Chỉ tiêu | G50: Mã chỉ tiêu | H50: Đơn vị tính | I50: Số người/Số tiền
E51: [1] | F51: [2] | G51: [3] | H51: [4] | I51: [5]
E52: 1 | F52: Tổng số cá nhân uỷ quyền cho tổ chức, cá nhân trả thu nhập quyết toán thay | G52: [42] | H52: Người
E53: 2 | F53: Tổng số thuế TNCN đã khấu trừ | G53: [43] | H53: VNĐ
E54: 3 | F54: Tổng số thuế TNCN phải nộp | G54: [44] | H54: VNĐ
E55: 4 | F55: Tổng số thuế TNCN còn phải nộp NSNN | G55: [45] | H55: VNĐ
E56: 5 | F56: Tổng số thuế TNCN đã nộp thừa | G56: [46] | H56: VNĐ
F58: Tôi cam đoan là các số liệu, tài liệu kê khai này là đúng và tự chịu trách nhiệm trước pháp luật về số liệu, tài liệu đã kê khai./.
G59: ...., ngày ......tháng ...... năm .........
E60: NHÂN VIÊN ĐẠI LÝ THUẾ | G60: NGƯỜI NỘP THUẾ hoặc
E61: Họ và tên:……….. | G61: ĐẠI DIỆN HỢP PHÁP CỦA NGƯỜI NỘP THUẾ
E62: Chứng chỉ hành nghề số:............... | G62: (Ký, ghi rõ họ tên; chức vụ và đóng dấu (nếu có))
G68: =KB_GD -> 0
F95: Khai theo: | G95: quý
F96: =IF($G$95="","","Chọn "&$G$95&" kết chuyển:") -> Chọn quý kết chuyển: | G96: III
E99: CỘNG HÒA XÃ HỘI CHỦ NGHĨA VIỆT NAM
E100: Độc lập - Tự do - Hạnh phúc
E101: _____________________
E103: TK KHẤU TRỪ THUẾ THU NHẬP CÁ NHÂN MẪU 05/KK-TNCN (TT80/2021)
E104: (Áp dụng cho tổ chức, cá nhân trả các khoản thu nhập từ tiền lương, tiền công)
E105: ="[01] Kỳ tính thuế: "&$G$95&" "&$G$96&" năm "&YEAR(KB_Den) -> [01] Kỳ tính thuế: quý III năm 2026
E106: [02] Lần đầu  [03] Bổ sung lần thứ: 
E107: ="[04] Tên người nộp thuế: "&KB_CTy -> [04] Tên người nộp thuế:
E108: ="[05] Mã số thuế: "&KB_MST -> [05] Mã số thuế:
E109: ="[06] Địa chỉ: "&KB_DC -> [06] Địa chỉ:
E110: ="[07] Quận/huyện: [08] Tỉnh/Thành phố: "&KB_TTP -> [07] Quận/huyện: [08] Tỉnh/Thành phố:
